Workbook
Name \0: #REF!
Name \a: #REF!
Name \b: #REF!
Name _____CAR1: #REF!
Name _____CAR2: #REF!
Name _____CAR3: #REF!
Name _____DES1: #REF!
Name _____DES2: #REF!
Name _____NOM01: #REF!
Name _____NOM02: #REF!
Name _____NOM03: #REF!
Name _____NOM1: #REF!
Name _____NOM2: #REF!
Name _____NOM3: #REF!
Name ____CAR1: #REF!
Name ____CAR2: #REF!
Name ____CAR3: #REF!
Name ____DES1: #REF!
Name ____DES2: #REF!
Name ____mo2: '[1]Analisis Hidraulicos'!#REF!
Name ____mo3: '[1]Analisis Hidraulicos'!#REF!
Name ____mo5: '[1]Analisis Hidraulicos'!#REF!
Name ____NOM01: #REF!
Name ____NOM02: #REF!
Name ____NOM03: #REF!
Name ____NOM1: #REF!
Name ____NOM2: #REF!
Name ____NOM3: #REF!
Name ____psi2: '[1]Analisis Hidraulicos'!#REF!
Name ____psi3: '[1]Analisis Hidraulicos'!#REF!
Name ____psi31: '[1]Analisis Hidraulicos'!#REF!
Name ____PSI4: '[2]Analisis Initarios '!#REF!
Name ____sub212: '[3]Analisis Electricos '!$B$466
Name ____sub26: '[3]Analisis Electricos '!$B$534
Name ____sub28: '[3]Analisis Electricos '!$B$330
Name ____sub288: '[3]Analisis Electricos '!$B$500
Name ____sub312: '[3]Analisis Electricos '!$B$432
Name ____sub34: '[3]Analisis Electricos '!$B$398
Name ____sub36: '[3]Analisis Electricos '!$B$364
Name ____sub38: '[3]Analisis Electricos '!$B$568
Name ___CAR1: #REF!
Name ___CAR2: #REF!
Name ___CAR3: #REF!
Name ___DES1: #REF!
Name ___DES2: #REF!
Name ___EST12: #REF!
Name ___mo1: '[4]1'!#REF!
Name ___mo2: '[1]Analisis Hidraulicos'!#REF!
Name ___mo3: '[1]Analisis Hidraulicos'!#REF!
Name ___mo5: '[1]Analisis Hidraulicos'!#REF!
Name ___MOD3: '[4]1'!#REF!
Name ___NOM01: #REF!
Name ___NOM02: #REF!
Name ___NOM03: #REF!
Name ___NOM1: #REF!
Name ___NOM2: #REF!
Name ___NOM3: #REF!
Name ___psi2: '[1]Analisis Hidraulicos'!#REF!
Name ___psi3: '[1]Analisis Hidraulicos'!#REF!
Name ___psi31: '[1]Analisis Hidraulicos'!#REF!

Sheet Tablero indicadores 2026
A1: PROCESOS ADMINISTRATIVOS / SEGURIDAD Y SALUD EN EL TRABAJO
A2: INDICADORES DE GESTION
A3: CODIGO | C3: RE-RH-37-SST | D3: NIVEL DE CLASIFICACIÓN | G3: USO INTERNO (NC2) | K3: VERSION | L3: 0.2
A5: INDICADORES DEL SISTEMA DE GESTION DE SEGURIDAD Y SALUD EN EL TRABAJO AÑO 2026
A6: TIPO DE INDICADOR | B6: NOMBRE INDICADOR | C6: DEFINICION | D6: COMO SE MIDE | F6: FUENTE DE INFORMACIÓN | G6: RESPONSABLE | H6: FRECUENCIA DE MEDICIÓN | I6: UNIDAD | J6: INFORMAR A | K6: INTERPRETACION | L6: META | M6: FORMULA | N6: RESULTADO 2017 | O6: RESULTADO 2018 | P6: RESULTADO 2019 | Q6: RESULTADO 2020 | R6: RESULTADO 2021 | S6: RESULTADO 2022 | T6: RESULTADO 2023 | U6: RESULTADO 2024 | V6: RESULTADO 2025 | W6: RESULTADO 2026
A7: ESTRUCTURA | B7: 1. Política de SST | C7: Divulgación de la política de SST | D7: Documento de la Política de SST firmada, divulgada y fechada. Cumplimiento de requisitos de norma. | F7: Politica SST | G7: Líder Funcional SG SST | H7: Anual | I7: Cumplimiento | J7: Gerencia General, Copasst | K7: El documento de la Política del SST esta firmada, divulgada y fechada. | L7: SI | M7: SI/NO | N7: SI | O7: SI | P7: SI | Q7: SI | R7: SI | S7: SI | T7: SI | U7: SI | V7: SI
A8: ESTRUCTURA | B8: 2. Objetivos y metas | C8: Objetivos y metas de seguridad divulgados | D8: Objetivos y metas de seguridad escritos y divulgados. | F8: SG-SST | G8: Líder Funcional SG SST | H8: Anual | I8: Cumplimiento | J8: Gerencia General, Copasst | K8: Los objetivos y metas de seguridad se encuentran escritos y divulgados. | L8: SI | M8: SI/NO | N8: SI | O8: SI | P8: SI | Q8: SI | R8: SI | S8: SI | T8: SI | U8: SI | V8: SI
A9: ESTRUCTURA | B9: 3. Plan de trabajo anual | C9: Actividades planeadas en el Plan de Trabajo anual en SST | D9: Cumplimiento de elaboración de plan de trabajo anual | F9: SG-SST | G9: Líder Funcional SG SST | H9: Mensual | I9: Cumplimiento | J9: Gerencia General, Copasst | K9: Se establece un plan de trabajo el cual incluye actividades para la gestión de los riesgos | L9: SI | M9: SI/NO | N9: SI | O9: SI | P9: SI | Q9: SI | R9: SI | S9: SI | T9: SI | U9: SI | V9: SI | W9: SI
A10: ESTRUCTURA | B10: 4. Responsabilidades | C10: Asignación de responsabilidades | D10: Evidencia de responsabilidades asignadas | F10: SG-SST | G10: Gerencia General - Líder funcional del SG SST | H10: Anual | I10: Cumplimiento | J10: Gerencia General, Copasst | K10: Se tienen responsabilidades asignadas en los diferentes niveles | L10: SI | M10: SI/NO | N10: SI | O10: SI | P10: SI | Q10: SI | R10: SI | S10: SI | T10: SI | U10: SI | V10: SI
A11: ESTRUCTURA | B11: 5. Recursos | C11: Asignación de recursos | D11: Presupuesto firmado por Gerencia General, donde se asignen los recursos fisicos, humanos, financieros y de otra indole. | F11: Presupuesto | G11: Gerencia General - Líder Funcional del SG SST | H11: Trimestral | I11: Cumplimiento | J11: Gerencia General, Copasst | K11: Se asignan los recursos para la implementación del SGSST | L11: SI | M11: SI/NO | N11: SI | O11: SI | P11: SI | Q11: SI | R11: SI | S11: SI | T11: SI | U11: SI | V11: SI
A12: ESTRUCTURA | B12: 6. Metodologia para identificación de peligros, evaluación y valoración de riesgos e Identificación de peligros y evaluación y valoración de reisgos con riesgos con participación de todos los niveles de la empresa. | C12: Método definido para la identificación de peligros e instrumento para reportar condiciones peligrosas. | D12: Cumplimiento de Método definido para la identificación de peligros. | F12: Procedimiento para la identificación de peligros e instrumento para reporte de condiciones/actos inseguras | G12: Líder Funcional SG SST | H12: Anual | I12: Cumplimiento | J12: Gerencia General, Copasst | K12: Se tiene definido un procedimiento para la identificación de peligros | L12: SI | M12: SI/NO | N12: SI | O12: SI | P12: SI | Q12: SI | R12: SI | S12: SI | T12: SI | U12: SI | V12: SI
A13: ESTRUCTURA | B13: 7. Conformación y funcionamiento del copasst y capacitación de los integrantes | C13: Conformación y Funcionamiento del COPASST | D13: Se cuenta con un COPASST en funcionamiento y con delegación de funciones. | F13: Actas de conformación y funcionamiento | G13: Copasst | H13: Mensual | I13: Cumplimiento | J13: Gerencia General, Copasst | K13: Se tiene definido un COPASST y funciona de acuerdo a la normatividad vigente | L13: SI | M13: SI/NO | N13: SI | O13: SI | P13: SI | Q13: SI | R13: SI | S13: SI | T13: SI | U13: SI | V13: SI | W13: SI
A14: ESTRUCTURA | B14: 8. Documentación | C14: Documentos que soportan el SGSST | D14: Cumplimiento con la documentación del SGSST | F14: SG-SST y soportes | G14: Gerente Líderes del area COPASST Comité de Convivencia laboral Líder funcional de SG SST | H14: Anual | I14: Cumplimiento | J14: Gerencia General, Copasst | K14: Informacion documentada de soportes para el SGSST | L14: SI | M14: SI/NO | N14: SI | O14: SI | P14: SI | Q14: SI | R14: SI | S14: SI | T14: SI | U14: SI | V14: SI
A15: ESTRUCTURA | B15: 9. Diagnostico de condiciones | C15: Procedimiento para efectuar el diagnostico de condiciones de salud de los trabajadores | D15: Evidencia del procedimiento | F15: Procedimiento para realizaciòn de examenes médicos y diagnóstico de las condiciones de salud | G15: Líder funcional del SGSST | H15: Anual | I15: Cumplimiento | J15: Gerencia General, Copasst | K15: Se tiene definido un procedimiento para el diagnóstico de condiciones de salud | L15: SI | M15: SI/NO | N15: SI | O15: SI | P15: SI | Q15: SI | R15: SI | S15: SI | T15: SI | U15: SI | V15: SI
A16: ESTRUCTURA | B16: 10. Plan de emergencias | C16: Existencia de plan de emergencia en las sedes | D16: N° de sedes con plan de emergencia/Nro total de sedes. *100 | F16: Plan de emergencias | G16: Líder Funcional SG SST | H16: Anual | I16: Número | J16: Gerencia General, Copasst | K16: Número de sedes con plan de emergencias | L16: 1 | M16: (8/8)*100 | N16: 0.5 | O16: 1 | P16: 1 | Q16: 1 | R16: 1 | S16: =(6/6)*100% -> 1 | T16: =(7/7) -> 1 | U16: =(8/8) -> 1 | V16: =(8/8) -> 1
A17: ESTRUCTURA | B17: 11. Plan de Capacitación en SST | C17: Documento del plan de capacitación en SST | D17: Evidencia de un plan de capacitacion en SST | F17: Plan de capacitación anual | G17: Líder Funcional SG SST | H17: Mensual | I17: Cumplimiento | J17: Gerencia General, Copasst | K17: Se tiene definido el plan de capacitación en SST | L17: SI | M17: SI/NO | N17: SI | O17: SI | P17: SI | Q17: SI | R17: SI | S17: SI | T17: SI | U17: SI | V17: SI | W17: SI
A18: TIPO DE INDICADOR | B18: NOMBRE INDICADOR | C18: DEFINICION | D18: COMO SE MIDE | F18: FUENTE DE INFORMACIÓN | G18: RESPONSABLE | H18: FRECUENCIA DE MEDICIÓN | I18: UNIDAD | J18: INFORMAR A | K18: INTERPRETACION | L18: META | M18: FORMULA | N18: RESULTADO 2017 | O18: RESULTADO 2018 | P18: RESULTADO 2019 | Q18: RESULTADO 2020 | R18: RESULTADO 2021 | S18: RESULTADO 2022 | T18: RESULTADO 2023 | U18: RESULTADO 2024 | V18: RESULTADO 2025 | W18: RESULTADO 2026
A19: PROCESO | B19: 1. Evaluacion Inicial | C19: Evaluación inicial del SG-SST | D19: SUMATORIA DE PORCENTAJE POR CADA UNO DE LOS ITEMS EVALUADOS QUE SE ENCUENTREN EN AVANZADO / NUMERO DE ITEMS EVALUADOS | F19: EVALUACIÓN INICIAL DEL SGSST | G19: Líder funcional del SGSST | H19: Anual | I19: Porcentaje | J19: Gerencia General, Copasst | K19: 95% de cumplimiento del SG SST | L19: 0.9 | M19: (10+15+19,26+10+5+10) | N19: 0.8025 | O19: 0.82 | P19: 0.9 | Q19: 0.89 | R19: 0.94 | S19: =SUM(10+15+19.5+27.5+10+5+10)% -> 0.97 | T19: =SUM(10+15+19+26+10+5+10)% -> 0.95 | U19: 0.95 | V19: =(8/8) -> 1
A20: PROCESO | B20: 2. Ejecución del plan de trabajo | C20: Ejecución del plan de trabajo en el SGSST | D20: (N° DE ACTIVIDADES DESARROLLADAS EN EL PERIODO EN EL PLAN/NRO DE ACTIVIDADES PROPUESTASEN EL PERIODO EN EL PLAN DE TRABAJO) X 100 | F20: PLAN ANUAL DE TRABAJO EN SST | G20: Líder Funcional SG SST | H20: Semestral | I20: Porcentaje | J20: Gerencia General, Copasst | K20: 58,48% de actividades cumplidas del plan de trabajo | L20: 0.9 | M20: (438/749)*100 | N20: 87.93% | O20: 0.89 | P20: 0.88 | Q20: 0.91 | R20: 0.97 | S20: =182/183 -> 0.99453552 | T20: =(403/703)*100% -> 0.57325747 | U20: 0.638 | V20: =(438/749) -> 0.58477971
A21: PROCESO | B21: 3. Ejecución del plan de capacitaciòn | C21: Capacitaciones realizadas en el año | D21: (N° DE CAPACITACIONES DESARROLLADAS EN EL PERIODOEN EL PLAN/NRO DE CAPACITACIONES PROPUESTAS EN EL PERIODO EN EL PLAN DE CAPACITACIÒN) X 100 | F21: PLAN DE CAPACITACION ANUAL | G21: Líder Funcional SG SST | H21: Semestral | I21: Porcentaje | J21: Gerencia General, Copasst | K21: 55% de capacitaciones realizadas del plan de capacitaciòn anual | L21: 0.9 | M21: (103/186)*100 | N21: 1 | O21: 0.9589 | P21: 0.95 | Q21: 0.9 | R21: 0.96 | S21: =157/157 -> 1 | T21: =(140/140)*100% -> 1 | U21: =(66/156) -> 0.42307692 | V21: =(103/186) -> 0.55376344
A22: PROCESO | B22: 4. Intervención de peligros identificados | C22: Intervención de los peligros identificados | D22: N° TOTAL DE PELIGROS INTERVENIDOS EN EL PERIODO/TOTAL DE PELIGROS IDENTIFICADOS | F22: INSPECCIONES DE SEGURIDAD MATRIZ DE RIESGOS INVESTIGACIONES DE AT REPORTES DEL COPASST | G22: Líder Funcional SG SST | H22: Semestral | I22: Porcentaje | J22: Gerencia General, Copasst | K22: 100% de peligros intervenidos | L22: 0.9 | M22: 7/3*100 | N22: 0.6857 | O22: 0.6857 | P22: 0.39 | Q22: 0.9 | R22: 1 | S22: =14/14 -> 1 | T22: =(5/7) -> 0.71428571 | U22: =(3/7) -> 0.42857143 | V22: =3/7 -> 0.42857143
A23: PROCESO | B23: 5. Condiciones de salud | C23: Evaluación de condiciones de salud y de trabajo | D23: CUMPLIMIENTO DE EVALUACION DE CONDICIONES DE SALUD | F23: EXAMENES MEDICOS, ENCUESTA CONDICIONES DE SALUD, | G23: Líder de Apoyo administrativo del SGSST | H23: Anual | I23: Cumplimiento | J23: Gerencia General, Copasst | K23: Se evaluan las condiciones de salud de los trabajadores | L23: SI | M23: SI/NO | N23: SI | O23: SI | P23: SI | Q23: SI | R23: SI | S23: SI | T23: SI | U23: SI | V23: SI
A24: PROCESO | B24: 6. Acciones preventivas, correctivas y de mejora | C24: Ejecución de acciones preventivas, correctivas y de mejora incluidas las generadas en la investigación de accidentes de trabajo | D24: (N° DE ACCIONES CORREGIDAS EN EL PERIODO/NRO DE ACCIONES ENCONTRADAS EN EL PERIODO) X 100 | F24: SGSST (INDICADORES, AT, EL, MATRIZ DE PELIGROS, AUDITORIA, REVISION POR LA DIRECCION) | G24: Líder Funcional SG SST | H24: Semestral | I24: Porcentaje | J24: Gerencia General, Copasst | K24: 100% acciones corregidas | L24: 0.9 | M24: (13/13)*100 | N24: 71.42% | O24: 71.42% | P24: 0.39 | Q24: 1 | R24: 1 | S24: =14/14 -> 1 | T24: =(6/6)*100% -> 1 | U24: =13/13 -> 1 | V24: =13/13 -> 1
A25: PROCESO | B25: 7. Mediciones ambientales | C25: Ejecución de mediciones ambientales ocupacionales | D25: (MEDICION AMBIENTAL REALIZADA/MEDICIONES AMBIENTALES DETECTADAS)*100 | F25: REGISTRO DE LOS ESTUDIOS AMBIENTALES | G25: Líder Funcional SG SST | H25: Anual | I25: Porcentaje | J25: Gerencia General, Copasst | K25: Ejecución de mediciones ambientales ocupacionales | L25: 0.9 | M25: (3/3)*100 | N25: 0.5 | O25: 0.66 | P25: 1 | Q25: 1 | R25: 1 | S25: 0 | T25: 1 | U25: =3/7 -> 0.42857143 | V25: =3/3 -> 1
A26: PROCESO | B26: 8. Vigilancia epidemiológica | C26: Desarrollo de los programas de vigilancia epidemiologica | D26: (NO. DE TRABAJADORES INTERVENIDOS EN EL SVE / NO. TRABAJADORES A INTERVENIR)*100 | F26: FORMATOS PROPIOS DE CADA SVE | G26: Líder Funcional SG SST | H26: Semestral | I26: Porcentaje | J26: Gerencia General, Copasst | K26: 100% de trabajadores incluidos en los SVE | L26: 0.9 | M26: (17%+53%+59%+68%+57%/5)*100 | N26: 1 | O26: 1 | P26: 1 | Q26: 1 | R26: 1 | S26: =1007/1007 -> 1 | T26: =(1099/1099) -> 1 | U26: =919/1041 -> 0.882805 | V26: =(17%+53%+59%+68%+57%)/5*(1) -> 0.508
A27: PROCESO | B27: 9. Investigación de accidentes, incidentes y enfermedades laborales | C27: Porcentaje de accidentes, incidentes y enfermedades laborales investigados | D27: N° DE AT, IT, EL INVESTIGADOS/NRO DE AT, IT, EL REPORTADOS | F27: REPORTE DE ACCIDENTES/INCIDENTES | G27: Gerente Líderes del area COPASST Comité de Convivencia laboral Líder funcional de SG SST | H27: Semestral | I27: Porcentaje | J27: Gerencia General, Copasst | K27: 100% de investigaciónes realizadas | L27: 0.9 | M27: (2*2)*100 | N27: 1 | O27: 1 | P27: 1 | Q27: 1 | R27: 1 | S27: =6/6 -> 1 | T27: =4/5 -> 0.8 | U27: 1 | V27: =(2/2) -> 1
A28: PROCESO | B28: 10. Plan de accidentalidad | C28: Ejecución del plan de intervención de la accidentalidad | D28: N° DE ACTIVIDADES DESARROLLADAS EN LA INTERVENCIÓN DE LOS RIESGOS PRIORITARIOS/ACTIVIDADES PROPUESTAS PARA LA INTERVENCIÓN DE LOS RIESGOS PRIORITARIOS | F28: ANÁLISIS DE LA ACCIDENTALIDAD INVESTIGACIÓN DE AT REPORTE DE IT, AT, EL | G28: Líderes del area COPASST Comité de Convivencia laboral Líder funcional de SG SST | H28: Semestral | I28: Porcentaje | J28: Gerencia General, Copasst | K28: 100% de actividades cumplidas del plan de intervención de riesgos | L28: 0.9 | M28: (6/6)*100 | N28: 1 | O28: 1 | P28: 1 | Q28: 1 | R28: 1 | S28: =6/6 -> 1 | T28: =4/5 -> 0.8 | U28: =5/5 -> 1 | V28: =(6/6) -> 1
A29: PROCESO | B29: 11. Estadisticas de EL, AT, IT y ausentismo laboral | C29: Registro Estadistico de AT, EL , y ausentismo laboral | D29: CUMPLIMIENTO DE REGISTRO DE ESTADISTICAS | F29: REGISTROS ESTADISTICOS | G29: Líder Funcional SG SST | H29: Trimestral | I29: Cumplimiento | J29: Gerencia General, Copasst | K29: Registro Estadistico realizado | L29: SI | M29: SI/NO | N29: SI | O29: SI | P29: SI | Q29: SI | R29: SI | S29: SI | T29: SI | U29: SI | V29: SI
A30: PROCESO | B30: 12. Plan de emergencias | C30: Ejecucion de los planes de emergencia en las sedes | D30: N° DE SEDES CON PLAN DE EMERGENCIAS / N° TOTAL DE SEDES *100 | F30: Plan de emergencias | G30: Líder Funcional SG SST | H30: Semestral | I30: Número | J30: Gerencia General, Copasst | K30: 100% de sedes con plan de emergencias | L30: 0.9 | M30: (9/12)*100 | N30: 0.5 | O30: 1 | P30: 1 | Q30: 1 | R30: 1 | S30: =7/7 -> 1 | T30: =6/8 -> 0.75 | U30: =8/8 -> 1 | V30: =(9/12) -> 0.75
A31: PROCESO | B31: Simulacros | C31: Procentaje de simulacros realizados | D31: N° DE SIMULACROS REALIZADOS/NRO DE SIMULACROS PROGRAMADOS | F31: PLAN ANUAL DE TRABAJO EN SST | G31: Gerente Jefes de Área COPASST Profesional en Salud Ocupacional, Brigada de emergencias | H31: Semestral | I31: Porcentaje | J31: Gerencia General, Copasst, Brigada de emergencias | K31: 100% de simulacros ejecutados | L31: 0.9 | M31: 1/12*100 | N31: 0.5 | O31: 0.66 | P31: 1 | Q31: 1 | R31: 1 | S31: =4/4 -> 1 | T31: =6/7 -> 0.85714286 | U31: =7/8 -> 0.875 | V31: =(1/12) -> 0.083333333
A32: PROCESO | B32: 13. Conservaciòn de documentos | C32: Evidencia de la conservación de documentos | D32: Conservación de documentos de manera controlada, garantizando que sean legibles, fácilmente identificables y accesibles. protegidos contra daño deterioro o pérdida. | F32: SGSST Y SOPORTES | G32: Líder Funcional SG SST | H32: Anual | I32: Cumplimiento | J32: Gerencia General, Copasst | K32: Se conservan los documentos de manera controlada, garantizando que sean legibles, fácilmente identificables y accesibles. protegidos contra daño. deterioro o pérdida. | L32: SI | M32: SI/NO | N32: SI | O32: SI | P32: SI | Q32: SI | R32: SI | S32: SI | T32: SI | U32: SI | V32: SI
A33: PROCESO | B33: 14.Riesgos de seguridad vial identeificados | C33: Verificar la cantidad de riesgos identificados al inicio del año vs final del año | D33: CANTIDAD DE RIESGOS IDENTIFICADOS AL FINAL DEL AÑO - CANTIDAD DE RIESGOS IDENTIFICADOS AL INICIO DEL AÑO | F33: PESV | G33: Líder Funcional SG SST | H33: Anual | I33: Porcentaje | J33: Gerencia General, Copasst | K33: Procedimiento de Identificación de Peligros, Evaluación y Valoración de Riesgos (IPEVR) Reportes de Actos y Condiciones Inseguras Auditorías de primera, segunda y tercera parte Informes ARL y otras partes interesadas Matriz o Herramienta para IPEVR | L33: 0.9 | M33: 35/35 | U33: 35/35 | V33: =35/35 -> 1
A34: PROCESO | B34: 15. Gestión de riesgos viales | C34: Identificar los riesgos viales con calificación alta a inicio de ñao vs los riesgos con calificación alta a final del año | D34: CANTIDAD DE RIESGOS CON VALORACIÓN ALTA AL FINAL DEL AÑO - CANTIDAD DE RIESGOS CON VALORACIÓN ALTA AL INICIO DEL AÑO | F34: PESV | G34: Líder Funcional SG SST | H34: Anual | I34: Porcentaje | J34: Gerencia General, Copasst | K34: Procedimiento de Identificación de Peligros, Evaluación y Valoración de Riesgos (IPEVR) Reportes de Actos y Condiciones Inseguras Auditorías de primera, segunda y tercera parte Informes ARL y otras partes interesadas Matriz o Herramienta para IPEVR | L34: 0.9 | V34: =3/3 -> 1
A35: TIPO DE INDICADOR | B35: NOMBRE INDICADOR | C35: DEFINICION | D35: COMO SE MIDE | F35: FUENTE DE INFORMACIÓN | G35: RESPONSABLE | H35: FRECUENCIA DE MEDICIÓN | I35: UNIDAD | J35: INFORMAR A | K35: INTERPRETACION | L35: META | M35: FORMULA | N35: RESULTADO 2017 | O35: RESULTADO 2018 | P35: RESULTADO 2019 | Q35: RESULTADO 2020 | R35: RESULTADO 2021 | S35: RESULTADO 2022 | T35: RESULTADO 2023 | U35: RESULTADO 2024 | V35: RESULTADO 2025 | W35: RESULTADO 2026
A36: RESULTADO | B36: 1. Requisitos Legales | C36: Cumplimiento de requisitos legales aplicables | D36: Verificaciòn de cumplimiento | F36: SG-SST | G36: Líder Funcional SG SST | H36: Mensual | I36: Cumplimiento | J36: Gerencia General, Copasst | K36: Se cumple con la normatividad legal vigente aplicable. | L36: 0.9 | M36: % | N36: SI | O36: SI | P36: SI | Q36: SI | R36: SI | S36: SI | T36: SI | U36: SI | V36: SI | W36: SI
A37: RESULTADO | B37: 2. Objetivos y metas | C37: Cumplimiento de Objetivos y metas en seguridad y salud. | D37: (No.de Objetivos y metas cumplidos/ No.de Objetivos y metas trazados) * 100 | F37: SG-SST | G37: Líder Funcional SG SST | H37: Semestral | I37: Cumplimiento | J37: Gerencia General, Copasst | K37: Se cumple con el 100% de los objetivos y metas trazados | L37: 0.9 | M37: (4/ 4 ) * 100 | N37: 0.4 | O37: 0.4 | P37: 0.2 | Q37: 0.25 | R37: 0.75 | S37: =4/4 -> 1 | T37: =4/4 -> 1 | U37: SI | V37: =(4/4) -> 1
A38: RESULTADO | B38: 3. Ejecución del plan de trabajo | C38: Ejecución del plan de trabajo en SST | D38: (N° DE ACTIVIDADES DESARROLLADAS EN EL PERIODO EN EL PLAN / NRO DE ACTIVIDADES PROPUESTASEN EL PERIODO EN EL PLAN DE TRABAJO) X 100 | F38: PLAN DE TRABAJO ANUAL EN SST | G38: Líder Funcional SG SST | H38: Semestral | I38: Porcentaje | J38: Gerencia General, Copasst | K38: 100% de actividades cumplidas del plan de trabajo | L38: 0.9 | M38: (438/749)*100 | N38: 87.93% | O38: 0.89 | P38: 0.88 | Q38: 0.91 | R38: 0.97 | S38: =182/183 -> 0.99453552 | T38: =178/181 -> 0.98342541 | U38: 0.638 | V38: =(438/749) -> 0.58477971
A39: RESULTADO | B39: 4. Evaluaciòn no conformidades | C39: Evaluación de las no conformidades detectadas en el seguimiento al plan de trabajo anual en seguridad y salud en el trabajo; | D39: (No. DE NO CONFORMIDADES EN EL PERIODO DEL PLAN DE TRABAJO ANUAL/ No DE ACTIVIDADES PLANEADAS PARA EL PERIODO)*100 | F39: PLAN DE TRABAJO ANUAL EN SST | G39: Líder Funcional SG SST | H39: Semestral | I39: Porcentaje | J39: Gerencia General, Copasst | K39: 0% de no conformidades detectadas en el seguimiento del plan de trabajo anual | L39: 0 | M39: 3/3*100 | N39: 0.4375 | O39: 0.1019 | P39: 0.13 | Q39: 0.085 | R39: 0.04 | S39: =1.8/183 -> 0.0098360656 | T39: =0/177% -> 0 | U39: =0/177% -> 0 | V39: =(3/3) -> 1
A40: RESULTADO | B40: 5. Acciones correctivas | C40: Muestra el porcentaje de acciones correctivas para las no conformidades resultantes de la revision por la direccion y auditorias (adicional ver indicadores de plan de accidentalidad e inpecciones). | D40: Acciones correctivas realizadas x 100 No de No Conformidades encontradas | F40: SG-SST | G40: Líder Funcional SG SST | H40: Anual | I40: Porcentaje | J40: Gerencia General, Copasst | K40: 100 % de las no conformidades tienen acciones correctivas | L40: 0.75 | M40: 13/13*100 | N40: 0.4375 | O40: 0.3793 | P40: 0.5769 | Q40: 1 | R40: 1 | S40: =15/15 -> 1 | T40: =15/15 -> 1 | U40: =13/13 -> 1 | V40: =13/13 -> 1
A41: RESULTADO | B41: 5.1 %Inspecciones realizadas | C41: Muestra el porcentaje de Inspecciones | D41: Número de inspecciones realizadas x 100 Número de inspecciones planeadas | F41: SG-SST | G41: Líder Funcional SG SST | H41: Trimestral | I41: Porcentaje | J41: Gerencia General, Copasst | K41: El 100% de las inspecciones planeadas se realizaron | L41: 0.9 | M41: (18/18 x 100 | N41: 0.5744 | O41: 0.5744 | P41: 1 | Q41: 0.75 | R41: 1 | S41: =68/68 -> 1 | T41: =52/52 -> 1 | U41: =18/18 -> 1 | V41: =18/18 -> 1
A42: RESULTADO | B42: 5. 2 % Condiciones mejoradas | C42: Muestra el porcentaje de condiciones mejoradas de las inspecciones realizadas | D42: Numero de condiciones mejoradas x 100 Número de condiciones encontradas | F42: SG-SST | G42: Líder Funcional SG SST | H42: Anual | I42: Porcentaje | J42: Gerencia General, Copasst | K42: 100% de condiciones mejoradas | L42: 0.9 | M42: (6/6)*100 | N42: 0.54 | O42: 0.54 | P42: 0.25 | Q42: 0.84 | R42: 1 | S42: =6/6 -> 1 | T42: =6/6 -> 1 | U42: =6/6 -> 1 | V42: =6/6 -> 1
A43: RESULTADO | B43: 5. 3 % Cubrimiento EPP | C43: Proporción de trabajadores que reciben los EPP | D43: Número de EPP entregados x 100 Número de EPP requeridos | F43: SG-SST | G43: Líder Funcional SG SST | H43: Mensual | I43: Porcentaje | J43: Gerencia General, Copasst | K43: 100%de los EPP requeridos fueron entregados | L43: 0.9 | M43: (31/31) *100 | N43: 1 | O43: 1 | P43: 1 | Q43: 1 | R43: 1 | S43: =1953/1953 -> 1 | T43: =1953/1953 -> 1 | U43: =28/28 -> 1 | V43: =28/28 -> 1 | W43: =31/31 -> 1
A44: RESULTADO | B44: 5.4 % uso EPP | C44: Muestra el porcentaje de personas que usan los EPP | D44: Trabajadores que usan EPP en el período de tiempo x 100 Número de EPP entregados | F44: SG-SST | G44: Líder Funcional SG SST | H44: Mensual | I44: Porcentaje | J44: Gerencia General, Copasst | K44: El % de los trabajadores usa el EPP | L44: 0.9 | M44: (31/31)*100 | N44: 0.9998 | O44: 1 | P44: 1 | Q44: 1 | R44: 1 | S44: =850/1053 -> 0.80721747 | T44: 0.85 | U44: =29/29 -> 1 | V44: =29/29 -> 1 | W44: =31/31 -> 1
A45: RESULTADO | B45: 6. Cumplimiento de SVE DME | C45: EI cumplimiento de los programas de vigilancia epidemiológica de la salud de los trabajadores, acorde con las características, peligros y riesgos | D45: (NO. DE TRABAJADORES INTERVENIDOS EN EL SVE / NO. TRABAJADORES A INTERVENIR)*100 | F45: FORMATOS PROPIOS DE CADA SVE DME | G45: Líder Funcional SG SST | H45: Semestral | I45: Porcentaje | J45: Gerencia General, Copasst | K45: 100% de trabajadores intervenidos en las actividades de los SVE DME | L45: 0.9 | M45: 671/995*100 | N45: 1 | O45: 1 | P45: 1 | Q45: 1 | R45: 1 | S45: =1007/1007 -> 1 | T45: =1099/1099 -> 1 | U45: =919/1041 -> 0.882805 | V45: =(671/995) -> 0.67437186
A46: RESULTADO | B46: 6.1 Cumplimiento del cronogrma de actividades de SVE FRPS | C46: Medir el cumplimiento del cronograma de actividades del SVE-FRP anualmente. | D46: # de acciones realizadas / Número total de acciones presupuestadas. | F46: FORMATOS PROPIOS DE CADA SVE | G46: Líder Funcional SG SST | H46: Anual | I46: Porcentaje | J46: Gerencia General, Copasst | K46: 100% de trabajadores intervenidos en las actividades de los SVE FRP | L46: 0.9 | M46: 1045/1045*100 | N46: 1 | O46: 1 | P46: 1 | Q46: 1 | R46: 1 | S46: =40/40 -> 1 | T46: =1007/1007 -> 1 | U46: =1007/1007 -> 1 | V46: =1007/1007 -> 1
A47: RESULTADO | B47: 6.2 Cumplimiento del cobertura del SVE FRPS | C47: Medir el porcentaje de la población cubierta por el SVE-FRP. | D47: (N° de trabajadores intervenidos/ N° de trabajadores de la empresa) * 100 | F47: FORMATOS PROPIOS DE CADA SVE | G47: Líder Funcional SG SST | H47: Anual | I47: Porcentaje | J47: Gerencia General, Copasst | K47: 100% de trabajadores intervenidos en las actividades de los SVE FRP | L47: 0.9 | M47: 1045/1045*100 | N47: 1 | O47: 1 | P47: 1 | Q47: 1 | R47: 1 | S47: =1007/1007 -> 1 | T47: =1007/1007 -> 1 | U47: =1007/1007 -> 1 | V47: =1007/1007 -> 1
A48: RESULTADO | B48: 7. Evaluación de los programas de rehabilitación de la salud | C48: La evaluación de los resultados de los programas de rehabilitación de la salud de los trabajadores; | D48: (NO. DE TRABAJADORES INTERVENIDOS EN EL PROGRAMA / NO. TRABAJADORES A INTERVENIR)*100 | F48: FORMATOS PROPIOS DEL PROGRAMA | G48: Líder Funcional SG SST | H48: Semestral | I48: Porcentaje | J48: Gerencia General, Copasst | K48: 0% de trabajadores intervenidos | L48: 0.9 | M48: 0 | N48: 1 | O48: 1 | P48: 1 | Q48: 1 | R48: 1 | S48: 0 | T48: 0 | U48: 0 | V48: 0
A49: RESULTADO | B49: 8.Frecuencia de Accidentalidad (Resoluciòn 312 de 2019) | C49: Número de veces que ocurre un accidente de trabajo en el mes | D49: IFAT =(N° TOTAL DE A.T EN EL MES / N° DE TRABAJADORES EN EL MES) * 100 | F49: REGISTRO DE ACCIDENTALIDAD | G49: Líder Funcional SG SST | H49: Mensual | I49: Número | J49: Gerencia General, Copasst | K49: Por cada 100 trabajadores que laboraron en el mes, se presentaron 0,19 accidentes de trabajo. | L49: 1 | M49: IFAT =(2/850)*100 | N49: 1.14 | O49: 1.2 | P49: 1.35 | Q49: 1.57 | R49: 0.73 | S49: =6/1007*100 -> 0.5958292 | T49: =(6/1087)*100 -> 0.55197792 | U49: 0.67 | V49: =(2/1026)*100 -> 0.19493177 | W49: =(2/850)*100 -> 0.23529412
A50: RESULTADO | B50: 8.1 Severidad de Accidentalidad (Resolución 312 de 2019) | C50: Número de días perdidos por accidentes de trabajo en el mes | D50: ISAT= (N° DIAS DE INCAPACIDAD POR ACCIDENTES DE TRABAJO EN EL MES + NÚMERO DE DÍAS CARGADOS EN EL MES / N° DE TRABAJADORES EN EL MES) * 100 | F50: REGISTRO DE ACCIDENTALIDAD | G50: Líder Funcional SG SST | H50: Mensual | I50: Número | J50: Gerencia General, Copasst | K50: Por cada 100 trabajadores que laboraron en el mes, se perdieron 0 días por accidente de trabajo. | L50: 1 | M50: ISAT= (8/850*100 | N50: 2.44 | O50: 2.41 | P50: 1.56 | Q50: 3.82 | R50: 1.05 | S50: =1/1007*100 -> 0.099304866 | T50: =(2/1087)*100 -> 0.18399264 | U50: 1.91 | V50: =(5/1026)*100 -> 0.48732943 | W50: =(8/850)*100 -> 0.94117647
A51: RESULTADO | B51: 8.2 Indice de Lesiones Incapacitantes por A.T | C51: Corresponde a la relacion entre los indices de frecuencia y severidad de Accidentes de Trabajo con Incapacidad. Es un indice global de comportamiento de lesiones incapacitantes que no tiene unidad, su utilidad radica en la comparacion entre diferentes periodos. | D51: I = (N° CASOS NUEVOS DE ENFERMEDAD LABORAL EN EL AÑO / PROMEDIO DE TRABAJADORES EN EL AÑO) * 100.000 | F51: INDICADORES DE ACCIDENTALIDAD | G51: Líder Funcional SG SST | H51: Anual | I51: Nùmero | J51: Gerencia General, Copasst | L51: 0 | M51: ILIAT= (0,35*0,09)/ 1142 | N51: 0 | O51: 0 | P51: 0 | Q51: 0.01 | R51: 0 | S51: =S49*S50/1007 -> 5.8757436e-05 | T51: 0 | U51: 0 | V51: 0
A52: RESULTADO | B52: 8.3 Proporciòn de accidentes de trabajo mortales (Resolución 312 de 2019) | C52: Nùmero de accidentes de trabajo mortales en el año | D52: (NO. DE ACCIDENTES DE TRABAJO MORTALES QUE SE PRESENTARON EL AÑO/ TOTAL DE ACCIDENTES DE TRABAJO QUE SE PRESENTARON EN EL AÑO) *100 | F52: REGISTRO DE ACCIDENTALIDAD | G52: Líder Funcional SG SST | H52: Anual | I52: Porcentaje | J52: Gerencia General, Copasst, | K52: En el año el 0% de accidentes de trabajo fueron mortales | L52: 0 | M52: (0/7)*100 | N52: 0 | O52: 0 | P52: 0 | Q52: 0 | R52: 0 | S52: =(0/6)*100 -> 0 | T52: 0 | U52: 0 | V52: 0
A53: RESULTADO | B53: 8.4 Tasa Accidentalidad | C53: Relación del número de casos de accidentes de trabajo, ocurridos durante el período con el número promedio de trabajadores en el mismo período | D53: TA = N° AT / N° PROMEDIO DE TRABAJADORES | F53: SG-SST | G53: Líder Funcional SG SST | H53: Mensual | I53: Porcentaje | J53: Gerencia General, Copasst, | K53: Por cada 100 trabajadores expuestos se presentan 0,67 % accidentes en el período. | L53: 0 | M53: IFAT =(2/1026)*100 | N53: 0.0114 | O53: 0.012 | P53: 0.0135 | Q53: 0.0157 | R53: 0.0073 | S53: =6/1007 -> 0.005958292 | T53: =6/1087 -> 0.0055197792 | U53: 0.67 | V53: =(2/1026)*100 -> 0.19493177 | W53: =(2/850)*100 -> 0.23529412
A54: RESULTADO | B54: 8.5 Prevalencia de la enfermedad (Resolución 312 de 2019) | C54: Nùmero de casos nuevos y antiguos de enfermedad en el periodo "Z"/ Promedio de trabajadores en el periodo "Z" | D54: P = (N° DE CASOS NUEVOS Y ANTIGUOS DE ENFERMEDAD LABORAL EN CINCO AÑOS / PROMEDIO DE TRABAJADORES EN CINCO AÑOS)* 100.000 | F54: REGISTRO ESTADISTICO DE MORBILIDAD | G54: Líder Funcional SG SST | H54: Anual | I54: Número | J54: Gerencia General, Copasst, | K54: Por cada 100.000 trabajadores existen 99 casos de enfermedad laboral en 5 años | L54: 0 | M54: P = (1/1087)*100.000 | N54: 0.0069 | O54: 0.008 | P54: 816 | Q54: 620 | R54: 289 | S54: =0/1007*100000 -> 0 | T54: =0/1007*100000 -> 0 | U54: =0/1007*100000 -> 0 | V54: =0/1007*100000 -> 0
A55: RESULTADO | B55: 8.6 Incidencia de la enfermedad (Resolución 312 de 2019) | C55: Número de casos nuevos de enfermedad laboral en una poblaciòn determinada en un periodo de tiempo. | D55: I = (N° CASOS NUEVOS DE ENFERMEDAD LABORAL EN EL AÑO / PROMEDIO DE TRABAJADORES EN EL AÑO) * 100.000 | F55: REGISTRO ESTADISTICO DE MORBILIDAD | G55: Líder Funcional SG SST | H55: Anual | I55: Número | J55: Gerencia General, Copasst, | K55: Por cada 100.000 trabajadores existen 0 casos nuevos de enfermedad laboral en el año | L55: 0 | M55: I = (0/1087)*100000 | N55: 0.0008 | O55: 0.0008 | P55: 104 | Q55: 0 | R55: 0 | S55: =0/1007*100000 -> 0 | T55: 0 | U55: 0 | V55: 0
A56: RESULTADO | B56: 9. Indice de Frecuecia de Ausentismo | C56: Incluye Enfermedad Comun, enfermedad profesional, accidente de trabajo y consulta de salud. | D56: IFA=N° DE EVENTOS DE AUSENCIA POR CAUSA DE SALUD ULTIMO AÑO / No, DE TRABAJADORES PROMEDIO AÑO *100 | F56: SG-SST | G56: Líder Funcional SG SST | H56: Anual | I56: Número | J56: Gerencia General, Copasst, | K56: Por cada 100 trabajadores se presentan 2,021 % eventos incapacitantes por enfermedad común, laboral, AT, LM, LP | L56: 90 | M56: IFA= (2064/1021) *100 | N56: 220.25 | O56: 184.15 | P56: 133.45 | Q56: 104.96 | R56: 149.32 | S56: =(1903/999)*100 -> 190.49049 | T56: =1483/1098 -> 1.3506375 | U56: 2.02% | V56: =(4068/1051)/100 -> 0.038705994
A57: RESULTADO | B57: 9.1. Ausentismo por causa médica (Resolución 312 de 2019) | C57: Ausentismo es la no asistencia al trabajo con incapacidad médica. | D57: ISA=(N° DIAS PERDIDOS POR INCAPACIDAD / N° TOTAL DE DIA LABORALES )* 100 | F57: INFORME DE AUSENTISMO, INDICADORES | G57: Líder Funcional SG SST | H57: Mensual | I57: Porcentaje | J57: Gerencia General, Copasst, | K57: se perdió el 3,33% de días programados de trabajo por incapacidad médica. | L57: 0 | M57: ISA=(# DE DIAS PERDIDOS POR INCAPACIDAD *8 / # TOTAL DE DIAS LABORALES HH:TT) | N57: 1210.14 | O57: 1018.15 | P57: 2195 | Q57: 0.0201 | R57: 0.0256 | S57: 2.13% | T57: 0.96% | U57: 0.0119 | V57: 1.98% | W57: =(4358*8/1048483) -> 0.033251851
A58: RESULTADO | B58: 9.2. Porcentaje de Tiempo Perdido | C58: Muestra el porcentaje perdido en un año con relacion al tiempo programado. | D58: %TP=N° DIAS U HORAS PERDIDAS EN EL AÑO *100 N° DIAS U HORAS PROGRAMADAS EN EL PERIODO | F58: SG-SST | G58: Líder Funcional SG SST | H58: Anual | I58: Porcentaje | J58: Gerencia General, Copasst, | K58: Se perdiò en el año el 2,56% de tiempo por incapacidades. | L58: 0.0303 | M58: %TP=(7678*8)/ 2400400)*100 | N58: 0.0403 | O58: 0.0339 | P58: 0.0299 | Q58: 0.0242 | R58: 0.0308 | S58: 0.0256 | U58: 0.0256
A59: RESULTADO | B59: 10. Medidas de control en los riesgos y peligros priorizados | C59: la efectividad de los controles de los peligros establecidos----Análisis de los resultados en la implementación de las medidas de control en los peligros identificados y los riesgos priorizados. | D59: No. De medidas de control de los peligros y riesgos realizadas /No. De medidas de control de los peligros y riesgos establecidas *100 | F59: SG-SST | G59: Líder Funcional SG SST | H59: Anual | I59: Porcentaje | J59: Gerencia General, Copasst, | K59: Se realizaron el 97% de las medidas de control establecidas para riesgos priorizados | L59: 0.9 | M59: 67/69*100 | N59: 0.66 | O59: 1 | P59: 1 | Q59: 1 | R59: 1 | S59: =67/69 -> 0.97101449 | T59: =67/69 -> 0.97101449 | U59: =67/69 -> 0.97101449 | V59: 0.98
A60: RESULTADO | B60: 11. Mediciones ambientales | C60: Evaluación del cumplimiento del cronograma de las mediciones ambientales ocupacionales (indicadores de proceso) y sus resultados si aplica. | D60: (No. RECOMENDACIONES ADOPTADAS DE LAS MEDICIONES / No. RECOMENDACIONES EMITIDAS)*100 | F60: REGISTRO DE LOS ESTUDIOS AMBIENTALES | G60: Líder Funcional SG SST | H60: Semestral | I60: Porcentaje | J60: Gerencia General, Copasst | K60: 100 de las recomendaciones se adoptaron derivadas de las mediciones ambientales | L60: 0.9 | M60: (2/2)*100 | N60: 1 | O60: 0.5 | P60: 0.5 | Q60: 0 | R60: 0 | S60: =1/1 -> 1 | T60: =1/1 -> 1 | U60: =6/7 -> 0.85714286 | V60: =(2/2) -> 1
A61: RESULTADO | B61: 12.Tasa de sinisiestros viales por nivel de perdida. TSV (n) | C61: Definir tasa de siniestros viales por nivel de perdida | D61: (NUMERO DE SISINIESTROS VIALES TRIMESTRE * 1000000 ) / NUMEROS DE KILOMETROS RECORRIDOS POR TRIMESTRE POR TODA LA FLOTA DE VEHICULOS | F61: PESV | G61: Líder Funcional SG SST | H61: Trimestral | I61: Porcentaje | J61: Gerencia General, Copasst | K61: Tasa de siniestros viales por nivel ed perdida TSV (n) | L61: 0 | M61: 3*1000000/53018 | U61: =0*1000000/53018 -> 0 | V61: =0*1000000/53018 -> 0
A62: RESULTADO | B62: 12.1Cumplimiento de metas PESV | C62: Medir el nivel de cumpliento de las metas propuestas en el PESV | D62: NUMERO DE METAS ALCANZADAS O LOGRADAS EN EL PESV X TRIMESTRE / NUMERO TOTAL DE METAS DEFINIDAS PESV X TRIMESTRE * 100 | F62: PESV | G62: Líder Funcional SG SST | H62: Trimestral | I62: Porcentaje | J62: Gerencia General, Copasst | K62: Indicadores propuestos del Paso 20 Auditorías de primera, segunda y tercera parte Diagnóstico (Paso 5) Revisión de la Dirección | L62: 0.9 | U62: =3/3 -> 1 | V62: =3/3 -> 1
A63: RESULTADO | B63: 12.2Cumplimiento plan de trabajo PESV | C63: Medir el nivel de cumplimiento de las actividades del plan anual del PESV | D63: NUMERO DE ACTIVIDADES EJECUTADAS DEL PLAN ANUAL DE TRABAJO POR TRIMESTRE / NUMERO DE ACTIVIDADES PLANEADAS DEL PLAN ANUAL DE TRABAJO PESV POR TRIMESTRE | F63: PESV | G63: Líder Funcional SG SST | H63: Trimestral | I63: Porcentaje | J63: Gerencia General, Copasst | K63: Plan Anual de Trabajo (SG-SST y PESV) Plan de Formación (SG-SST y PESV) Auditoría | L63: 0.9 | M63: 438/749 | U63: =159/197 -> 0.8071066 | V63: =(438/749) -> 0.58477971
A64: RESULTADO | B64: 12.3 Exceso jornadas laborales conductores | C64: Identificar el exceso e jorandas laborales de los conductores | D64: NUMERO DE EXCESOS EN LA JORNADA DIARIA DE TRABAJO DE LOS CONDUCTORES ( EVENTOS EN LOS QUE LOS CONDUCTORES HAN SUPERADO EL TIEMPO MAXIMO PERMITIDO EN LA LEGISLACIÓN ) POR MES /SUMATORIA TOTA DE DIAS TRABAJADOS POR TODOS LOS CONDUCTORES QUE REALIZAN DESPLAZAMIENTOS LABORALES POR MES | F64: PESV | G64: Líder Funcional SG SST | H64: Mensual | I64: Porcentaje | J64: Gerencia General, Copasst | K64: Programa de prevención de la fatiga | L64: 0.9 | M64: 0/26 | U64: =0/26*100 -> 0 | V64: =0/26*100 -> 0 | W64: =0/26*100 -> 0
A65: RESULTADO | B65: 12.4 Tasa de Accidentes de Transito | C65: Muestra el numero de conductores accidentados | D65: [(No de personas accidentadas por Periodo)/(No de Personas Expuestas por Periodo)]*100 | F65: PESV | G65: Líder Funcional SG SST | H65: Semestral | I65: Porcentaje | J65: Gerencia General, Copasst | K65: 0% de conductores accidentados | L65: 0 | M65: (0/4)*100 | N65: 0 | O65: 0 | P65: 0 | Q65: 0 | R65: 0 | S65: =0/4 -> 0 | T65: =0/4 -> 0 | U65: =0/4 -> 0 | V65: =0/4 -> 0
A66: RESULTADO | B66: 12.5 Frecuencia de Accidentes de Transito | C66: Muestra el numero de accidentes de tránsito | D66: [(No de Accidentes de tránsito en un Periodo)/( No de Vehículos de la compañía)] | F66: PESV | G66: Líder Funcional SG SST | H66: Semestral | I66: Porcentaje | J66: Gerencia General, Copasst | K66: 0% de accidentes de tránsito | L66: 0 | M66: (0/4)*100 | N66: 0 | O66: 0.25 | P66: 0 | Q66: 0 | R66: 0 | S66: =(0/4)*100% -> 0 | T66: =0/4 -> 0 | U66: =0/4 -> 0 | V66: =0/4 -> 0
A67: RESULTADO | B67: 12.6 % de Afectación | C67: Número de conductores lesionados | D67: [(No de Conductores Lesionados con Accidente Transito)/(Total de Accidentes de tránsito en el periodo)]*100 | F67: PESV | G67: Líder Funcional SG SST | H67: Semestral | I67: Porcentaje | J67: Gerencia General, Copasst | K67: 0% de conductores lesionados por accidentes de tránsito | L67: 0 | M67: (0/0)*100 | N67: 0 | O67: 0 | P67: 0 | Q67: 0 | R67: 0 | S67: =(0/4)*100% -> 0 | T67: 0 | U67: 0 | V67: =0/4 -> 0
A68: RESULTADO | C68: Número de dias de incapacidad por accidente de tránsito | D68: [(No de días de incapacidad con Accidente transito)/( No. De dias en el periodo)]*100 | F68: PESV | G68: Líder Funcional SG SST | H68: Semestral | I68: Porcentaje | J68: Gerencia General, Copasst | K68: 0% de días de incapacidad por accidente de tránsito en el periodo | L68: 0 | M68: (0/360)*100 | N68: 0 | O68: 0 | P68: 0 | Q68: 0 | R68: 0 | S68: =0/360 -> 0 | T68: 0 | U68: 0 | V68: =0/4 -> 0
A69: RESULTADO | C69: Número de vehiculos no disponibles | D69: [(No de días de vehículos no disponibles)/(No de dias en el periodo)]*100 | F69: PESV | G69: Líder Funcional SG SST | H69: Semestral | I69: Porcentaje | J69: Gerencia General, Copasst | K69: 0% de vehiculos no disponibles | L69: 0 | M69: (0/360)*100 | N69: 0 | O69: 3.33 | P69: 0 | Q69: 0 | R69: 0 | S69: =0/360 -> 0 | T69: 0 | U69: 0 | V69: =0/4 -> 0
A70: RESULTADO | B70: 12.7 Impacto Económico de los Incidentes de Transito | C70: Costos de los accidentes | D70: Costos directos + Costos Indirecto | F70: PESV | G70: Líder Funcional SG SST | H70: Semestral | I70: Porcentaje | J70: Gerencia General, Copasst | K70: 0 costos totales por accidente de tránsito | L70: N.A | M70: (0+0) | N70: 0 | O70: 0 | P70: 0 | Q70: 0 | R70: 0 | S70: =0+0 -> 0 | T70: 0 | U70: 0 | V70: =0/4 -> 0
A71: RESULTADO | B71: 12.8 Número de personal formado en Seguridad Vial. | C71: Número de personas capacitadas en seguridad vial | D71: [(Número de personas formadas)/(Total de personas a formar en seguridad vial)]*100 | F71: PESV | G71: Líder Funcional SG SST | H71: Semestral | I71: Porcentaje | J71: Gerencia General, Copasst | K71: 100% de personas formadas en seguridad vial | L71: 0.9 | M71: (545/545)*100 | N71: 0 | O71: 1 | P71: 25.75 | Q71: 0.5625 | R71: 1 | S71: =241/241 -> 1 | T71: =545/545 -> 1 | U71: =545/545 -> 1 | V71: =(4/4) -> 1
A72: RESULTADO | B72: 12.9 Cumplimiento en los programas de mantenimiento preventivo de los vehículos. | C72: Mantenimientos realizados a los vehiculos | D72: [(Número de mantenimientos realizados)/(Total de mantenimientos programados)]*100 | F72: PESV | G72: Líder Funcional SG SST | H72: Semestral | I72: Porcentaje | J72: Gerencia General, Copasst | K72: 100% de los mantenimientos realizados | L72: 0.9 | M72: (4/4)*100 | N72: 1 | O72: 1 | P72: 1 | Q72: 1 | R72: 1 | S72: =3/3 -> 1 | T72: =(4/4)*100% -> 1 | U72: =(4/4)*100% -> 1 | V72: =(4/4) -> 1
A73: RESULTADO | B73: 12.10 Numero de Evaluaciones Practicas de los conductores | C73: Evaluaciones de los conductores | D73: [(Número de evaluaciones realizadas)/(Total de evaluaciones programados)]*100 | F73: PESV | G73: Líder Funcional SG SST | H73: Semestral | I73: Porcentaje | J73: Gerencia General, Copasst | K73: 100% de los conducores con la evaluación de seguridad vial | L73: 0.9 | M73: (3/3)*100 | N73: 0 | O73: 0.75 | P73: 0.75 | Q73: 1 | R73: 1 | S73: =1/1 -> 1 | T73: =3/3 -> 1 | U73: =3/3 -> 1 | V73: =(4/4) -> 1
A74: RESULTADO | B74: 13. % Cobertura Inducciòn | C74: Muestra el porcentaje de personas que reciben la inducciòn al SG-SST | D74: Número de personas que asisten a la Id.*100 Número de personas que ingresan en el periodo | F74: SG-SST | G74: Líder Funcional SG SST | H74: Mensual | I74: Porcentaje | J74: Gerencia General, Copasst | K74: 90,59% de las personas nuevas recibieron inducción al SGSST | L74: 0.9 | M74: (77/85*100 | N74: 1 | O74: 1 | P74: 1 | Q74: 1 | R74: 1 | S74: =488/488 -> 1 | T74: =391/391 -> 1 | U74: =391/391 -> 1 | V74: =(77/85)*100 -> 90.588235
A75: RESULTADO | B75: 14. % Cubrimiento Capacitación | C75: Muestra el porcentaje de actividades de capacitación que cubren al 100% de la población | D75: Número de capacitaciones para el 100% de la población x 100 Número de capacitaciones requeridas para el 100% de la población | F75: SG-SST | G75: Líder Funcional SG SST | H75: Semestral | I75: Porcentaje | J75: Gerencia General, Copasst | K75: 100% de las actividades de capacitación son para toda la población SYC | L75: 0.9 | M75: (103/103) *100 | R75: 1 | S75: =157/157 -> 1 | T75: =135/135 -> 1 | U75: =135/135 -> 1 | V75: =(103/103) -> 1
A76: RESULTADO | B76: 15. % Cubrimiento Examenes médicos | C76: Muestra el porcentaje de cobertura en examenes médicos | D76: Número de examenes médicos realizados x 100 Número de examenes médicos requeridos | F76: SG-SST | G76: Líder Funcional SG SST | H76: Anual | I76: Porcentaje | J76: Gerencia General, Copasst | K76: 84 % de los examenes médicos fueron realizados | L76: 0.9 | M76: (850/1007) *100 | R76: 1 | S76: =850/1007 -> 0.84409136 | T76: =850/1031 -> 0.82444229 | U76: =732/1045 -> 0.70047847

Sheet 1
A1: PROCESOS ADMINISTRATIVOS / SEGURIDAD Y SALUD EN EL TRABAJO
A2: INDICADORES DE GESTION
A3: CODIGO | C3: RE-RH-37-SST | D3: NIVEL DE CLASIFICACIÓN | G3: USO INTERNO (NC2) | K3: VERSION | L3: 0.2
A5: NOMBRE DEL INDICADOR | E5: ='Tablero indicadores 2026'!B7 -> 1. Política de SST
A7: PROCESO | E7: ='Tablero indicadores 2026'!A1 -> PROCESOS ADMINISTRATIVOS / SEGURIDAD Y SALUD EN EL TRABAJO | R7: META | T7: ='Tablero indicadores 2026'!W7 -> 0
A9: FORMULA | E9: ='Tablero indicadores 2026'!M7 -> SI/NO | R9: FRECUENCIA DE MEDICIÓN | T9: ='Tablero indicadores 2026'!H7 -> Anual
A11: UNIDAD | E11: ='Tablero indicadores 2026'!I7 -> Cumplimiento | R11: TIPO INDICADOR | T11: ='Tablero indicadores 2026'!A7 -> ESTRUCTURA
A13: RESPONSABLE MEDICIÓN | E13: ='Tablero indicadores 2026'!G7 -> Líder Funcional SG SST | R13: VIGENCIA | T13: 2026
A17: PARAMETROS | E17: Enero | F17: Febrero | G17: Marzo | H17: Abril | I17: Mayo | J17: Junio | K17: Julio | L17: Agosto | M17: Septiembre | N17: Octubre | O17: Noviembre | P17: Diciembre | R17: OBSERVACIONES: Documento de la política de SST firmada, divulgada y fechada.
A19: Numerador | G19: 1
A20: Denominador | G20: 1
A22: Rango Mayor (Meta) | G22: 1 | Q22: =#REF! -> #REF!
A24: Rango Menor | G24: 0
A26: Avance | G26: =G19/G20 -> 1
C31: ANÁLISIS | I31: ACCIÓN A SEGUIR
C32: El documento de la Política del SST se encuentre firmada, divulgada y fechada. | I32: Elaborar política de SST escrita, firmada, fechada y comunicada al copasst y a todos los trabajadores
C33: FECHA SEGUIMIENTO | I33: SEGUIMIENTO A LA IMPLEMENTACIÓN
C34: 46094 | I34: Se realiza socialización de la Política de seguridad y salud en el trabajo a todo el personal de SYC incluido el copasst en el mes de marzo y se publica en plataforma interna edocs, asi mismo se comparte por los diferentes medios de comunicación.
C35: RESPONSABLE
C36: ='Tablero indicadores 2026'!G7 -> Líder Funcional SG SST

Sheet 2
A1: PROCESOS ADMINISTRATIVOS / SEGURIDAD Y SALUD EN EL TRABAJO
A2: INDICADORES DE GESTION
A3: CODIGO | C3: RE-RH-37-SST | D3: NIVEL DE CLASIFICACIÓN | G3: USO INTERNO (NC2) | K3: VERSION | L3: 0.2
A5: NOMBRE DEL INDICADOR | E5: ='Tablero indicadores 2026'!B8 -> 2. Objetivos y metas
A7: PROCESO | E7: ='Tablero indicadores 2026'!A1 -> PROCESOS ADMINISTRATIVOS / SEGURIDAD Y SALUD EN EL TRABAJO | R7: META | T7: ='Tablero indicadores 2026'!A49:V50 -> #VALUE!
A9: FORMULA | E9: ='Tablero indicadores 2026'!M7 -> SI/NO | R9: FRECUENCIA DE MEDICIÓN | T9: ='Tablero indicadores 2026'!H8 -> Anual
A11: UNIDAD | E11: ='Tablero indicadores 2026'!I7 -> Cumplimiento | R11: TIPO INDICADOR | T11: ='Tablero indicadores 2026'!A7 -> ESTRUCTURA
A13: RESPONSABLE MEDICIÓN | E13: ='Tablero indicadores 2026'!G7 -> Líder Funcional SG SST | R13: VIGENCIA | T13: 2026
A17: PARAMETROS | E17: Enero | F17: Febrero | G17: Marzo | H17: Abril | I17: Mayo | J17: Junio | K17: Julio | L17: Agosto | M17: Septiembre | N17: Octubre | O17: Noviembre | P17: Diciembre | R17: OBSERVACIONES: Objetivos y metas de seguridad escritos y divulgados.
A19: Numerador | F19: 1
A20: Denominador | F20: 1
A22: Rango Mayor (Meta) | F22: 1 | Q22: =#REF! -> #REF!
A24: Rango Menor | F24: 0
A26: Avance | F26: =F19/F20 -> 1
C31: ANÁLISIS | I31: ACCIÓN A SEGUIR
C32: Definir los objetivos del Sistema de Gestión de SST de conformidad con la política de SST, los cuales deben ser claros, medibles, cuantificables y tener metas, coherentes con el plan de trabajo anual, compatibles con la normatividad vigente, se encuentran documentados, son comunicados a los trabajadores, son revisados y evaluados mínimo una vez al año, actualizados de ser necesario y se encuentran en documento firmado por el empleador | I32: Elaborar Objetivos para el 2025 de SST escritos, firmados, fechados y comunicados al copasst y a todos los trabajadores
C33: FECHA SEGUIMIENTO | I33: SEGUIMIENTO A LA IMPLEMENTACIÓN
C34: 46059 | I34: Se realiza socialización de los objetivos y metas del 2025 en seguridad y salud en el trabajo a todo el personal de SYC incluido el copasst en el mes de marzo y se publica en plataforma interna edocs y paraíso, asi mismo se comparte por los diferentes medios de comunicación.
C35: RESPONSABLE
C36: ='Tablero indicadores 2026'!G7 -> Líder Funcional SG SST

Sheet 3
A1: PROCESOS ADMINISTRATIVOS / SEGURIDAD Y SALUD EN EL TRABAJO
A2: INDICADORES DE GESTION
A3: CODIGO | C3: RE-RH-37-SST | D3: NIVEL DE CLASIFICACIÓN | G3: USO INTERNO (NC2) | K3: VERSION | L3: 0.2
A5: NOMBRE DEL INDICADOR | E5: ='Tablero indicadores 2026'!B9 -> 3. Plan de trabajo anual
A7: PROCESO | E7: ='Tablero indicadores 2026'!A1 -> PROCESOS ADMINISTRATIVOS / SEGURIDAD Y SALUD EN EL TRABAJO | R7: META | T7: ='Tablero indicadores 2026'!L20 -> 0.9
A9: FORMULA | E9: ='Tablero indicadores 2026'!M7 -> SI/NO | R9: FRECUENCIA DE MEDICIÓN | T9: ='Tablero indicadores 2026'!H9 -> Mensual
A11: UNIDAD | E11: ='Tablero indicadores 2026'!I7 -> Cumplimiento | R11: TIPO INDICADOR | T11: ='Tablero indicadores 2026'!A7 -> ESTRUCTURA
A13: RESPONSABLE MEDICIÓN | E13: ='Tablero indicadores 2026'!G7 -> Líder Funcional SG SST | R13: VIGENCIA | T13: 2026
A17: PARAMETROS | E17: Enero | F17: Febrero | G17: Marzo | H17: Abril | I17: Mayo | J17: Junio | K17: Julio | L17: Agosto | M17: Septiembre | N17: Octubre | O17: Noviembre | P17: Diciembre | R17: OBSERVACIONES: Cumplimiento de elaboración y ejecución del plan de trabajo anual.
A19: Numerador
A20: Denominador | E20: 33 | F20: 60
A22: Rango Mayor (Meta) | E22: 1 | F22: 1 | G22: 1 | H22: 1 | I22: 1 | J22: 1 | K22: 1 | L22: 1 | M22: 1 | N22: 1 | O22: 1 | P22: 1 | Q22: =#REF! -> #REF!
A24: Rango Menor | E24: 0 | F24: 0 | G24: 0 | H24: 0 | I24: 0 | J24: 0 | K24: 0 | L24: 0 | M24: 0 | N24: 0 | O24: 0 | P24: 0
A26: Avance | E26: =E19/E20 -> 0 | F26: =F19/F20 -> 0 | G26: =G19/G20 -> #DIV/0! | H26: =H19/H20 -> #DIV/0! | I26: =I19/I20 -> #DIV/0! | J26: =J19/J20 -> #DIV/0! | K26: =K19/K20 -> #DIV/0! | L26: =L19/L20 -> #DIV/0! | ... P26: =P19/P20 -> #DIV/0!
C31: ANÁLISIS | I31: ACCIÓN A SEGUIR
C32: Diseñar y definir un plan anual de trabajo para el cumplimiento del Sistema de Gestión de SST, el cual identifica los objetivos, metas, responsabilidades, recursos, cronograma de actividades, firmado por el empleador y el responsable del Sistema de Gestión de SST. | I32: Elaborar Plan anual para el 2026, donde se identifica los objetivos, metas, responsabilidades, recursos, cronograma de las actividades, firmados por el empleador y el responsable del SG SST.
C33: FECHA SEGUIMIENTO | I33: SEGUIMIENTO A LA IMPLEMENTACIÓN
C34: 46056 | F34: Elaboración plan de trabajo | I34: Se ha desarrollado el plan anual de trabajo para el año 2026 y se ha llevado a cabo la socialización con la alta dirección y se encuentra firmado por el empleador y el responsable del Sistema de Gestión de SST.
C35: 46080 | F35: Revisón y seguimiento al plan de trabajo
C36: 46112 | F36: Revisón y seguimiento al plan de trabajo
C37: 46142 | F37: Revisón y seguimiento al plan de trabajo
C38: 46171 | F38: Revisón y seguimiento al plan de trabajo
C39: 46203 | F39: Revisón y seguimiento al plan de trabajo
C40: 46234 | F40: Revisón y seguimiento al plan de trabajo
C41: 46265 | F41: Revisón y seguimiento al plan de trabajo
C42: 46295 | F42: Revisón y seguimiento al plan de trabajo
C43: 46325 | F43: Revisón y seguimiento al plan de trabajo
C44: 46356 | F44: Revisón y seguimiento al plan de trabajo
C45: 46360 | F45: Revisón y seguimiento al plan de trabajo
C46: RESPONSABLE
C47: ='Tablero indicadores 2026'!G7 -> Líder Funcional SG SST

Sheet 4
A1: PROCESOS ADMINISTRATIVOS / SEGURIDAD Y SALUD EN EL TRABAJO
A2: INDICADORES DE GESTION
A3: CODIGO | C3: RE-RH-37-SST | D3: NIVEL DE CLASIFICACIÓN | G3: USO INTERNO (NC2) | K3: VERSION | L3: 0.2
A5: NOMBRE DEL INDICADOR | E5: ='Tablero indicadores 2026'!B10 -> 4. Responsabilidades
A7: PROCESO | E7: ='Tablero indicadores 2026'!A1 -> PROCESOS ADMINISTRATIVOS / SEGURIDAD Y SALUD EN EL TRABAJO | R7: META | T7: ='Tablero indicadores 2026'!W7 -> 0
A9: FORMULA | E9: ='Tablero indicadores 2026'!M7 -> SI/NO | R9: FRECUENCIA DE MEDICIÓN | T9: ='Tablero indicadores 2026'!H10 -> Anual
A11: UNIDAD | E11: ='Tablero indicadores 2026'!I7 -> Cumplimiento | R11: TIPO INDICADOR | T11: ='Tablero indicadores 2026'!A7 -> ESTRUCTURA
A13: RESPONSABLE MEDICIÓN | E13: ='Tablero indicadores 2026'!G7 -> Líder Funcional SG SST | R13: VIGENCIA | T13: 2026
A17: PARAMETROS | E17: Enero | F17: Febrero | G17: Marzo | H17: Abril | I17: Mayo | J17: Junio | K17: Julio | L17: Agosto | M17: Septiembre | N17: Octubre | O17: Noviembre | P17: Diciembre | R17: OBSERVACIONES: Socializar con evidencia de responsabilidades asignadas tanto del responsable como los de toda la organización.
A19: Numerador | I19: 1
A20: Denominador | I20: 1
A22: Rango Mayor (Meta) | I22: 1 | Q22: =#REF! -> #REF!
A24: Rango Menor | I24: 0
A26: Avance | I26: =I19/I20 -> 1
C31: ANÁLISIS | I31: ACCIÓN A SEGUIR
C32: Asignar y documentar las responsabilidades específicas en el Sistema de Gestión SST a todos los niveles de la organización, para el desarrollo y mejora continua de dicho Sistema. | I32: Asignación de una persona que diseñe e implemente el Sistema de Gestión de SST Asignación de las responsabilidades en SST a todos los niveles de la organización
C33: FECHA SEGUIMIENTO | I33: SEGUIMIENTO A LA IMPLEMENTACIÓN
C34: 46083 | F34: Asignación de una persona que diseñe e implemente el Sistema de Gestión de SST | I34: _Se realiza la asignación de una persona que diseñe e implemente el Sistema de Gestión de SST. _Enviar a los diferentes niveles de la organización las responsabilidades específicas que cuentan dentro del Sistema de Gestión SST.
C35: 46171 | F35: Asignación de las responsabilidades en SSTa todos los niveles de la organización
C36: RESPONSABLE
C37: ='Tablero indicadores 2026'!G7 -> Líder Funcional SG SST

Sheet 5
A1: PROCESOS ADMINISTRATIVOS / SEGURIDAD Y SALUD EN EL TRABAJO
A2: INDICADORES DE GESTION
A3: CODIGO | C3: RE-RH-37-SST | D3: NIVEL DE CLASIFICACIÓN | G3: USO INTERNO (NC2) | K3: VERSION | L3: 0.2
A5: NOMBRE DEL INDICADOR | E5: ='Tablero indicadores 2026'!B11 -> 5. Recursos
A7: PROCESO | E7: ='Tablero indicadores 2026'!A1 -> PROCESOS ADMINISTRATIVOS / SEGURIDAD Y SALUD EN EL TRABAJO | R7: META | T7: ='Tablero indicadores 2026'!W7 -> 0
A9: FORMULA | E9: ='Tablero indicadores 2026'!M7 -> SI/NO | R9: FRECUENCIA DE MEDICIÓN | T9: TRIMESTRAL
A11: UNIDAD | E11: ='Tablero indicadores 2026'!I7 -> Cumplimiento | R11: TIPO INDICADOR | T11: ='Tablero indicadores 2026'!A7 -> ESTRUCTURA
A13: RESPONSABLE MEDICIÓN | E13: ='Tablero indicadores 2026'!G7 -> Líder Funcional SG SST | R13: VIGENCIA | T13: 2026
A17: PARAMETROS | E17: Enero | F17: Febrero | G17: Marzo | H17: Abril | I17: Mayo | J17: Junio | K17: Julio | L17: Agosto | M17: Septiembre | N17: Octubre | O17: Noviembre | P17: Diciembre | R17: OBSERVACIONES: Asignación de recursos para el sg sst, verificar con jefe de compras.
A19: Numerador | E19: 1 | G19: 1 | J19: 1
A20: Denominador | E20: 1 | G20: 1 | J20: 1 | M20: 1 | P20: 1
A22: Rango Mayor (Meta) | E22: 1 | G22: 1 | J22: 1 | M22: 1 | P22: 1 | Q22: =#REF! -> #REF!
A24: Rango Menor | E24: 0 | G24: 0 | J24: 0 | M24: 0 | P24: 0
A26: Avance | E26: =E19/E20 -> 1 | G26: =G19/G20 -> 1 | J26: =J19/J20 -> 1 | M26: =M19/M20 -> 0 | P26: =P19/P20 -> 0
C31: ANÁLISIS | I31: ACCIÓN A SEGUIR
C32: Definir y asignar el talento humano, los recursos financieros, técnicos y tecnológicos, requeridos para la implementación, mantenimiento y continuidad del Sistema de Gestión de SST. | I32: Asignar recursos para el Sistema de Gestión en SST firmado
C33: FECHA SEGUIMIENTO | I33: SEGUIMIENTO A LA IMPLEMENTACIÓN
C34: 46057 | F34: Definición y asignación de recursos para el SST | I34: Se ha constatado la asignación de recursos para el Sistema de Gestión en Seguridad y Salud en el Trabajo (SST). Se llevará a cabo una revisión trimestral de dicha asignación en concordancia con lo planificado por el área de compras, con el fin de efectuar un seguimiento. Además, se realizará un análisis semestral de la información recibida.
C35: 46111 | F35: Seguimiento a los recursos de acuerdo a lo planeado con el área de compras
C36: 46202 | F36: Seguimiento a los recursos de acuerdo a lo planeado con el área de compras
C37: 46295 | F37: Seguimiento a los recursos de acuerdo a lo planeado con el área de compras
C38: 46360 | F38: Seguimiento a los recursos de acuerdo a lo planeado con el área de compras
C39: RESPONSABLE
C40: ='Tablero indicadores 2026'!G7 -> Líder Funcional SG SST

Sheet 6
A1: PROCESOS ADMINISTRATIVOS / SEGURIDAD Y SALUD EN EL TRABAJO
A2: INDICADORES DE GESTION
A3: CODIGO | C3: RE-RH-37-SST | D3: NIVEL DE CLASIFICACIÓN | G3: USO INTERNO (NC2) | K3: VERSION | L3: 0.2
A5: NOMBRE DEL INDICADOR | E5: ='Tablero indicadores 2026'!B12 -> 6. Metodologia para identificación de peligros, evaluación y valoración de riesgos e Identificación de peligros y evaluación y valoración de reisgos con riesgos con participación de todos los niveles de la empresa.
A7: PROCESO | E7: ='Tablero indicadores 2026'!A1 -> PROCESOS ADMINISTRATIVOS / SEGURIDAD Y SALUD EN EL TRABAJO | R7: META | T7: ='Tablero indicadores 2026'!W7 -> 0
A9: FORMULA | E9: ='Tablero indicadores 2026'!M7 -> SI/NO | R9: FRECUENCIA DE MEDICIÓN | T9: ='Tablero indicadores 2026'!H10 -> Anual
A11: UNIDAD | E11: ='Tablero indicadores 2026'!I7 -> Cumplimiento | R11: TIPO INDICADOR | T11: ='Tablero indicadores 2026'!A7 -> ESTRUCTURA
A13: RESPONSABLE MEDICIÓN | E13: ='Tablero indicadores 2026'!G7 -> Líder Funcional SG SST | R13: VIGENCIA | T13: 2026
A17: PARAMETROS | E17: Enero | F17: Febrero | G17: Marzo | H17: Abril | I17: Mayo | J17: Junio | K17: Julio | L17: Agosto | M17: Septiembre | N17: Octubre | O17: Noviembre | P17: Diciembre | R17: OBSERVACIONES: Metodo definido para la identificación de peligros e instrumento para reportar condiciones peligrosas y participación de los trabajadores en la identificación de peligros, evaluación y valoración de los riesgos.
A19: Numerador | I19: 1
A20: Denominador | I20: 1
A22: Rango Mayor (Meta) | I22: 1 | Q22: =#REF! -> #REF!
A24: Rango Menor | I24: 0
A26: Avance | I26: =I19/I20 -> 1
C31: ANÁLISIS | I31: ACCIÓN A SEGUIR
C32: Definir y aplicar una metodología para la identificación de peligros y evaluación y valoración de los riesgos de origen físico, ergonómico o biomecánico, biológico, químico, de seguridad, público, psicosocial, entre otros, con alcance sobre todos los procesos, actividades rutinarias y no rutinarias, maquinaria y equipos en todos los centros de trabajo y respecto de todos los trabajadores independientemente de su forma de vinculación y/o contratación. Identificar con base en la valoración de los riesgos, aquellos que son prioritarios. | I32: _Solicitar el documento que contiene la metodología. _ Verificar que se realiza la identificación de peligros, evaluación y valoración de los riesgos conforme a la metodología definida de acuerdo con el criterio y con la participación de los trabajadores, seleccionando de manera aleatoria algunas de las actividades identificadas. _Confrontar mediante observación directa durante el recorrido a las instalaciones de la empresa la identificación de peligros.
C33: Identificación de peligros y evaluación y valoración de riesgos con participación de todos los niveles de la empresa | I33: Realizar la identificación de peligros y evaluación y valoración de los riesgos con participación de los trabajadores de todos los niveles de la empresa y actualizarla como mínimo una (1) vez al año y cada vez que ocurra un accidente de trabajo mortal o un evento catastrófico en la empresa o cuando se presenten cambios en los procesos, en las instalaciones, o maquinaria o equipos.
C34: FECHA SEGUIMIENTO | I34: SEGUIMIENTO A LA IMPLEMENTACIÓN
C35: 46300 | F35: Revisión de documento que contiene la metodología IPERV | I35: _ Revisar si la identificación de peligros, evaluación y valoración de los riesgos se debe actualizar de acuerdo al criterio y participación de los trabajadores. _ Realizar la identificación de peligro y valoración de los riesgos de acuerdo a la participación de los trabajadores de todos los niveles de la empresa.
C36: 46330 | F36: Realizar la participación de los trabajadores de todos los niveles de la empresa.
C37: RESPONSABLE
C38: ='Tablero indicadores 2026'!G7 -> Líder Funcional SG SST

Sheet 7
A1: PROCESOS ADMINISTRATIVOS / SEGURIDAD Y SALUD EN EL TRABAJO
A2: INDICADORES DE GESTION
A3: CODIGO | C3: RE-RH-37-SST | D3: NIVEL DE CLASIFICACIÓN | G3: USO INTERNO (NC2) | K3: VERSION | L3: 0.2
A5: NOMBRE DEL INDICADOR | E5: ='Tablero indicadores 2026'!B13 -> 7. Conformación y funcionamiento del copasst y capacitación de los integrantes
A7: PROCESO | E7: ='Tablero indicadores 2026'!A1 -> PROCESOS ADMINISTRATIVOS / SEGURIDAD Y SALUD EN EL TRABAJO | R7: META | T7: ='Tablero indicadores 2026'!W7 -> 0
A9: FORMULA | E9: ='Tablero indicadores 2026'!M7 -> SI/NO | R9: FRECUENCIA DE MEDICIÓN | T9: ='Tablero indicadores 2026'!H13 -> Mensual
A11: UNIDAD | E11: ='Tablero indicadores 2026'!I7 -> Cumplimiento | R11: TIPO INDICADOR | T11: ='Tablero indicadores 2026'!A7 -> ESTRUCTURA
A13: RESPONSABLE MEDICIÓN | E13: ='Tablero indicadores 2026'!G7 -> Líder Funcional SG SST | R13: VIGENCIA | T13: 2026
A17: PARAMETROS | E17: Enero | F17: Febrero | G17: Marzo | H17: Abril | I17: Mayo | J17: Junio | K17: Julio | L17: Agosto | M17: Septiembre | N17: Octubre | O17: Noviembre | P17: Diciembre | R17: OBSERVACIONES: Se cuenta con un COPASST en funcionamiento y con delegación de funciones.
A19: Numerador | E19: 1 | F19: 1 | G19: 1 | H19: 1 | I19: 1 | J19: 1
A20: Denominador | E20: 1 | F20: 1 | G20: 1 | H20: 1 | I20: 1 | J20: 1 | K20: 1 | L20: 1 | M20: 1 | N20: 1 | O20: 1 | P20: 1
A22: Rango Mayor (Meta) | E22: 1 | F22: 1 | G22: 1 | H22: 1 | I22: 1 | J22: 1 | K22: 1 | L22: 1 | M22: 1 | N22: 1 | O22: 1 | P22: 1 | Q22: =#REF! -> #REF!
A24: Rango Menor | E24: 0 | F24: 0 | G24: 0 | H24: 0 | I24: 0 | J24: 0 | K24: 0 | L24: 0 | M24: 0 | N24: 0 | O24: 0 | P24: 0
A26: Avance | E26: =E19/E20 -> 1 | F26: =F19/F20 -> 1 | G26: =G19/G20 -> 1 | H26: =H19/H20 -> 1 | I26: =I19/I20 -> 1 | J26: =J19/J20 -> 1 | K26: =K19/K20 -> 0 | L26: =L19/L20 -> 0 | ... P26: =P19/P20 -> 0
C31: ANÁLISIS | I31: ACCIÓN A SEGUIR
C32: Conformar y garantizar el funcionamiento del Comité paritario de Seguridad y Salud en el Trabajo y capacitar a los (sic) integrantes del copasst para el cumplimiento efectivo de las responsabilidades que le asigna la ley. | I32: _ Solicitarlos soportes de convocatoria, elección, conformación del comité Paritario de Seguridad y Salud en el trabajo y el acta de constitución. _Constatar si es igual el número de representante del empleador y de los trabajadores y revisar si el acta de conformación se encuentra vigente. _ Solicitar las actas de reunión mensuales del último año del Comité Paritario y verificar el cumplimiento de sus funciones. _Solicitar documentos que evidencien las actividades de capacitación brindada a los integrantes del COPASST.
C33: FECHA SEGUIMIENTO | I33: SEGUIMIENTO A LA IMPLEMENTACIÓN
C34: 46052 | F34: Revisión de acta de reunión mes enero | I34: Acta realizada
C35: 46080 | F35: Revisión de acta de reuinión mes febrero y capacitación de funciones y responsabilidades
C36: 46112 | F36: Revisión acta de reunión y evaluación identificación de peligros y valoración de riesgos
C37: 46142 | F37: Revisión acta de reunión y evaluación identificación de peligros y valoración de riesgos
C38: 46171 | F38: Revisión acta de reunión y evaluación identificación de peligros y valoración de riesgos
C39: 46203 | F39: Revisión acta de reunión y evaluación identificación de peligros y valoración de riesgos
C40: 46234 | F40: Revisión acta de reunión y evaluación identificación de peligros y valoración de riesgos
C41: 46265 | F41: Revisión acta de reunión y evaluación identificación de peligros y valoración de riesgos
C42: 46295 | F42: Revisión acta de reunión y evaluación identificación de peligros y valoración de riesgos
C43: 46325 | F43: Revisión acta de reunión y evaluación identificación de peligros y valoración de riesgos
C44: 46356 | F44: Revisión acta de reunión y evaluación identificación de peligros y valoración de riesgos
C45: 46387
C46: RESPONSABLE
C47: ='Tablero indicadores 2026'!G7 -> Líder Funcional SG SST

Sheet 8
A1: PROCESOS ADMINISTRATIVOS / SEGURIDAD Y SALUD EN EL TRABAJO
A2: INDICADORES DE GESTION
A3: CODIGO | C3: RE-RH-37-SST | D3: NIVEL DE CLASIFICACIÓN | G3: USO INTERNO (NC2) | K3: VERSION | L3: 0.2
A5: NOMBRE DEL INDICADOR | E5: ='Tablero indicadores 2026'!B14 -> 8. Documentación
A7: PROCESO | E7: ='Tablero indicadores 2026'!A1 -> PROCESOS ADMINISTRATIVOS / SEGURIDAD Y SALUD EN EL TRABAJO | R7: META | T7: ='Tablero indicadores 2026'!W7 -> 0
A9: FORMULA | E9: ='Tablero indicadores 2026'!M7 -> SI/NO | R9: FRECUENCIA DE MEDICIÓN | T9: ='Tablero indicadores 2026'!H10 -> Anual
A11: UNIDAD | E11: ='Tablero indicadores 2026'!I7 -> Cumplimiento | R11: TIPO INDICADOR | T11: ='Tablero indicadores 2026'!A7 -> ESTRUCTURA
A13: RESPONSABLE MEDICIÓN | E13: ='Tablero indicadores 2026'!G7 -> Líder Funcional SG SST | R13: VIGENCIA | T13: 2026
A17: PARAMETROS | E17: Enero | F17: Febrero | G17: Marzo | H17: Abril | I17: Mayo | J17: Junio | K17: Julio | L17: Agosto | M17: Septiembre | N17: Octubre | O17: Noviembre | P17: Diciembre | R17: OBSERVACIONES: Cumplimiento con la documentación del SGSST.
A19: Numerador
A20: Denominador | P20: 1
A22: Rango Mayor (Meta) | P22: 1 | Q22: =#REF! -> #REF!
A24: Rango Menor | P24: 0
A26: Avance | P26: =P19/P20 -> 0
C31: ANÁLISIS | I31: ACCIÓN A SEGUIR
C32: Contar con un sistema de archivoy retención documental, para los registros y documentos que soportane el Sistema de Gestión de SST | I32: _Constatar la existencia de un sistema de archivo y retención documental, para los registros y documentos que soportan el Sistema de Gestión de SST. _Verificar mediante muestreo que los registros y documentos sean legibles (entendible para el lector objeto), fácilmente identificables y accesibles (para todos los que estén vinculados con cada documento en particular), protegidos contra daño y pérdida
C33: FECHA SEGUIMIENTO | I33: SEGUIMIENTO A LA IMPLEMENTACIÓN
C34: 46360 | F34: Revisar si a existido cambio en el procedimiento control de documentos área de calidad y constatar el archivo de retención documental por 20 años. | I34: Revisar que el sistema de archivo y retención documental, para los registros y documentos que soportan el Sistema de Gestión de SST no tenga ninguna novedad.
C35: RESPONSABLE
C36: ='Tablero indicadores 2026'!G7 -> Líder Funcional SG SST

Sheet 9
A1: PROCESOS ADMINISTRATIVOS / SEGURIDAD Y SALUD EN EL TRABAJO
A2: INDICADORES DE GESTION
A3: CODIGO | C3: RE-RH-37-SST | D3: NIVEL DE CLASIFICACIÓN | G3: USO INTERNO (NC2) | K3: VERSION | L3: 0.2
A5: NOMBRE DEL INDICADOR | E5: ='Tablero indicadores 2026'!B15 -> 9. Diagnostico de condiciones
A7: PROCESO | E7: ='Tablero indicadores 2026'!A1 -> PROCESOS ADMINISTRATIVOS / SEGURIDAD Y SALUD EN EL TRABAJO | R7: META | T7: ='Tablero indicadores 2026'!W7 -> 0
A9: FORMULA | E9: ='Tablero indicadores 2026'!M7 -> SI/NO | R9: FRECUENCIA DE MEDICIÓN | T9: ='Tablero indicadores 2026'!H10 -> Anual
A11: UNIDAD | E11: ='Tablero indicadores 2026'!I7 -> Cumplimiento | R11: TIPO INDICADOR | T11: ='Tablero indicadores 2026'!A7 -> ESTRUCTURA
A13: RESPONSABLE MEDICIÓN | E13: ='Tablero indicadores 2026'!G7 -> Líder Funcional SG SST | R13: VIGENCIA | T13: 2026
A17: PARAMETROS | E17: Enero | F17: Febrero | G17: Marzo | H17: Abril | I17: Mayo | J17: Junio | K17: Julio | L17: Agosto | M17: Septiembre | N17: Octubre | O17: Noviembre | P17: Diciembre | R17: OBSERVACIONES: Procedimiento para realización de examenes medicos y diagnosticos de la condiciones de salud.
A19: Numerador
A20: Denominador | P20: 1
A22: Rango Mayor (Meta) | P22: 1 | Q22: =#REF! -> #REF!
A24: Rango Menor | P24: 0
A26: Avance | P26: =P19/P20 -> 0
C31: ANÁLISIS | I31: ACCIÓN A SEGUIR
C32: Procedimiento para efectuar el diagnostico de condiciones de salud de los trabajadores | I32: Evidencia del procedimiento para realizaciòn de examenes médicos y diagnóstico de las condiciones de salud
C33: FECHA SEGUIMIENTO | I33: SEGUIMIENTO A LA IMPLEMENTACIÓN
C34: 46360 | F34: Revisar si a existido cambio en el procedimiento control de documentos área de calidad y constatar el archivo de retención documental por 20 años. | I34: Revisar la evidencia del procedimiento para la realización de examenes medicos y diagnostico de con las condiciones de salud.
C35: RESPONSABLE
C36: ='Tablero indicadores 2026'!G7 -> Líder Funcional SG SST

Sheet 10
A1: PROCESOS ADMINISTRATIVOS / SEGURIDAD Y SALUD EN EL TRABAJO
A2: INDICADORES DE GESTION
A3: CODIGO | C3: RE-RH-37-SST | D3: NIVEL DE CLASIFICACIÓN | G3: USO INTERNO (NC2) | K3: VERSION | L3: 0.2
A5: NOMBRE DEL INDICADOR | E5: ='Tablero indicadores 2026'!B16 -> 10. Plan de emergencias
A7: PROCESO | E7: ='Tablero indicadores 2026'!A1 -> PROCESOS ADMINISTRATIVOS / SEGURIDAD Y SALUD EN EL TRABAJO | R7: META | T7: ='Tablero indicadores 2026'!W7 -> 0
A9: FORMULA | E9: ='Tablero indicadores 2026'!M7 -> SI/NO | R9: FRECUENCIA DE MEDICIÓN | T9: ='Tablero indicadores 2026'!H10 -> Anual
A11: UNIDAD | E11: ='Tablero indicadores 2026'!I16 -> Número | R11: TIPO INDICADOR | T11: ='Tablero indicadores 2026'!A7 -> ESTRUCTURA
A13: RESPONSABLE MEDICIÓN | E13: ='Tablero indicadores 2026'!G7 -> Líder Funcional SG SST | R13: VIGENCIA | T13: 2026
A17: PARAMETROS | E17: Enero | F17: Febrero | G17: Marzo | H17: Abril | I17: Mayo | J17: Junio | K17: Julio | L17: Agosto | M17: Septiembre | N17: Octubre | O17: Noviembre | P17: Diciembre | R17: OBSERVACIONES: Existencia de plan de emergencia en las sedes.
A19: Numerador | J19: 9
A20: Denominador | J20: 12 | O20: 8
A22: Rango Mayor (Meta) | J22: 1 | O22: 1 | Q22: =#REF! -> #REF!
A24: Rango Menor | J24: 0 | O24: 0
A26: Avance | J26: =J19/J20 -> 0.75 | O26: =O19/O20 -> 0
C31: ANÁLISIS | I31: ACCIÓN A SEGUIR
C32: _Elaborar un plan de prevención, preparación y respuesta ante emergencias que identifique las amenazas, evalúe y analice la vulnerabilidad. _Como mínimo el plan debe incluir: planos de las instalaciones que identifican áreas y salidas de emergencia, así como la señalización, realización de simulacros como mínimo una (1) vez al año. _El plan debe tener en cuenta todas las jornadas de trabajo en todos los centros de trabajo y debe ser divulgado. | I32: _Solicitar el plan de prevención, preparación y respuesta ante emergencias y constatar evidencias de su divulgación. _Verificar si existen los planos de las instalaciones que identifican áreas y salidas de emergencia y verificar si existe la debida señalización de la empresa. _Verificar los soportes que evidencien la realización de los simulacros y análisis de los mismos y validar que las recomendaciones emitidas con base en dicho análisis hayan sido tenidas en cuenta en el mejoramiento del plan de emergencias.
C33: FECHA SEGUIMIENTO | I33: SEGUIMIENTO A LA IMPLEMENTACIÓN
C34: 46178 | F34: Divulgación del plan de emergencias
C35: 46304 | F35: Simulacro a nivel nacional y participación | I35: Verificar los soportes que evidencien la realización de los simulacros y divulgación del plan de emergencias en las diferentes sedes.
C36: RESPONSABLE
C37: ='Tablero indicadores 2026'!G7 -> Líder Funcional SG SST

Sheet 11
A1: PROCESOS ADMINISTRATIVOS / SEGURIDAD Y SALUD EN EL TRABAJO
A2: INDICADORES DE GESTION
A3: CODIGO | C3: RE-RH-37-SST | D3: NIVEL DE CLASIFICACIÓN | G3: USO INTERNO (NC2) | K3: VERSION | L3: 0.2
A5: NOMBRE DEL INDICADOR | E5: ='Tablero indicadores 2026'!B17 -> 11. Plan de Capacitación en SST
A7: PROCESO | E7: ='Tablero indicadores 2026'!A1 -> PROCESOS ADMINISTRATIVOS / SEGURIDAD Y SALUD EN EL TRABAJO | R7: META | T7: ='Tablero indicadores 2026'!W7 -> 0
A9: FORMULA | E9: SI/NO | R9: FRECUENCIA DE MEDICIÓN | T9: ='Tablero indicadores 2026'!H17 -> Mensual
A11: UNIDAD | E11: ='Tablero indicadores 2026'!I7 -> Cumplimiento | R11: TIPO INDICADOR | T11: ='Tablero indicadores 2026'!A7 -> ESTRUCTURA
A13: RESPONSABLE MEDICIÓN | E13: ='Tablero indicadores 2026'!G7 -> Líder Funcional SG SST | R13: VIGENCIA | T13: 2026
A17: PARAMETROS | E17: Enero | F17: Febrero | G17: Marzo | H17: Abril | I17: Mayo | J17: Junio | K17: Julio | L17: Agosto | M17: Septiembre | N17: Octubre | O17: Noviembre | P17: Diciembre | R17: OBSERVACIONES:Evidencia de un plan de capacitacion en SST
A19: Numerador | E19: 5 | F19: 18 | G19: 22 | H19: 42 | I19: 17 | J19: 20 | K19: 16
A20: Denominador | E20: 5 | F20: 18 | G20: 22 | H20: 42 | I20: 21 | J20: 25 | K20: 16 | L20: 20 | M20: 24 | N20: 15 | O20: 9 | P20: 6
A22: Rango Mayor (Meta) | E22: 1 | F22: 1 | G22: 1 | H22: 1 | I22: 1 | J22: 1 | K22: 1 | L22: 1 | M22: 1 | N22: 1 | O22: 1 | P22: 1 | Q22: =#REF! -> #REF!
A24: Rango Menor | E24: 0 | F24: 0 | G24: 0 | H24: 0 | I24: 0 | J24: 0 | K24: 0 | L24: 0 | M24: 0 | N24: 0 | O24: 0 | P24: 0
A26: Avance | E26: =E19/E20 -> 1 | F26: =F19/F20 -> 1 | G26: =G19/G20 -> 1 | H26: =H19/H20 -> 1 | I26: =I19/I20 -> 0.80952381 | J26: =J19/J20 -> 0.8 | K26: =K19/K20 -> 1 | L26: =L19/L20 -> 0 | ... P26: =P19/P20 -> 0
C32: ANÁLISIS | I32: ACCIÓN A SEGUIR
C33: Elaborar y ejecutar el programa de capacitación en promoción y prevención, que incluye lo referente a los peligros/riesgos prioritarios y las medidas de prevención y control, extensivo a todos los niveles de la organización. | I33: Solicitar el programa de capacitación anual y la matriz de identificación de peligros y verificar que el mismo esté dirigido a los peligros ya identificados y esté acorde con la evaluación y control de los riesgos y/o necesidades en Seguridad y Salud en el Trabajo. Solicitar los documentos que evidencien el cumplimiento del programa de capacitación.
C34: FECHA SEGUIMIENTO | I34: SEGUIMIENTO A LA IMPLEMENTACIÓN
C35: 46056 | F35: Verificar que las capacitaciónes se halla ejecutado | I35: Se verifica la realización de la capacitación planeada
C36: 46080 | F36: Verificar que las capacitaciónes se halla ejecutado | I36: Se verifica la realización de la capacitación planeada
C37: 46112 | F37: Verificar que las capacitaciónes se halla ejecutado | I37: Se verifica la realización de la capacitación planeada
C38: 46142 | F38: Verificar que las capacitaciónes se halla ejecutado | I38: Se verifica la realización de la capacitación planeada
C39: 46171 | F39: Verificar que las capacitaciónes se halla ejecutado | I39: Se verifica la realización de la capacitación planeada
C40: 46203 | F40: Verificar que las capacitaciónes se halla ejecutado | I40: Se verifica la realización de la capacitación planeada
C41: 46234 | F41: Verificar que las capacitaciónes se halla ejecutado
C42: 46265 | F42: Verificar que las capacitaciónes se halla ejecutado
C43: 46295 | F43: Verificar que las capacitaciónes se halla ejecutado
C44: 46325 | F44: Verificar que las capacitaciónes se halla ejecutado
C45: 46356 | F45: Verificar que las capacitaciónes se halla ejecutado
C46: 46360 | F46: Verificar que las capacitaciónes se halla ejecutado
C47: RESPONSABLE | I47: Ejecutar el programa de capacitación acorde a los peligros/riesgos prioritatios y las medidas de prevención y control de la empresa
C48: ='Tablero indicadores 2026'!G8 -> Líder Funcional SG SST

Sheet 1.
A1: PROCESOS ADMINISTRATIVOS / SEGURIDAD Y SALUD EN EL TRABAJO
A2: INDICADORES DE GESTION
A3: CODIGO | C3: RE-RH-37-SST | D3: NIVEL DE CLASIFICACIÓN | G3: USO INTERNO (NC2) | K3: VERSION | L3: 0.2
A5: NOMBRE DEL INDICADOR | E5: ='Tablero indicadores 2026'!B19 -> 1. Evaluacion Inicial
A7: PROCESO | E7: ='Tablero indicadores 2026'!A1 -> PROCESOS ADMINISTRATIVOS / SEGURIDAD Y SALUD EN EL TRABAJO | R7: META | T7: ='Tablero indicadores 2026'!L19 -> 0.9
A9: FORMULA | E9: ='Tablero indicadores 2026'!M7 -> SI/NO | R9: FRECUENCIA DE MEDICIÓN | T9: ='Tablero indicadores 2026'!H19 -> Anual
A11: UNIDAD | E11: ='Tablero indicadores 2026'!I19 -> Porcentaje | R11: TIPO INDICADOR | T11: ='Tablero indicadores 2026'!A19 -> PROCESO
A13: RESPONSABLE MEDICIÓN | E13: ='Tablero indicadores 2026'!G7 -> Líder Funcional SG SST | R13: VIGENCIA | T13: 2026
A17: PARAMETROS | E17: Enero | F17: Febrero | G17: Marzo | H17: Abril | I17: Mayo | J17: Junio | K17: Julio | L17: Agosto | M17: Septiembre | N17: Octubre | O17: Noviembre | P17: Diciembre | R17: OBSERVACIONES: Sumatoria de porcentaje por cada uno de los items evaluados que se encuentren en avanzado / numero de items evaluados.
A19: Numerador
A20: Denominador | P20: 100
A22: Rango Mayor (Meta) | P22: 1 | Q22: =#REF! -> #REF!
A24: Rango Menor | P24: 0
A26: Avance | P26: =P19/P20 -> 0
C32: ANÁLISIS | I32: ACCIÓN A SEGUIR
C33: _Realizar la evaluación inicial del Sistema de Gestión de SST, identificando las prioridades para establecer el plan de trabajo anual o para la actualización del existente. _Debe ser realizada por el responsable del Sistema de Gestión de SST o contratada por la empresa con personal externo con licencia en Seguridad y Salud en el Trabajo. | I33: Solicitar la evaluación inicial del Sistema de Gestión de SST mediante la matriz legal, matriz de peligros y evaluación de riesgos, verificación de controles, lista de asistencia a capacitaciones, análisis de puestos de trabajo, exámenes médicos de ingreso y periódicos y seguimiento de indicadores, entre otros.
C34: FECHA SEGUIMIENTO | I34: SEGUIMIENTO A LA IMPLEMENTACIÓN
C35: 45997 | F35: Realizar evaluación Final SST | I35: Se realiza la evaluación final generando acciones de mejora en los siguientes items : 4.1.4 Realización mediciones ambientales, químicos, físicos y biológicos y 3.1.7 Estilos de vida y entornos saludables (controles tabaquismo, alcoholismo, farmacodependencia y otros)
C36: 46024 | F36: Realizar evaluación Inical SST
C37: RESPONSABLE | I37: Verificar que se realicen las acciones de mejora de acuerdo al resultado de los estandares
C38: ='Tablero indicadores 2026'!G8 -> Líder Funcional SG SST

Sheet 2.
A1: PROCESOS ADMINISTRATIVOS / SEGURIDAD Y SALUD EN EL TRABAJO
A2: INDICADORES DE GESTION
A3: CODIGO | C3: RE-RH-37-SST | D3: NIVEL DE CLASIFICACIÓN | G3: USO INTERNO (NC2) | K3: VERSION | L3: 0.2
A5: NOMBRE DEL INDICADOR | E5: ='Tablero indicadores 2026'!B20 -> 2. Ejecución del plan de trabajo
A7: PROCESO | E7: ='Tablero indicadores 2026'!A1 -> PROCESOS ADMINISTRATIVOS / SEGURIDAD Y SALUD EN EL TRABAJO | R7: META | T7: ='Tablero indicadores 2026'!L20 -> 0.9
A9: FORMULA | E9: ='Tablero indicadores 2026'!M7 -> SI/NO | R9: FRECUENCIA DE MEDICIÓN | T9: ='Tablero indicadores 2026'!H20 -> Semestral
A11: UNIDAD | E11: ='Tablero indicadores 2026'!I20 -> Porcentaje | R11: TIPO INDICADOR | T11: ='Tablero indicadores 2026'!A19 -> PROCESO
A13: RESPONSABLE MEDICIÓN | E13: ='Tablero indicadores 2026'!G7 -> Líder Funcional SG SST | R13: VIGENCIA | T13: 2026
A17: PARAMETROS | E17: Enero | F17: Febrero | G17: Marzo | H17: Abril | I17: Mayo | J17: Junio | K17: Julio | L17: Agosto | M17: Septiembre | N17: Octubre | O17: Noviembre | P17: Diciembre | R17: OBSERVACIONES: ( N° de actividades desarrolladas en el periodo en el plan / nro de actividades propuestas en el periodo en el plan de trabajo) x 100
A19: Numerador
A20: Denominador | J20: 353 | P20: 390
A22: Rango Mayor (Meta) | J22: 1 | P22: 1 | Q22: =#REF! -> #REF!
A24: Rango Menor | J24: 0 | P24: 0
A26: Avance | J26: =J19/J20 -> 0 | P26: =P19/P20 -> 0
C32: ANÁLISIS | I32: ACCIÓN A SEGUIR
C33: Diseñar y definir un plan anual de trabajo para el cumplimiento del Sistema de Gestión de SST, el cual identifica los objetivos, metas, responsabilidades, recursos, cronograma de actividades, firmado por el empleador y el responsable del Sistema de Gestión de SST. | I33: Solicitar el plan de trabajo anual. Verificar el cumplimiento del mismo. En el caso que se hayan presentado incumplimientos al plan, solicitar los planes de mejora respectivos.
C34: FECHA SEGUIMIENTO | I34: SEGUIMIENTO A LA IMPLEMENTACIÓN
C35: 46360 | F35: Realizar plan de trabajo | I35: Diseñar y defenir un plan de trabajo para el cumplimiento del Sistema de Gestión SST, el cual debe tener los objetivos, metas, responsabilidades, recursos, cronograma de actividades, firmado por el empleador y el responsable del Sistema de Gestión de SST.
C36: RESPONSABLE | I36: Revisar que plan de trabajo se cumpla con lo establecido de acuerdo a lo planeado
C37: ='Tablero indicadores 2026'!G8 -> Líder Funcional SG SST

Sheet 3.
A1: PROCESOS ADMINISTRATIVOS / SEGURIDAD Y SALUD EN EL TRABAJO
A2: INDICADORES DE GESTION
A3: CODIGO | C3: RE-RH-37-SST | D3: NIVEL DE CLASIFICACIÓN | G3: USO INTERNO (NC2) | K3: VERSION | L3: 0.2
A5: NOMBRE DEL INDICADOR | E5: ='Tablero indicadores 2026'!B21 -> 3. Ejecución del plan de capacitaciòn
A7: PROCESO | E7: ='Tablero indicadores 2026'!A1 -> PROCESOS ADMINISTRATIVOS / SEGURIDAD Y SALUD EN EL TRABAJO | R7: META | T7: ='Tablero indicadores 2026'!L20 -> 0.9
A9: FORMULA | E9: ='Tablero indicadores 2026'!M7 -> SI/NO | R9: FRECUENCIA DE MEDICIÓN | T9: ='Tablero indicadores 2026'!H21 -> Semestral
A11: UNIDAD | E11: ='Tablero indicadores 2026'!I20 -> Porcentaje | R11: TIPO INDICADOR | T11: ='Tablero indicadores 2026'!A19 -> PROCESO
A13: RESPONSABLE MEDICIÓN | E13: ='Tablero indicadores 2026'!G7 -> Líder Funcional SG SST | R13: VIGENCIA | T13: 2026
A17: PARAMETROS | E17: Enero | F17: Febrero | G17: Marzo | H17: Abril | I17: Mayo | J17: Junio | K17: Julio | L17: Agosto | M17: Septiembre | N17: Octubre | O17: Noviembre | P17: Diciembre | R17: OBSERVACIONES: ( N° de actividades desarrolladas en el periodo en el plan / nro de capacitaciones propuestas en el periodo en el plan de capacitación ) x 100
A19: Numerador | J19: 133
A20: Denominador | J20: 133 | P20: 25
A22: Rango Mayor (Meta) | J22: 1 | P22: 1 | Q22: =#REF! -> #REF!
A24: Rango Menor | J24: 0 | P24: 0
A26: Avance | J26: =J19/J20 -> 1 | P26: =P19/P20 -> 0
C32: ANÁLISIS | I32: ACCIÓN A SEGUIR
C33: Elaborar y ejecutar el programa de capacitación en promoción y prevención, que incluye lo referente a los peligros/riesgos prioritarios y las medidas de prevención y control, extensivo a todos los niveles de la organización. | I33: Solicitar el programa de capacitación anual y la matriz de identificación de peligros y verificar que el mismo esté dirigido a los peligros ya identificados y esté acorde con la evaluación y control de los riesgos y/o necesidades en Seguridad y Salud en el Trabajo. Solicitar los documentos que evidencien el cumplimiento del programa de capacitación.
C34: FECHA SEGUIMIENTO | I34: SEGUIMIENTO A LA IMPLEMENTACIÓN
C35: 46360 | F35: Realizar plan de capacitación | I35: Elaborar y ejecutar el programa de capacitación en promoción y prevención, que incluye lo referente a los peligros/riesgos prioritarios y las medidas de prevención y control, extensivo a todos los niveles de la organización
C36: RESPONSABLE | I36: Revisar y adecuar plan de capacitación de acuerdo a lo enctrado en la indentifiación de peligros y riesgos
C37: ='Tablero indicadores 2026'!G8 -> Líder Funcional SG SST

Sheet 4.
A1: PROCESOS ADMINISTRATIVOS / SEGURIDAD Y SALUD EN EL TRABAJO
A2: INDICADORES DE GESTION
A3: CODIGO | C3: RE-RH-37-SST | D3: NIVEL DE CLASIFICACIÓN | G3: USO INTERNO (NC2) | K3: VERSION | L3: 0.2
A5: NOMBRE DEL INDICADOR | E5: ='Tablero indicadores 2026'!B22 -> 4. Intervención de peligros identificados
A7: PROCESO | E7: ='Tablero indicadores 2026'!A1 -> PROCESOS ADMINISTRATIVOS / SEGURIDAD Y SALUD EN EL TRABAJO | R7: META | T7: ='Tablero indicadores 2026'!L20 -> 0.9
A9: FORMULA | E9: ='Tablero indicadores 2026'!M7 -> SI/NO | R9: FRECUENCIA DE MEDICIÓN | T9: Anual
A11: UNIDAD | E11: ='Tablero indicadores 2026'!I20 -> Porcentaje | R11: TIPO INDICADOR | T11: ='Tablero indicadores 2026'!A19 -> PROCESO
A13: RESPONSABLE MEDICIÓN | E13: ='Tablero indicadores 2026'!G7 -> Líder Funcional SG SST | R13: VIGENCIA | T13: 2026
A17: PARAMETROS | E17: Enero | F17: Febrero | G17: Marzo | H17: Abril | I17: Mayo | J17: Junio | K17: Julio | L17: Agosto | M17: Septiembre | N17: Octubre | O17: Noviembre | P17: Diciembre | R17: OBSERVACIONES: N° total de peligros intervenidos en el periodo / total de peligros identificados
A19: Numerador
A20: Denominador | P20: 7
A22: Rango Mayor (Meta) | P22: 1 | Q22: =#REF! -> #REF!
A24: Rango Menor | P24: 0
A26: Avance | P26: =P19/P20 -> 0
C32: ANÁLISIS | I32: ACCIÓN A SEGUIR
C33: Realizar la identificación de peligros y evaluación y valoración de los riesgos con participación de los trabajadores de todos los niveles de la empresa y actualizarla como mínimo una (1) vez al año y cada vez que ocurra un accidente de trabajo mortal o un evento catastrófico en la empresa o cuando se presenten cambios en los procesos, en las instalaciones, o maquinaria o equipos. | I33: _Solicitar las evidencias que den cuenta de la participación de los trabajadores en la identificación de peligros, evaluación y valoración de los riesgos, así como de la realización de dicha identificación con la periodicidad señalada en el criterio. _Solicitar información acerca de si ha habido eventos mortales o catastróficos y validar que el peligro asociado al evento esté identificado, evaluado y valorado. _En los casos de que se encuentren valoraciones de riesgo no tolerable, verificar la implementación inmediata de las acciones de intervención y control.
C34: FECHA SEGUIMIENTO | I34: SEGUIMIENTO A LA IMPLEMENTACIÓN
C35: 46325 | F35: Realizar las evidencias de participación de los trabajadores en la IPERV | I35: Revisar que se halla realizado la identificación de peligros y evaluación de peligros y valoración de riesgos con la participación de los trabajdores de todos los niveles de la empresa.
C36: RESPONSABLE
C37: ='Tablero indicadores 2026'!G8 -> Líder Funcional SG SST

Sheet 5.
A1: PROCESOS ADMINISTRATIVOS / SEGURIDAD Y SALUD EN EL TRABAJO
A2: INDICADORES DE GESTION
A3: CODIGO | C3: RE-RH-37-SST | D3: NIVEL DE CLASIFICACIÓN | G3: USO INTERNO (NC2) | K3: VERSION | L3: 0.2
A5: NOMBRE DEL INDICADOR | E5: ='Tablero indicadores 2026'!B23 -> 5. Condiciones de salud
A7: PROCESO | E7: ='Tablero indicadores 2026'!A1 -> PROCESOS ADMINISTRATIVOS / SEGURIDAD Y SALUD EN EL TRABAJO | R7: META | T7: ='Tablero indicadores 2026'!L20 -> 0.9
A9: FORMULA | E9: ='Tablero indicadores 2026'!M7 -> SI/NO | R9: FRECUENCIA DE MEDICIÓN | T9: ='Tablero indicadores 2026'!H23 -> Anual
A11: UNIDAD | E11: ='Tablero indicadores 2026'!I42 -> Porcentaje | R11: TIPO INDICADOR | T11: ='Tablero indicadores 2026'!A19 -> PROCESO
A13: RESPONSABLE MEDICIÓN | E13: ='Tablero indicadores 2026'!G7 -> Líder Funcional SG SST | R13: VIGENCIA | T13: 2026
A17: PARAMETROS | E17: Enero | F17: Febrero | G17: Marzo | H17: Abril | I17: Mayo | J17: Junio | K17: Julio | L17: Agosto | M17: Septiembre | N17: Octubre | O17: Noviembre | P17: Diciembre | R17: OBSERVACIONES: Cumplimiento de evaluación de condiciones de salud.
A19: Numerador
A20: Denominador | P20: 1
A22: Rango Mayor (Meta) | P22: 1 | Q22: =#REF! -> #REF!
A24: Rango Menor | P24: 0
A26: Avance | P26: =P19/P20 -> 0
C32: ANÁLISIS | I32: ACCIÓN A SEGUIR
C33: Recolectar la siguientes información actualizada de todos los trabajadores del último año: la descripción socio demográfica de los trabajadores (edad, sexo, escolaridad, estado civil) y el diagnóstico de condiciones de salud que incluya la caracterización de sus condiciones de salud, la evaluación y análisis de las estadísticas sobre la salud de los trabajadores tanto de origen laboral como común y los resultados de las evaluaciones médicas ocupacionales. | I33: Solicitar el documento consolidado con la información socio demográfica acorde con lo requerido y el diagnóstico de condiciones de salud.
C34: FECHA SEGUIMIENTO | I34: SEGUIMIENTO A LA IMPLEMENTACIÓN
C35: 46358 | F35: Solicitar documento con la informaicón sociodemografica | I35: Revisar que se cuente con el documento con la información sociodemografica y diagnostico de salud
C36: RESPONSABLE
C37: ='Tablero indicadores 2026'!G8 -> Líder Funcional SG SST

Sheet 6.
A1: PROCESOS ADMINISTRATIVOS / SEGURIDAD Y SALUD EN EL TRABAJO
A2: INDICADORES DE GESTION
A3: CODIGO | C3: RE-RH-37-SST | D3: NIVEL DE CLASIFICACIÓN | G3: USO INTERNO (NC2) | K3: VERSION | L3: 0.2
A5: NOMBRE DEL INDICADOR | E5: ='Tablero indicadores 2026'!B24 -> 6. Acciones preventivas, correctivas y de mejora
A7: PROCESO | E7: ='Tablero indicadores 2026'!A1 -> PROCESOS ADMINISTRATIVOS / SEGURIDAD Y SALUD EN EL TRABAJO | R7: META | T7: ='Tablero indicadores 2026'!L20 -> 0.9
A9: FORMULA | E9: ='Tablero indicadores 2026'!M7 -> SI/NO | R9: FRECUENCIA DE MEDICIÓN | T9: ='Tablero indicadores 2026'!H20 -> Semestral
A11: UNIDAD | E11: ='Tablero indicadores 2026'!I20 -> Porcentaje | R11: TIPO INDICADOR | T11: ='Tablero indicadores 2026'!A19 -> PROCESO
A13: RESPONSABLE MEDICIÓN | E13: ='Tablero indicadores 2026'!G7 -> Líder Funcional SG SST | R13: VIGENCIA | T13: 2026
A17: PARAMETROS | E17: Enero | F17: Febrero | G17: Marzo | H17: Abril | I17: Mayo | J17: Junio | K17: Julio | L17: Agosto | M17: Septiembre | N17: Octubre | O17: Noviembre | P17: Diciembre | R17: OBSERVACIONES: (N° de acciones corregidas en el periodo / Nro de acciones encontradas en el periodo) x 100
A19: Numerador | J19: 13
A20: Denominador | J20: 13 | P20: 13
A22: Rango Mayor (Meta) | J22: 1 | P22: 1 | Q22: =#REF! -> #REF!
A24: Rango Menor | J24: 0 | P24: 0
A26: Avance | J26: =J19/J20 -> 1 | P26: =P19/P20 -> 0
C32: ANÁLISIS | I32: ACCIÓN A SEGUIR
C33: Definir e implementar las acciones preventivas y/o correctivas necesarias con base en los resultados de la supervisión, inspecciones, medición de los indicadores del Sistema de Gestión de SST entre otros, y las recomendaciones del COPASST. | I33: Solicitar la evidencia documental de la implementación de las acciones preventivas y/o correctivas.
C34: FECHA SEGUIMIENTO | I34: SEGUIMIENTO A LA IMPLEMENTACIÓN
C35: 46353 | F35: Realizar seguimiento a la implementación de las acciones preventivas y/o correctivas | I35: Revisar la evidencia docmental de las acciones preventivas y/o correctivas
C36: RESPONSABLE
C37: ='Tablero indicadores 2026'!G8 -> Líder Funcional SG SST

Sheet 7.
A1: PROCESOS ADMINISTRATIVOS / SEGURIDAD Y SALUD EN EL TRABAJO
A2: INDICADORES DE GESTION
A3: CODIGO | C3: RE-RH-37-SST | D3: NIVEL DE CLASIFICACIÓN | G3: USO INTERNO (NC2) | K3: VERSION | L3: 0.2
A5: NOMBRE DEL INDICADOR | E5: ='Tablero indicadores 2026'!B25 -> 7. Mediciones ambientales
A7: PROCESO | E7: ='Tablero indicadores 2026'!A1 -> PROCESOS ADMINISTRATIVOS / SEGURIDAD Y SALUD EN EL TRABAJO | R7: META | T7: ='Tablero indicadores 2026'!L20 -> 0.9
A9: FORMULA | E9: ='Tablero indicadores 2026'!M7 -> SI/NO | R9: FRECUENCIA DE MEDICIÓN | T9: ='Tablero indicadores 2026'!H25 -> Anual
A11: UNIDAD | E11: ='Tablero indicadores 2026'!I20 -> Porcentaje | R11: TIPO INDICADOR | T11: ='Tablero indicadores 2026'!A19 -> PROCESO
A13: RESPONSABLE MEDICIÓN | E13: ='Tablero indicadores 2026'!G7 -> Líder Funcional SG SST | R13: VIGENCIA | T13: 2026
A17: PARAMETROS | E17: Enero | F17: Febrero | G17: Marzo | H17: Abril | I17: Mayo | J17: Junio | K17: Julio | L17: Agosto | M17: Septiembre | N17: Octubre | O17: Noviembre | P17: Diciembre | R17: OBSERVACIONES: (Mediciones ambiental realizada / mediciones ambientales dectectadas ) x 100
A19: Numerador
A20: Denominador | L20: 1
A22: Rango Mayor (Meta) | L22: 1 | Q22: =#REF! -> #REF!
A24: Rango Menor | L24: 0
A26: Avance | L26: =L19/L20 -> 0
C32: ANÁLISIS | I32: ACCIÓN A SEGUIR
C33: Realizar mediciones ambientales de los riesgos prioritarios, provenientes de peligros químicos, físicos y/o biológicos. | I33: Verificar los soportes documentales de las mediciones ambientales realizadas y la remisión de estos resultados al Comité Paritario de Seguridad y Salud en el Trabajo.
C34: FECHA SEGUIMIENTO | I34: SEGUIMIENTO A LA IMPLEMENTACIÓN
C35: 46210 | F35: Revisar los informes realizados si ha obtenido mejoras | I35: Seguimiento a los soportes documentales de las mediciones ambientales realizadas y notificar al copasst
C36: RESPONSABLE
C37: ='Tablero indicadores 2026'!G8 -> Líder Funcional SG SST

Sheet 8.
A1: PROCESOS ADMINISTRATIVOS / SEGURIDAD Y SALUD EN EL TRABAJO
A2: INDICADORES DE GESTION
A3: CODIGO | C3: RE-RH-37-SST | D3: NIVEL DE CLASIFICACIÓN | G3: USO INTERNO (NC2) | K3: VERSION | L3: 0.2
A5: NOMBRE DEL INDICADOR | E5: ='Tablero indicadores 2026'!B26 -> 8. Vigilancia epidemiológica
A7: PROCESO | E7: ='Tablero indicadores 2026'!A1 -> PROCESOS ADMINISTRATIVOS / SEGURIDAD Y SALUD EN EL TRABAJO | R7: META | T7: 0.95
A9: FORMULA | E9: (NO. DE TRABAJADORES INTERVENIDOS EN EL SVE / NO. TRABAJADORES A INTERVENIR)*100 | R9: FRECUENCIA DE MEDICIÓN | T9: ='Tablero indicadores 2026'!H20 -> Semestral
A11: UNIDAD | E11: ='Tablero indicadores 2026'!I20 -> Porcentaje | R11: TIPO INDICADOR | T11: ='Tablero indicadores 2026'!A19 -> PROCESO
A13: RESPONSABLE MEDICIÓN | E13: ='Tablero indicadores 2026'!G7 -> Líder Funcional SG SST | R13: VIGENCIA | T13: 2026
A17: PARAMETROS | E17: Enero | F17: Febrero | G17: Marzo | H17: Abril | I17: Mayo | J17: Junio | K17: Julio | L17: Agosto | M17: Septiembre | N17: Octubre | O17: Noviembre | P17: Diciembre | R17: OBSERVACIONES: (N° de trabajadores intervenidos en el SVE / N° de trabajadores a intervenir ) x 100
A19: Numerador | J19: 34
A20: Denominador | J20: 34 | P20: 23
A22: Rango Mayor (Meta) | J22: 1 | P22: 1 | Q22: =#REF! -> #REF!
A24: Rango Menor | J24: 0 | P24: 0
A26: Avance | J26: =J19/J20 -> 1 | P26: =P19/P20 -> 0
C32: ANÁLISIS | I32: ACCIÓN A SEGUIR
C33: Desarrollar las actividades de medicina del trabajo, prevención y promoción de la salud y programas de vigilancia epidemiológica requeridos, de conformidad con las prioridades identificadas en el diagnóstico de condiciones de salud y con los peligros/riesgos prioritarios. | I33: Solicitar las evidencias que constaten la definición y ejecución de las actividades de medicina del trabajo, promoción y prevención y los programas de vigilancia epidemiológica, de conformidad con las prioridades que se identificaron con base en los resultados del diagnóstico de las condiciones de salud y los peligros/riesgos de intervención prioritarios.
C34: FECHA SEGUIMIENTO | I34: SEGUIMIENTO A LA IMPLEMENTACIÓN
C35: 46080 | F35: Revisar actividades de p y p | I35: Pausa activa ritmicas SYC NATURA (846), Pausa activa Gimnasia cerebral clt bucaramanga (14), Pausa activa cambio de emociones SYC natura (846), Pausa activa ritmicas clt bucaramanga (15), Pausas activas movimientos, sonrisas y tips de higiene postural - Arl (846)
C36: 46112 | F36: Revisar actividades de p y p | I36: Resolución 3050 de 2022 (7), Pausa activa Gimnasia cerebral SYC natura (393), Capacitación cáncer de mama (63), Pausa activa manejo estres (13), Pausa activa manejo estres presencial (302), Pausa activa manejo estres nacional (502), Pausa activa ritmicas clt bucaramanga (19)
C37: 46142 | F37: Revisar actividades de p y p | I37: Campaña visual (816), Circuito saludable semanas de la salud ARL (816), Estilos de vida salubale (816), Simulacion Sustancias Pisicoactivas (816), Píldora saludable N° 1: Capacitación de fomentos de estilos de vida y trabajo saludable (816), Diversidad e inclusión de genero (57)
C38: 46171 | F38: Revisar actividades de p y p | I38: Liderazgo efectivo: manejo de emociones y administración del tiempo (811), Capacitación medidas preventivas audición (13), Pausas activas ritmicas cuidado postural clt (18), Temor a expresar emociones por miedo a represarias (164), Píldora saludable N° 2: Capacitar a todos los trabajadores en Actividad Física mejorando el sedentarismo (365), Pausas activas ritmicas (365), Salas Amigas: Beneficios, propiedades y efectos a corto y mediano plazo de la leche materna (),
C39: 46203 | F39: Revisar actividades de p y p | I39: Campaña prevención del acoso labora y sexual (36), Empatía y resiliencia – Construir y resolver (72), Pausa activa gimnasia cerebral (10), Empatía y Resiliencia: Construyendo Soluciones y Fortaleciendo Capacidades (51), Sensibilizacion: tabaquismo, alcoholismo y farmcodependencia (380), Pausa activa gimnasia cerebral (62), Manejo de cargas y ergonomia (56), Pausa activa gimnasia cerebral (10), Campaña inteligencia emocional (45), Socialización programa de conservación visual (562), Diversidad e inclusión de genero ()
C40: 46234 | F40: Revisar actividades de p y p
C41: 46265 | F41: Revisar actividades de p y p
C42: 46295 | F42: Revisar actividades de p y p
C43: 46325 | F43: Revisar actividades de p y p
C44: 46356 | F44: Revisar actividades de p y p
C45: 46360 | F45: Revisar actividades de p y p
C46: RESPONSABLE
C47: ='Tablero indicadores 2026'!G8 -> Líder Funcional SG SST

Sheet 9.
A1: PROCESOS ADMINISTRATIVOS / SEGURIDAD Y SALUD EN EL TRABAJO
A2: INDICADORES DE GESTION
A3: CODIGO | C3: RE-RH-37-SST | D3: NIVEL DE CLASIFICACIÓN | G3: USO INTERNO (NC2) | K3: VERSION | L3: 0.2
A5: NOMBRE DEL INDICADOR | E5: ='Tablero indicadores 2026'!B27 -> 9. Investigación de accidentes, incidentes y enfermedades laborales
A7: PROCESO | E7: ='Tablero indicadores 2026'!A1 -> PROCESOS ADMINISTRATIVOS / SEGURIDAD Y SALUD EN EL TRABAJO | R7: META | T7: ='Tablero indicadores 2026'!L20 -> 0.9
A9: FORMULA | E9: N° DE AT, IT, EL INVESTIGADOS/NRO DE AT, IT, EL REPORTADOS | R9: FRECUENCIA DE MEDICIÓN | T9: ='Tablero indicadores 2026'!H20 -> Semestral
A11: UNIDAD | E11: ='Tablero indicadores 2026'!I20 -> Porcentaje | R11: TIPO INDICADOR | T11: ='Tablero indicadores 2026'!A19 -> PROCESO
A13: RESPONSABLE MEDICIÓN | E13: ='Tablero indicadores 2026'!G7 -> Líder Funcional SG SST | R13: VIGENCIA | T13: 2026
A17: PARAMETROS | E17: Enero | F17: Febrero | G17: Marzo | H17: Abril | I17: Mayo | J17: Junio | K17: Julio | L17: Agosto | M17: Septiembre | N17: Octubre | O17: Noviembre | P17: Diciembre | R17: OBSERVACIONES: (N° de AT, IT y EL investigados / N° de AT, IT y EL reportados ) x 100
A19: Numerador | J19: 2
A20: Denominador | J20: 2 | P20: 0
A22: Rango Mayor (Meta) | J22: 1 | P22: 1 | Q22: =#REF! -> #REF!
A24: Rango Menor | J24: 0 | P24: 0
A26: Avance | J26: =J19/J20 -> 1 | P26: =P19/P20 -> #DIV/0!
C32: ANÁLISIS | I32: ACCIÓN A SEGUIR
C33: Investigar los incidentes y todos los accidentes de trabajo y las enfermedades cuando sean diagnosticadas como laborales con la participación del COPASST, determinando las causas básicas e inmediatas y la posibilidad de que se presenten nuevos casos. | I33: _Verificar por medio de un muestreo si se investigan los incidentes, accidentes de trabajo y las enfermedades laborales con la participación del COPASST, y si se definieron acciones para otros trabajadores potencialmente expuestos. _Constatar que las investigaciones se hayan realizado dentro de los quince (15) días siguientes a su ocurrencia a través del equipo investigador y evidenciar que se hayan remitido los informes de las investigaciones de accidente de trabajo grave o mortal o de enfermedad laboral mortal. _En caso de accidente grave o se produzca la muerte, verificar la participación de un profesional con licencia en Seguridad y Salud en el Trabajo en la investigación (propio o contratado), así como del Comité Paritario de SST.
C34: FECHA SEGUIMIENTO | I34: SEGUIMIENTO A LA IMPLEMENTACIÓN
C35: 46203 | F35: revisar atel | I35: Seguimiento a los ATEL y revisar que se tomaron la acciones correctivas, preventivas y de mejora.
C36: 46358 | F36: revisar atel
C37: RESPONSABLE
C38: ='Tablero indicadores 2026'!G8 -> Líder Funcional SG SST

Sheet 10.
A1: PROCESOS ADMINISTRATIVOS / SEGURIDAD Y SALUD EN EL TRABAJO
A2: INDICADORES DE GESTION
A3: CODIGO | C3: RE-RH-37-SST | D3: NIVEL DE CLASIFICACIÓN | G3: USO INTERNO (NC2) | K3: VERSION | L3: 0.2
A5: NOMBRE DEL INDICADOR | E5: ='Tablero indicadores 2026'!B28 -> 10. Plan de accidentalidad
A7: PROCESO | E7: ='Tablero indicadores 2026'!A1 -> PROCESOS ADMINISTRATIVOS / SEGURIDAD Y SALUD EN EL TRABAJO | R7: META | T7: ='Tablero indicadores 2026'!L20 -> 0.9
A9: FORMULA | E9: N° DE ACTIVIDADES DESARROLLADAS EN LA INTERVENCIÓN DE LOS RIESGOS PRIORITARIOS/ACTIVIDADES PROPUESTAS PARA LA INTERVENCIÓN DE LOS RIESGOS PRIORITARIOS | R9: FRECUENCIA DE MEDICIÓN | T9: ='Tablero indicadores 2026'!H20 -> Semestral
A11: UNIDAD | E11: ='Tablero indicadores 2026'!I20 -> Porcentaje | R11: TIPO INDICADOR | T11: ='Tablero indicadores 2026'!A19 -> PROCESO
A13: RESPONSABLE MEDICIÓN | E13: ='Tablero indicadores 2026'!G7 -> Líder Funcional SG SST | R13: VIGENCIA | T13: 2026
A17: PARAMETROS | E17: Enero | F17: Febrero | G17: Marzo | H17: Abril | I17: Mayo | J17: Junio | K17: Julio | L17: Agosto | M17: Septiembre | N17: Octubre | O17: Noviembre | P17: Diciembre | R17: OBSERVACIONES: N° DE ACTIVIDADES DESARROLLADAS EN LA INTERVENCIÓN DE LOS RIESGOS PRIORITARIOS/ACTIVIDADES PROPUESTAS PARA LA INTERVENCIÓN DE LOS RIESGOS PRIORITARIOS
A19: Numerador | J19: 2
A20: Denominador | J20: 2 | P20: 0
A22: Rango Mayor (Meta) | J22: 1 | P22: 1 | Q22: =#REF! -> #REF!
A24: Rango Menor | J24: 0 | P24: 0
A26: Avance | J26: =J19/J20 -> 1 | P26: =P19/P20 -> #DIV/0!
C32: ANÁLISIS | I32: ACCIÓN A SEGUIR
C33: Ejecución del plan de intervención de la accidentalidad | I33: _Analisis de accidentalidad, investigación de AT, reporte IT, AT, EL.
C34: FECHA SEGUIMIENTO | I34: SEGUIMIENTO A LA IMPLEMENTACIÓN
C35: 46203 | F35: Seguimiento al analisis de accidentalidad y actividades desarrolladas en la intervención de los riesgos prioritarios | I35: Analisis de accidentalidad, investigación de AT, reporte IT, AT, EL.
C36: 46358 | F36: Seguimiento al analisis de accidentalidad y actividades desarrolladas en la intervención de los riesgos prioritarios
C37: RESPONSABLE
C38: ='Tablero indicadores 2026'!G8 -> Líder Funcional SG SST

Sheet 11.
A1: PROCESOS ADMINISTRATIVOS / SEGURIDAD Y SALUD EN EL TRABAJO
A2: INDICADORES DE GESTION
A3: CODIGO | C3: RE-RH-37-SST | D3: NIVEL DE CLASIFICACIÓN | G3: USO INTERNO (NC2) | K3: VERSION | L3: 0.2
A5: NOMBRE DEL INDICADOR | E5: ='Tablero indicadores 2026'!B29 -> 11. Estadisticas de EL, AT, IT y ausentismo laboral
A7: PROCESO | E7: ='Tablero indicadores 2026'!A1 -> PROCESOS ADMINISTRATIVOS / SEGURIDAD Y SALUD EN EL TRABAJO | R7: META | T7: ='Tablero indicadores 2026'!L29 -> SI
A9: FORMULA | E9: ='Tablero indicadores 2026'!M7 -> SI/NO | R9: FRECUENCIA DE MEDICIÓN | T9: ='Tablero indicadores 2026'!H29 -> Trimestral
A11: UNIDAD | E11: ='Tablero indicadores 2026'!I29 -> Cumplimiento | R11: TIPO INDICADOR | T11: ='Tablero indicadores 2026'!A19 -> PROCESO
A13: RESPONSABLE MEDICIÓN | E13: ='Tablero indicadores 2026'!G7 -> Líder Funcional SG SST | R13: VIGENCIA | T13: 2026
A17: PARAMETROS | E17: Enero | F17: Febrero | G17: Marzo | H17: Abril | I17: Mayo | J17: Junio | K17: Julio | L17: Agosto | M17: Septiembre | N17: Octubre | O17: Noviembre | P17: Diciembre | R17: OBSERVACIONES: (Cumplimiento de registro de estadisticas )
A19: Numerador | G19: 1 | J19: 1
A20: Denominador | G20: 1 | J20: 1 | M20: 1 | P20: 1
A22: Rango Mayor (Meta) | G22: 1 | J22: 1 | M22: 1 | P22: 1 | Q22: =#REF! -> #REF!
A24: Rango Menor | G24: 0 | J24: 0 | M24: 0 | P24: 0
A26: Avance | G26: =G19/G20 -> 1 | J26: =J19/J20 -> 1 | M26: =M19/M20 -> 0 | P26: =P19/P20 -> 0
C31: ANÁLISIS | I31: ACCIÓN A SEGUIR
C32: Llevar registro estadístico de los accidentes de trabajo que ocurren así como de las enfermedades laborales que se presentan; se analiza este registro y las conclusiones derivadas del estudio son usadas para el mejoramiento del Sistema de Gestión de SST. | I32: Solicitar el registro estadístico actualizado de lo corrido del año y el año inmediatamente anterior al de la visita, así como la evidencia que contiene el análisis y las conclusiones derivadas del estudio que son usadas para el mejoramiento del Sistema de Gestión de SST.
C33: FECHA SEGUIMIENTO | I33: SEGUIMIENTO A LA IMPLEMENTACIÓN
C34: 46052 | F34: Revisión del registro estadistico | I34: Se actualiza el registro estadistico sin ningun reporte de 0 ATEL
C35: 46080 | F35: Revisión del registro estadistico | I35: Se actualiza el registro estadistico sin ningun reporte de 0 ATEL
C36: 46112 | F36: Revisión del registro estadistico | I36: Se actualiza el registro estadistico sin ningun reporte de 0 ATEL
C37: 46142 | F37: Revisión del registro estadistico | I37: Se actualiza el registro estadistico sin ningun reporte de 0 ATEL
C38: 46171 | F38: Revisión del registro estadistico | I38: Se actualiza el registro estadistico sin ningun reporte de 0 ATEL
C39: 46203 | F39: Revisión del registro estadistico | I39: Se actualiza el registro estadistico sin ningun reporte de 1 ATEL
C40: 46234 | F40: Revisión del registro estadistico
C41: 46265 | F41: Revisión del registro estadistico
C42: 46295 | F42: Revisión del registro estadistico
C43: 46325 | F43: Revisión del registro estadistico
C44: 46356 | F44: Revisión del registro estadistico
C45: 46360 | F45: Revisión del registro estadistico
C46: RESPONSABLE
C47: ='Tablero indicadores 2026'!G7 -> Líder Funcional SG SST

Sheet 12.
A1: PROCESOS ADMINISTRATIVOS / SEGURIDAD Y SALUD EN EL TRABAJO
A2: INDICADORES DE GESTION
A3: CODIGO | C3: RE-RH-37-SST | D3: NIVEL DE CLASIFICACIÓN | G3: USO INTERNO (NC2) | K3: VERSION | L3: 0.2
A5: NOMBRE DEL INDICADOR | E5: ='Tablero indicadores 2026'!B30 -> 12. Plan de emergencias
A7: PROCESO | E7: ='Tablero indicadores 2026'!A1 -> PROCESOS ADMINISTRATIVOS / SEGURIDAD Y SALUD EN EL TRABAJO | R7: META | T7: ='Tablero indicadores 2026'!L29 -> SI
A9: FORMULA | E9: N° DE SEDES CON PLAN DE EMERGENCIAS / N° TOTAL DE SEDES *100 | R9: FRECUENCIA DE MEDICIÓN | T9: ='Tablero indicadores 2026'!H30 -> Semestral
A11: UNIDAD | E11: ='Tablero indicadores 2026'!I30 -> Número | R11: TIPO INDICADOR | T11: ='Tablero indicadores 2026'!A19 -> PROCESO
A13: RESPONSABLE MEDICIÓN | E13: ='Tablero indicadores 2026'!G7 -> Líder Funcional SG SST | R13: VIGENCIA | T13: 2026
A17: PARAMETROS | E17: Enero | F17: Febrero | G17: Marzo | H17: Abril | I17: Mayo | J17: Junio | K17: Julio | L17: Agosto | M17: Septiembre | N17: Octubre | O17: Noviembre | P17: Diciembre | R17: OBSERVACIONES: (N° de sdes con plan de emergencias / N° total de sedes ) x 100
A19: Numerador | J19: 9
A20: Denominador | J20: 12 | P20: 12
A22: Rango Mayor (Meta) | J22: 1 | P22: 1 | Q22: =#REF! -> #REF!
A24: Rango Menor | J24: 0 | P24: 0
A26: Avance | J26: =J19/J20 -> 0.75 | P26: =P19/P20 -> 0
C32: ANÁLISIS | I32: ACCIÓN A SEGUIR
C33: _Elaborar un plan de prevención, preparación y respuesta ante emergencias que identifique las amenazas, evalúe y analice la vulnerabilidad. _Como mínimo el plan debe incluir: planos de las instalaciones que identifican áreas y salidas de emergencia, así como la señalización, realización de simulacros como mínimo una (1) vez al año. _El plan debe tener en cuenta todas las jornadas de trabajo en todos los centros de trabajo y debe ser divulgado. | I33: _Solicitar el plan de prevención, preparación y respuesta ante emergencias y constatar evidencias de su divulgación. _Verificar si existen los planos de las instalaciones que identifican áreas y salidas de emergencia y verificar si existe la debida señalización de la empresa. _Verificar los soportes que evidencien la realización de los simulacros y análisis de los mismos y validar que las recomendaciones emitidas con base en dicho análisis hayan sido tenidas en cuenta en el mejoramiento del plan de emergencias.
C34: FECHA SEGUIMIENTO | I34: SEGUIMIENTO A LA IMPLEMENTACIÓN
C35: 46203 | F35: _Seguimiento al plan de prevención, preparación y respuesta ante emergencias y constatar evidencia de su divulgación. _Seguimiento a que existan planos de las instalaciones que identifiquen áreas y salidas de emergencia y verificar si existe la debida señalización de la empresa. | I35: Seguimiento al plan de prevención, preparación y respuesta ante emergencias para determinar si requiere alguna actualizacipon
C36: 46360 | F36: _Seguimiento a los soportes que evidencien la realización de los simulacros y analisis de los mismos y validar las recomendaciones emitidas se tengan en cuenta como mejora, | I36: Seguimiento a que existan planos de las instalaciones que identifiquen áreas y salidas de emergencia y verificar si existe la debida señalización de la empresa.
I37: Seguimiento a los soportes que evidencien la realización de los simulacros y analisis de los mismos y validar las recomendaciones emitidas se tengan en cuenta como mejora,
C38: RESPONSABLE
C39: ='Tablero indicadores 2026'!G8 -> Líder Funcional SG SST

Sheet Simulacros
A1: PROCESOS ADMINISTRATIVOS / SEGURIDAD Y SALUD EN EL TRABAJO
A2: INDICADORES DE GESTION
A3: CODIGO | C3: RE-RH-37-SST | D3: NIVEL DE CLASIFICACIÓN | G3: USO INTERNO (NC2) | K3: VERSION | L3: 0.2
A5: NOMBRE DEL INDICADOR | E5: ='Tablero indicadores 2026'!B31 -> Simulacros
A7: PROCESO | E7: ='Tablero indicadores 2026'!A1 -> PROCESOS ADMINISTRATIVOS / SEGURIDAD Y SALUD EN EL TRABAJO | R7: META | T7: ='Tablero indicadores 2026'!L29 -> SI
A9: FORMULA | E9: N° DE SIMULACROS REALIZADOS/NRO DE SIMULACROS PROGRAMADOS | R9: FRECUENCIA DE MEDICIÓN | T9: ='Tablero indicadores 2026'!H30 -> Semestral
A11: UNIDAD | E11: ='Tablero indicadores 2026'!I31 -> Porcentaje | R11: TIPO INDICADOR | T11: ='Tablero indicadores 2026'!A19 -> PROCESO
A13: RESPONSABLE MEDICIÓN | E13: ='Tablero indicadores 2026'!G7 -> Líder Funcional SG SST | R13: VIGENCIA | T13: 2026
A17: PARAMETROS | E17: Enero | F17: Febrero | G17: Marzo | H17: Abril | I17: Mayo | J17: Junio | K17: Julio | L17: Agosto | M17: Septiembre | N17: Octubre | O17: Noviembre | P17: Diciembre | R17: OBSERVACIONES: (N° de simulacros realizados / nro de simulacros programados )
A19: Numerador
A20: Denominador | O20: 12
A22: Rango Mayor (Meta) | O22: 1 | Q22: =#REF! -> #REF!
A24: Rango Menor | O24: 0
A26: Avance | O26: =O19/O20 -> 0
C31: ANÁLISIS | I31: ACCIÓN A SEGUIR
C32: _Elaborar un plan de prevención, preparación y respuesta ante emergencias que identifique las amenazas, evalúe y analice la vulnerabilidad. _Como mínimo el plan debe incluir: planos de las instalaciones que identifican áreas y salidas de emergencia, así como la señalización, realización de simulacros como mínimo una (1) vez al año. _El plan debe tener en cuenta todas las jornadas de trabajo en todos los centros de trabajo y debe ser divulgado. | I32: _Verificar los soportes que evidencien la realización de los simulacros y análisis de los mismos y validar que las recomendaciones emitidas con base en dicho análisis hayan sido tenidas en cuenta en el mejoramiento del plan de emergencias.
C33: FECHA SEGUIMIENTO | I33: SEGUIMIENTO A LA IMPLEMENTACIÓN
C34: 46203 | F34: _Seguimiento a los soportes que evidencien la realización de los simulacros y analisis de los mismos y validar las recomendaciones emitidas se tengan en cuenta como mejora, | I34: Seguimiento a los soportes que evidencien la realización de los simulacros y analisis de los mismos y validar las recomendaciones emitidas se tengan en cuenta como mejora,
C36: RESPONSABLE
C37: ='Tablero indicadores 2026'!G7 -> Líder Funcional SG SST

Sheet 13.
A1: PROCESOS ADMINISTRATIVOS / SEGURIDAD Y SALUD EN EL TRABAJO
A2: INDICADORES DE GESTION
A3: CODIGO | C3: RE-RH-37-SST | D3: NIVEL DE CLASIFICACIÓN | G3: USO INTERNO (NC2) | K3: VERSION | L3: 0.2
A5: NOMBRE DEL INDICADOR | E5: ='Tablero indicadores 2026'!B32 -> 13. Conservaciòn de documentos
A7: PROCESO | E7: ='Tablero indicadores 2026'!A1 -> PROCESOS ADMINISTRATIVOS / SEGURIDAD Y SALUD EN EL TRABAJO | R7: META | T7: ='Tablero indicadores 2026'!L29 -> SI
A9: FORMULA | E9: SI/NO | R9: FRECUENCIA DE MEDICIÓN | T9: ='Tablero indicadores 2026'!H32 -> Anual
A11: UNIDAD | E11: ='Tablero indicadores 2026'!I32 -> Cumplimiento | R11: TIPO INDICADOR | T11: ='Tablero indicadores 2026'!A19 -> PROCESO
A13: RESPONSABLE MEDICIÓN | E13: ='Tablero indicadores 2026'!G7 -> Líder Funcional SG SST | R13: VIGENCIA | T13: 2026
A17: PARAMETROS | E17: Enero | F17: Febrero | G17: Marzo | H17: Abril | I17: Mayo | J17: Junio | K17: Julio | L17: Agosto | M17: Septiembre | N17: Octubre | O17: Noviembre | P17: Diciembre | R17: OBSERVACIONES:Conservación de documentos de manera controlada, garantizando que sean legibles, fácilmente identificables y accesibles. protegidos contra daño deterioro o pérdida.
A19: Numerador
A20: Denominador | P20: 1
A22: Rango Mayor (Meta) | P22: 1 | Q22: =#REF! -> #REF!
A24: Rango Menor | P24: 0
A26: Avance | P26: =P19/P20 -> 0
C32: ANÁLISIS | I32: ACCIÓN A SEGUIR
C33: Contar con un sistema de archivo y retención documental, para los registros y documentos que soportan el Sistema de Gestión de SST. | I33: _Constatar la existencia de un sistema de archivo y retención documental, para los registros y documentos que soportan el Sistema de Gestión de SST. _Verificar mediante muestreo que los registros y documentos sean legibles (entendible para el lector objeto), fácilmente identificables y accesibles (para todos los que estén vinculados con cada documento en particular), protegidos contra daño y pérdida
C34: FECHA SEGUIMIENTO | I34: SEGUIMIENTO A LA IMPLEMENTACIÓN
C35: 46358 | F35: Seguimiento al sistema de archivo y retención documental del SST | I35: Seguimiento al sistema de archivo y retención documental del SST
C37: RESPONSABLE
C38: ='Tablero indicadores 2026'!G8 -> Líder Funcional SG SST

Sheet 14.
A1: PROCESOS ADMINISTRATIVOS / SEGURIDAD Y SALUD EN EL TRABAJO
A2: INDICADORES DE GESTION
A3: CODIGO | C3: RE-RH-37-SST | D3: NIVEL DE CLASIFICACIÓN | G3: USO INTERNO (NC2) | K3: VERSION | L3: 0.2
A5: NOMBRE DEL INDICADOR | E5: ='Tablero indicadores 2026'!B33 -> 14.Riesgos de seguridad vial identeificados
A7: PROCESO | E7: ='Tablero indicadores 2026'!A1 -> PROCESOS ADMINISTRATIVOS / SEGURIDAD Y SALUD EN EL TRABAJO | R7: META | T7: 0.9
A9: FORMULA | E9: RSVI = RI(ia) - RI(fa) | R9: FRECUENCIA DE MEDICIÓN | T9: ='Tablero indicadores 2026'!H32 -> Anual
A11: UNIDAD | E11: ='Tablero indicadores 2026'!I32 -> Cumplimiento | R11: TIPO INDICADOR | T11: ='Tablero indicadores 2026'!A19 -> PROCESO
A13: RESPONSABLE MEDICIÓN | E13: ='Tablero indicadores 2026'!G7 -> Líder Funcional SG SST | R13: VIGENCIA | T13: 2026
A17: PARAMETROS | E17: Enero | F17: Febrero | G17: Marzo | H17: Abril | I17: Mayo | J17: Junio | K17: Julio | L17: Agosto | M17: Septiembre | N17: Octubre | O17: Noviembre | P17: Diciembre | R17: OBSERVACIONES: 3.1 Riesgos de Seguridad Vial Identificados: RSVI (Relacionados con el paso 6) Variables a medir en el indicador: RI(ia): Cantidad de riesgos identificados al inicio del año (total en matriz). RI(fa): Cantidad de riesgos identificados al final del año (total en matriz).
A19: Numerador
A20: Denominador | P20: 35
A22: Rango Mayor (Meta) | P22: 1 | Q22: =#REF! -> #REF!
A24: Rango Menor | P24: 0
A26: Avance | P26: =P19/P20 -> 0
C32: ANÁLISIS | I32: ACCIÓN A SEGUIR
C33: Verificar la cantidad de riesgos identificados al inicio del año vs el final del año | I33: De acuerdo a la matriz de riesgos revisar lo identificado al inicio y final del año
C34: FECHA SEGUIMIENTO | I34: SEGUIMIENTO A LA IMPLEMENTACIÓN
C35: 46358 | F35: Seguimiento a la cantidad de riesgos identificados | I35: Seguimiento a la cantidad de riesgos identificados
C37: RESPONSABLE
C38: ='Tablero indicadores 2026'!G8 -> Líder Funcional SG SST

Sheet 15. 
A1: PROCESOS ADMINISTRATIVOS / SEGURIDAD Y SALUD EN EL TRABAJO
A2: INDICADORES DE GESTION
A3: CODIGO | C3: RE-RH-37-SST | D3: NIVEL DE CLASIFICACIÓN | G3: USO INTERNO (NC2) | K3: VERSION | L3: 0.2
A5: NOMBRE DEL INDICADOR | E5: ='Tablero indicadores 2026'!B34 -> 15. Gestión de riesgos viales
A7: PROCESO | E7: ='Tablero indicadores 2026'!A1 -> PROCESOS ADMINISTRATIVOS / SEGURIDAD Y SALUD EN EL TRABAJO | R7: META | T7: 1
A9: FORMULA | E9: GRV = RVA (ia) - RVA (fa) | R9: FRECUENCIA DE MEDICIÓN | T9: ='Tablero indicadores 2026'!H32 -> Anual
A11: UNIDAD | E11: ='Tablero indicadores 2026'!I32 -> Cumplimiento | R11: TIPO INDICADOR | T11: ='Tablero indicadores 2026'!A19 -> PROCESO
A13: RESPONSABLE MEDICIÓN | E13: ='Tablero indicadores 2026'!G7 -> Líder Funcional SG SST | R13: VIGENCIA | T13: 2026
A17: PARAMETROS | E17: Enero | F17: Febrero | G17: Marzo | H17: Abril | I17: Mayo | J17: Junio | K17: Julio | L17: Agosto | M17: Septiembre | N17: Octubre | O17: Noviembre | P17: Diciembre | R17: OBSERVACIONES: 3.2. Gestión de Riesgos Viales: GRV Variables a medir en el indicador: RVA(ia): Cantidad de riesgos con valoración alta al inicio del año. RVA(fa): Cantidad de riesgos con valoración alta al final del año.
A19: Numerador
A20: Denominador | P20: 35
A22: Rango Mayor (Meta) | P22: 1 | Q22: =#REF! -> #REF!
A24: Rango Menor | P24: 0
A26: Avance | P26: =P19/P20 -> 0
C32: ANÁLISIS | I32: ACCIÓN A SEGUIR
C33: Verificar la cantidad de riesgos identificados al inicio del año vs el final del año | I33: De acuerdo a la matriz de riesgos revisar lo identificado al inicio y final del año
C34: FECHA SEGUIMIENTO | I34: SEGUIMIENTO A LA IMPLEMENTACIÓN
C35: 46358 | F35: Seguimiento a la cantidad de riesgos identificados | I35: Seguimiento a la cantidad de riesgos identificados
C37: RESPONSABLE
C38: ='Tablero indicadores 2026'!G8 -> Líder Funcional SG SST

Sheet 1,
A1: PROCESOS ADMINISTRATIVOS / SEGURIDAD Y SALUD EN EL TRABAJO
A2: INDICADORES DE GESTION
A3: CODIGO | C3: RE-RH-37-SST | D3: NIVEL DE CLASIFICACIÓN | G3: USO INTERNO (NC2) | K3: VERSION | L3: 0.2
A5: NOMBRE DEL INDICADOR | E5: ='Tablero indicadores 2026'!B36 -> 1. Requisitos Legales
A7: PROCESO | E7: ='Tablero indicadores 2026'!A1 -> PROCESOS ADMINISTRATIVOS / SEGURIDAD Y SALUD EN EL TRABAJO | R7: META | T7: ='Tablero indicadores 2026'!L29 -> SI
A9: FORMULA | E9: SI/NO | R9: FRECUENCIA DE MEDICIÓN | T9: ='Tablero indicadores 2026'!H36 -> Mensual
A11: UNIDAD | E11: ='Tablero indicadores 2026'!I36 -> Cumplimiento | R11: TIPO INDICADOR | T11: ='Tablero indicadores 2026'!A36 -> RESULTADO
A13: RESPONSABLE MEDICIÓN | E13: ='Tablero indicadores 2026'!G7 -> Líder Funcional SG SST | R13: VIGENCIA | T13: 2026
A17: PARAMETROS | E17: Enero | F17: Febrero | G17: Marzo | H17: Abril | I17: Mayo | J17: Junio | K17: Julio | L17: Agosto | M17: Septiembre | N17: Octubre | O17: Noviembre | P17: Diciembre | R17: OBSERVACIONES:Verificación de cumplimiento de requesitos legales aplicables.
A19: Numerador | E19: 1 | F19: 1 | G19: 1 | H19: 1 | I19: 1 | J19: 1
A20: Denominador | E20: 1 | F20: 1 | G20: 1 | H20: 1 | I20: 1 | J20: 1 | K20: 1 | L20: 1 | M20: 1 | N20: 1 | O20: 1 | P20: 1
A22: Rango Mayor (Meta) | E22: 1 | F22: 1 | G22: 1 | H22: 1 | I22: 1 | J22: 1 | K22: 1 | L22: 1 | M22: 1 | N22: 1 | O22: 1 | P22: 1 | Q22: =#REF! -> #REF!
A24: Rango Menor | E24: 0 | F24: 0 | G24: 0 | H24: 0 | I24: 0 | J24: 0 | K24: 0 | L24: 0 | M24: 0 | N24: 0 | O24: 0 | P24: 0
A26: Avance | E26: =E19/E20 -> 1 | F26: =F19/F20 -> 1 | G26: =G19/G20 -> 1 | H26: =H19/H20 -> 1 | I26: =I19/I20 -> 1 | J26: =J19/J20 -> 1 | K26: =K19/K20 -> 0 | L26: =L19/L20 -> 0 | ... P26: =P19/P20 -> 0
C32: ANÁLISIS | I32: ACCIÓN A SEGUIR
C33: Definir la matriz legal que contemple las normas actualizadas del Sistema General de Riesgos Laborales aplicables a la empresa. | I33: Solicitar la matriz legal. Verificar que contenga: Normas vigentes en riesgos laborales, aplicables a la empresa. Normas técnicas de cumplimiento de acuerdo con los peligros/riesgos identificados en la empresa. Normas vigentes de diferentes entidades que le apliquen relacionadas con los riesgos laborales.
C34: FECHA SEGUIMIENTO | I34: SEGUIMIENTO A LA IMPLEMENTACIÓN
C35: 46052 | F35: Revisión de normatividad vigente | I35: Se revisa en diferentes plataformas como ministerio del trabajo, ministerio de salud y protección social, SGRL,
C36: 46080 | F36: Revisión de normatividad vigente | I36: Se revisa en diferentes plataformas como ministerio del trabajo, ministerio de salud y protección social, SGRL,
C37: 46112 | F37: Revisión de normatividad vigente | I37: Se revisa en diferentes plataformas como ministerio del trabajo, ministerio de salud y protección social, SGRL,
C38: 46142 | F38: Revisión de normatividad vigente | I38: Se revisa en diferentes plataformas como ministerio del trabajo, ministerio de salud y protección social, SGRL,
C39: 46171 | F39: Revisión de normatividad vigente | I39: Se revisa en diferentes plataformas como ministerio del trabajo, ministerio de salud y protección social, SGRL,
C40: 46203 | F40: Revisión de normatividad vigente | I40: Se revisa en diferentes plataformas como ministerio del trabajo, ministerio de salud y protección social, SGRL,
C41: 46234 | F41: Revisión de normatividad vigente
C42: 46265 | F42: Revisión de normatividad vigente
C43: 46295 | F43: Revisión de normatividad vigente
C44: 46325 | F44: Revisión de normatividad vigente
C45: 46356 | F45: Revisión de normatividad vigente
C46: 46360
C47: RESPONSABLE
C48: ='Tablero indicadores 2026'!G8 -> Líder Funcional SG SST

Sheet 2,
A1: PROCESOS ADMINISTRATIVOS / SEGURIDAD Y SALUD EN EL TRABAJO
A2: INDICADORES DE GESTION
A3: CODIGO | C3: RE-RH-37-SST | D3: NIVEL DE CLASIFICACIÓN | G3: USO INTERNO (NC2) | K3: VERSION | L3: 0.2
A5: NOMBRE DEL INDICADOR | E5: ='Tablero indicadores 2026'!B37 -> 2. Objetivos y metas
A7: PROCESO | E7: ='Tablero indicadores 2026'!A1 -> PROCESOS ADMINISTRATIVOS / SEGURIDAD Y SALUD EN EL TRABAJO | R7: META | T7: ='Tablero indicadores 2026'!L37 -> 0.9
A9: FORMULA | E9: (No.de Objetivos y metas cumplidos/ No.de Objetivos y metas trazados) * 100 | R9: FRECUENCIA DE MEDICIÓN | T9: ='Tablero indicadores 2026'!H37 -> Semestral
A11: UNIDAD | E11: ='Tablero indicadores 2026'!I36 -> Cumplimiento | R11: TIPO INDICADOR | T11: ='Tablero indicadores 2026'!A36 -> RESULTADO
A13: RESPONSABLE MEDICIÓN | E13: ='Tablero indicadores 2026'!G7 -> Líder Funcional SG SST | R13: VIGENCIA | T13: 2026
A17: PARAMETROS | E17: Enero | F17: Febrero | G17: Marzo | H17: Abril | I17: Mayo | J17: Junio | K17: Julio | L17: Agosto | M17: Septiembre | N17: Octubre | O17: Noviembre | P17: Diciembre | R17: OBSERVACIONES:(No.de Objetivos y metas cumplidos/ No.de Objetivos y metas trazados) * 100
A19: Numerador | J19: 1
A20: Denominador | J20: 1 | P20: 1
A22: Rango Mayor (Meta) | J22: 1 | P22: 1 | Q22: =#REF! -> #REF!
A24: Rango Menor | J24: 0 | P24: 0
A26: Avance | J26: =J19/J20 -> 1 | P26: =P19/P20 -> 0
C32: ANÁLISIS | I32: ACCIÓN A SEGUIR
C33: Definir los objetivos del Sistema de Gestión de SST de conformidad con la política de SST, los cuales deben ser claros, medibles, cuantificables y tener metas, coherentes con el plan de trabajo anual, compatibles con la normatividad vigente, se encuentran documentados, son comunicados a los trabajadores, son revisados y evaluados mínimo una vez al año, actualizados de ser necesario y se encuentran en documento firmado por el empleador. | I33: Revisar si los objetivos se encuentran definidos, cumplen con las condiciones mencionadas en el criterio y si existen evidencias del proceso de difusión.
C34: FECHA SEGUIMIENTO | I34: SEGUIMIENTO A LA IMPLEMENTACIÓN
C35: 46203 | F35: Cumplimiento de objetivos | I35: Seguimiento a los objetivos definidos, cumplen con las condiciones mencionadas en el criterio y si existen evidencias del proceso de difusión
C36: RESPONSABLE
C37: ='Tablero indicadores 2026'!G8 -> Líder Funcional SG SST

Sheet 3,
A1: PROCESOS ADMINISTRATIVOS / SEGURIDAD Y SALUD EN EL TRABAJO
A2: INDICADORES DE GESTION
A3: CODIGO | C3: RE-RH-37-SST | D3: NIVEL DE CLASIFICACIÓN | G3: USO INTERNO (NC2) | K3: VERSION | L3: 0.2
A5: NOMBRE DEL INDICADOR | E5: ='Tablero indicadores 2026'!B38 -> 3. Ejecución del plan de trabajo
A7: PROCESO | E7: ='Tablero indicadores 2026'!A1 -> PROCESOS ADMINISTRATIVOS / SEGURIDAD Y SALUD EN EL TRABAJO | R7: META | T7: ='Tablero indicadores 2026'!L37 -> 0.9
A9: FORMULA | E9: ( N° de actividades desarrolladas en el periodo en el plan / Nro de actividades propuestas en el periodo en el plan de trabajo ) x 100 | R9: FRECUENCIA DE MEDICIÓN | T9: ='Tablero indicadores 2026'!H37 -> Semestral
A11: UNIDAD | E11: ='Tablero indicadores 2026'!I38 -> Porcentaje | R11: TIPO INDICADOR | T11: ='Tablero indicadores 2026'!A36 -> RESULTADO
A13: RESPONSABLE MEDICIÓN | E13: ='Tablero indicadores 2026'!G7 -> Líder Funcional SG SST | R13: VIGENCIA | T13: 2026
A17: PARAMETROS | E17: Enero | F17: Febrero | G17: Marzo | H17: Abril | I17: Mayo | J17: Junio | K17: Julio | L17: Agosto | M17: Septiembre | N17: Octubre | O17: Noviembre | P17: Diciembre | R17: OBSERVACIONES:( N° de actividades desarrolladas en el periodo en el plan / Nro de actividades propuestas en el periodo en el plan de trabajo ) x 100
A19: Numerador
A20: Denominador | J20: 749 | P20: 744
A22: Rango Mayor (Meta) | J22: 1 | P22: 1 | Q22: =#REF! -> #REF!
A24: Rango Menor | J24: 0 | P24: 0
A26: Avance | J26: =J19/J20 -> 0 | P26: =P19/P20 -> 0
C32: ANÁLISIS | I32: ACCIÓN A SEGUIR
C33: Diseñar y definir un plan anual de trabajo para el cumplimiento del Sistema de Gestión de SST, el cual identifica los objetivos, metas, responsabilidades, recursos, cronograma de actividades, firmado por el empleador y el responsable del Sistema de Gestión de SST. | I33: Solicitar el plan de trabajo anual. Verificar el cumplimiento del mismo. En el caso que se hayan presentado incumplimientos al plan, solicitar los planes de mejora respectivos.
C34: FECHA SEGUIMIENTO | I34: SEGUIMIENTO A LA IMPLEMENTACIÓN
C35: 46203 | I35: Seguimiento al plan de trabajo
C36: 46387 | I36: Seguimiento al cumplimiento del mismo.
C37: RESPONSABLE
C38: ='Tablero indicadores 2026'!G8 -> Líder Funcional SG SST

Sheet 4,
A1: PROCESOS ADMINISTRATIVOS / SEGURIDAD Y SALUD EN EL TRABAJO
A2: INDICADORES DE GESTION
A3: CODIGO | C3: RE-RH-37-SST | D3: NIVEL DE CLASIFICACIÓN | G3: USO INTERNO (NC2) | K3: VERSION | L3: 0.2
A5: NOMBRE DEL INDICADOR | E5: ='Tablero indicadores 2026'!B39 -> 4. Evaluaciòn no conformidades
A7: PROCESO | E7: ='Tablero indicadores 2026'!A1 -> PROCESOS ADMINISTRATIVOS / SEGURIDAD Y SALUD EN EL TRABAJO | R7: META | T7: ='Tablero indicadores 2026'!L37 -> 0.9
A9: FORMULA | E9: (No. DE NO CONFORMIDADES EN EL PERIODO DEL PLAN DE TRABAJO ANUAL/ No DE ACTIVIDADES PLANEADAS PARA EL PERIODO)*100 | R9: FRECUENCIA DE MEDICIÓN | T9: ='Tablero indicadores 2026'!H37 -> Semestral
A11: UNIDAD | E11: ='Tablero indicadores 2026'!I38 -> Porcentaje | R11: TIPO INDICADOR | T11: ='Tablero indicadores 2026'!A36 -> RESULTADO
A13: RESPONSABLE MEDICIÓN | E13: ='Tablero indicadores 2026'!G7 -> Líder Funcional SG SST | R13: VIGENCIA | T13: 2026
A17: PARAMETROS | E17: Enero | F17: Febrero | G17: Marzo | H17: Abril | I17: Mayo | J17: Junio | K17: Julio | L17: Agosto | M17: Septiembre | N17: Octubre | O17: Noviembre | P17: Diciembre | R17: OBSERVACIONES: (No. DE NO CONFORMIDADES EN EL PERIODO DEL PLAN DE TRABAJO ANUAL/ No DE ACTIVIDADES PLANEADAS PARA EL PERIODO) x 100
A19: Numerador
A20: Denominador | J20: 0 | P20: 0 | Q20: 0
A22: Rango Mayor (Meta) | J22: 1 | P22: 1 | Q22: =#REF! -> #REF!
A24: Rango Menor | J24: 0 | P24: 0
A26: Avance | J26: =J19/J20 -> #DIV/0! | P26: =P19/P20 -> #DIV/0!
C32: ANÁLISIS | I32: ACCIÓN A SEGUIR
C33: Evaluación de las no conformidades detectadas en el seguimiento al plan de trabajo anual en seguridad y salud en el trabajo; | I33: Revisar si se presenta una no conformidad durante la ejecución del plan de trabajo
C34: FECHA SEGUIMIENTO | I34: SEGUIMIENTO A LA IMPLEMENTACIÓN
C35: 46203 | I35: Seguimiento al plan de trabajo y revisar si se presenta una no conformidad
C36: 46387 | I36: Seguimiento al plan de trabajo y revisar si se presenta una no conformidad
C37: RESPONSABLE
C38: ='Tablero indicadores 2026'!G8 -> Líder Funcional SG SST

Sheet 5,
A1: PROCESOS ADMINISTRATIVOS / SEGURIDAD Y SALUD EN EL TRABAJO
A2: INDICADORES DE GESTION
A3: CODIGO | C3: RE-RH-37-SST | D3: NIVEL DE CLASIFICACIÓN | G3: USO INTERNO (NC2) | K3: VERSION | L3: 0.2
A5: NOMBRE DEL INDICADOR | E5: ='Tablero indicadores 2026'!B40 -> 5. Acciones correctivas
A7: PROCESO | E7: ='Tablero indicadores 2026'!A1 -> PROCESOS ADMINISTRATIVOS / SEGURIDAD Y SALUD EN EL TRABAJO | R7: META | T7: ='Tablero indicadores 2026'!L37 -> 0.9
A9: FORMULA | E9: (Acciones correctivas realizadas/ N° de no conformidades emcontradas) x 100 | R9: FRECUENCIA DE MEDICIÓN | T9: ='Tablero indicadores 2026'!H40 -> Anual
A11: UNIDAD | E11: ='Tablero indicadores 2026'!I38 -> Porcentaje | R11: TIPO INDICADOR | T11: ='Tablero indicadores 2026'!A36 -> RESULTADO
A13: RESPONSABLE MEDICIÓN | E13: ='Tablero indicadores 2026'!G7 -> Líder Funcional SG SST | R13: VIGENCIA | T13: 2026
A17: PARAMETROS | E17: Enero | F17: Febrero | G17: Marzo | H17: Abril | I17: Mayo | J17: Junio | K17: Julio | L17: Agosto | M17: Septiembre | N17: Octubre | O17: Noviembre | P17: Diciembre | R17: OBSERVACIONES: (Acciones correctivas realizadas/ N° de no conformidades emcontradas) x 100
A19: Numerador
A20: Denominador | P20: 0
A22: Rango Mayor (Meta) | P22: 1 | Q22: =#REF! -> #REF!
A24: Rango Menor | P24: 0
A26: Avance | P26: =P19/P20 -> #DIV/0!
C32: ANÁLISIS | I32: ACCIÓN A SEGUIR
C33: Implementar las medidas y acciones correctivas producto de requerimientos o recomendaciones de autoridades administrativas y de las administradoras de riesgos laborales. | I33: Solicitar las evidencias de las acciones correctivas realizadas en respuesta a los requerimientos o recomendaciones de las autoridades administrativas y de las administradoras de riesgos laborales.
C34: FECHA SEGUIMIENTO | I34: SEGUIMIENTO A LA IMPLEMENTACIÓN
C35: 46358 | I35: Seguimiento a las acciones correctivas encontradas
C36: RESPONSABLE
C37: ='Tablero indicadores 2026'!G8 -> Líder Funcional SG SST

Sheet 5,1
A1: PROCESOS ADMINISTRATIVOS / SEGURIDAD Y SALUD EN EL TRABAJO
A2: INDICADORES DE GESTION
A3: CODIGO | C3: RE-RH-37-SST | D3: NIVEL DE CLASIFICACIÓN | G3: USO INTERNO (NC2) | K3: VERSION | L3: 0.2
A5: NOMBRE DEL INDICADOR | E5: ='Tablero indicadores 2026'!B41 -> 5.1 %Inspecciones realizadas
A7: PROCESO | E7: ='Tablero indicadores 2026'!A1 -> PROCESOS ADMINISTRATIVOS / SEGURIDAD Y SALUD EN EL TRABAJO | R7: META | T7: ='Tablero indicadores 2026'!L37 -> 0.9
A9: FORMULA | E9: (Número de inspecciones realizadas/ número de inspecciones planeadas )x 100 | R9: FRECUENCIA DE MEDICIÓN | T9: ='Tablero indicadores 2026'!H41 -> Trimestral
A11: UNIDAD | E11: ='Tablero indicadores 2026'!I38 -> Porcentaje | R11: TIPO INDICADOR | T11: ='Tablero indicadores 2026'!A36 -> RESULTADO
A13: RESPONSABLE MEDICIÓN | E13: ='Tablero indicadores 2026'!G7 -> Líder Funcional SG SST | R13: VIGENCIA | T13: 2026
A17: PARAMETROS | E17: Enero | F17: Febrero | G17: Marzo | H17: Abril | I17: Mayo | J17: Junio | K17: Julio | L17: Agosto | M17: Septiembre | N17: Octubre | O17: Noviembre | P17: Diciembre | R17: OBSERVACIONES: (Número de inspecciones realizadas/ número de inspecciones planeadas )x 100
A19: Numerador
A20: Denominador | F20: 18 | I20: 19 | L20: 19 | O20: 19
A22: Rango Mayor (Meta) | F22: 1 | I22: 1 | L22: 1 | O22: 1 | Q22: =#REF! -> #REF!
A24: Rango Menor | F24: 0 | I24: 0 | L24: 0 | O24: 0
A26: Avance | F26: =F19/F20 -> 0 | I26: =I19/I20 -> 0 | L26: =L19/L20 -> 0 | O26: =O19/O20 -> 0
C32: ANÁLISIS | I32: ACCIÓN A SEGUIR
C33: Elaborar formatos de registro para la realización de las visitas de inspección. Realizar las visitas de inspección sistemática a las instalaciones, maquinaria o equipos, incluidos los relacionados con la prevención y atención de emergencias; con la participación del COPASST. | I33: Solicitar los formatos de registro de visitas de inspección elaborados. Solicitar la evidencia de las visitas de inspección realizadas a las instalaciones, maquinaria y equipos, incluidos los relacionados con la prevención y atención de emergencias y verificar la participación del COPASST en las mismas.
C34: FECHA SEGUIMIENTO | I34: SEGUIMIENTO A LA IMPLEMENTACIÓN
C35: 46080 | I35: Verificar la realización de inspecciones de seguridad en conjunto con COPASST
C36: 46171 | I36: Verificar la realización de inspecciones de seguridad en conjunto con COPASST
C37: 46265
C38: 46356
C39: RESPONSABLE
C40: ='Tablero indicadores 2026'!G8 -> Líder Funcional SG SST
C1048576: 2

Sheet 5,2
A1: PROCESOS ADMINISTRATIVOS / SEGURIDAD Y SALUD EN EL TRABAJO
A2: INDICADORES DE GESTION
A3: CODIGO | C3: RE-RH-37-SST | D3: NIVEL DE CLASIFICACIÓN | G3: USO INTERNO (NC2) | K3: VERSION | L3: 0.2
A5: NOMBRE DEL INDICADOR | E5: ='Tablero indicadores 2026'!B42 -> 5. 2 % Condiciones mejoradas
A7: PROCESO | E7: ='Tablero indicadores 2026'!A1 -> PROCESOS ADMINISTRATIVOS / SEGURIDAD Y SALUD EN EL TRABAJO | R7: META | T7: ='Tablero indicadores 2026'!L37 -> 0.9
A9: FORMULA | E9: ( Número de condiciones mejoradas / Número de condiciones encontradas) x 100 | R9: FRECUENCIA DE MEDICIÓN | T9: ='Tablero indicadores 2026'!H42 -> Anual
A11: UNIDAD | E11: ='Tablero indicadores 2026'!I38 -> Porcentaje | R11: TIPO INDICADOR | T11: ='Tablero indicadores 2026'!A36 -> RESULTADO
A13: RESPONSABLE MEDICIÓN | E13: ='Tablero indicadores 2026'!G7 -> Líder Funcional SG SST | R13: VIGENCIA | T13: 2026
A17: PARAMETROS | E17: Enero | F17: Febrero | G17: Marzo | H17: Abril | I17: Mayo | J17: Junio | K17: Julio | L17: Agosto | M17: Septiembre | N17: Octubre | O17: Noviembre | P17: Diciembre | R17: OBSERVACIONES: ( Número de condiciones mejoradas / Número de condiciones encontradas) x 100
A19: Numerador
A20: Denominador | P20: 0
A22: Rango Mayor (Meta) | P22: 1 | Q22: =#REF! -> #REF!
A24: Rango Menor | P24: 0
A26: Avance | P26: =P19/P20 -> #DIV/0!
C32: ANÁLISIS | I32: ACCIÓN A SEGUIR
C33: Muestra el porcentaje de condiciones mejoradas de las inspecciones realizadas | I33: Revisar que el % de condiciones mejoradas de las inspecciones realizadas se ejecuten
C34: FECHA SEGUIMIENTO | I34: SEGUIMIENTO A LA IMPLEMENTACIÓN
C35: 46358 | I35: Seguimiento a las condieones mejoradas de la inspecciones realizadas
C36: RESPONSABLE
C37: ='Tablero indicadores 2026'!G8 -> Líder Funcional SG SST

Sheet 5,3
A1: PROCESOS ADMINISTRATIVOS / SEGURIDAD Y SALUD EN EL TRABAJO
A2: INDICADORES DE GESTION
A3: CODIGO | C3: RE-RH-37-SST | D3: NIVEL DE CLASIFICACIÓN | G3: USO INTERNO (NC2) | K3: VERSION | L3: 0.2
A5: NOMBRE DEL INDICADOR | E5: ='Tablero indicadores 2026'!B43 -> 5. 3 % Cubrimiento EPP
A7: PROCESO | E7: ='Tablero indicadores 2026'!A1 -> PROCESOS ADMINISTRATIVOS / SEGURIDAD Y SALUD EN EL TRABAJO | R7: META | T7: ='Tablero indicadores 2026'!L37 -> 0.9
A9: FORMULA | E9: Número de EPP entregados / Número de EPP requeridos x 100 | R9: FRECUENCIA DE MEDICIÓN | T9: ='Tablero indicadores 2026'!H43 -> Mensual
A11: UNIDAD | E11: ='Tablero indicadores 2026'!I43 -> Porcentaje | R11: TIPO INDICADOR | T11: ='Tablero indicadores 2026'!A36 -> RESULTADO
A13: RESPONSABLE MEDICIÓN | E13: ='Tablero indicadores 2026'!G7 -> Líder Funcional SG SST | R13: VIGENCIA | T13: 2026
A17: PARAMETROS | E17: Enero | F17: Febrero | G17: Marzo | H17: Abril | I17: Mayo | J17: Junio | K17: Julio | L17: Agosto | M17: Septiembre | N17: Octubre | O17: Noviembre | P17: Diciembre | R17: OBSERVACIONES: Número de EPP entregados / Número de EPP requeridos x 100
A19: Numerador | E19: 29 | F19: 33 | G19: 43 | H19: 21 | I19: 49 | J19: 76
A20: Denominador | E20: 29 | F20: 33 | G20: 43 | H20: 21 | I20: 49 | J20: 76 | K20: 83 | L20: 40 | M20: 40 | N20: 50 | O20: 28
A22: Rango Mayor (Meta) | E22: 1 | F22: 1 | G22: 1 | H22: 1 | I22: 1 | J22: 1 | K22: 1 | L22: 1 | M22: 1 | N22: 1 | O22: 1 | P22: 1 | Q22: =#REF! -> #REF!
A24: Rango Menor | E24: 0 | F24: 0 | G24: 0 | H24: 0 | I24: 0 | J24: 0 | K24: 0 | L24: 0 | M24: 0 | N24: 0 | O24: 0 | P24: 0
A26: Avance | E26: =E19/E20 -> 1 | F26: =F19/F20 -> 1 | G26: =G19/G20 -> 1 | H26: =H19/H20 -> 1 | I26: =I19/I20 -> 1 | J26: =J19/J20 -> 1 | K26: =K19/K20 -> 0 | L26: =L19/L20 -> 0 | ... P26: =P19/P20 -> #DIV/0!
C32: ANÁLISIS | I32: ACCIÓN A SEGUIR
C33: _Suministrar a los trabajadores los elementos de protección personal que se requieran y reponerlos oportunamente, conforme al desgaste y condiciones de uso de los mismos. _Verificar que los contratistas y subcontratistas entregan los elementos de protección personal que se requiera a sus trabajadores y realizan la reposición de los mismos oportunamente, conforme al desgaste y condiciones de uso. _Realizar la capacitación para el uso de los elementos de protección personal. | I33: _Solicitar los soportes que evidencien la entrega y reposición de los elementos de protección personal a los trabajadores. _Verificar los soportes del cumplimiento del criterio por parte de los contratistas y subcontratistas. _Verificar los soportes que evidencian la realización de la capacitación en el uso de los elementos de protección personal.
C34: FECHA SEGUIMIENTO | I34: SEGUIMIENTO A LA IMPLEMENTACIÓN
C35: 46358 | I35: De acuerdo al proceso que este el personal se tiene estipulado la entrega y la supervición por parte del líder a cargo
C36: RESPONSABLE
C37: ='Tablero indicadores 2026'!G8 -> Líder Funcional SG SST

Sheet 6,
A1: PROCESOS ADMINISTRATIVOS / SEGURIDAD Y SALUD EN EL TRABAJO
A2: INDICADORES DE GESTION
A3: CODIGO | C3: RE-RH-37-SST | D3: NIVEL DE CLASIFICACIÓN | G3: USO INTERNO (NC2) | K3: VERSION | L3: 0.2
A5: NOMBRE DEL INDICADOR | E5: ='Tablero indicadores 2026'!B45 -> 6. Cumplimiento de SVE DME
A7: PROCESO | E7: ='Tablero indicadores 2026'!A1 -> PROCESOS ADMINISTRATIVOS / SEGURIDAD Y SALUD EN EL TRABAJO | R7: META | T7: ='Tablero indicadores 2026'!L37 -> 0.9
A9: FORMULA | E9: (NO. DE TRABAJADORES INTERVENIDOS EN EL SVE / NO. TRABAJADORES A INTERVENIR)*100 | R9: FRECUENCIA DE MEDICIÓN | T9: ='Tablero indicadores 2026'!H45 -> Semestral
A11: UNIDAD | E11: ='Tablero indicadores 2026'!I45 -> Porcentaje | R11: TIPO INDICADOR | T11: ='Tablero indicadores 2026'!A36 -> RESULTADO
A13: RESPONSABLE MEDICIÓN | E13: ='Tablero indicadores 2026'!G7 -> Líder Funcional SG SST | R13: VIGENCIA | T13: 2026
A17: PARAMETROS | E17: Enero | F17: Febrero | G17: Marzo | H17: Abril | I17: Mayo | J17: Junio | K17: Julio | L17: Agosto | M17: Septiembre | N17: Octubre | O17: Noviembre | P17: Diciembre | R17: OBSERVACIONES: (NO. DE TRABAJADORES INTERVENIDOS EN EL SVE / NO. TRABAJADORES A INTERVENIR) X 100
A19: Numerador | J19: 524
A20: Denominador | J20: 1079 | P20: 1033
A22: Rango Mayor (Meta) | J22: 1 | P22: 1 | Q22: =#REF! -> #REF!
A24: Rango Menor | J24: 0 | P24: 0
A26: Avance | J26: =J19/J20 -> 0.48563485 | P26: =P19/P20 -> 0
C32: ANÁLISIS | I32: ACCIÓN A SEGUIR
C33: Desarrollar las actividades de medicina del trabajo, prevención y promoción de la salud y programas de vigilancia epidemiológica requeridos, de conformidad con las prioridades identificadas en el diagnóstico de condiciones de salud y con los peligros/riesgos prioritarios | I33: Solicitar las evidencias que constaten la definición y ejecución de las actividades de medicina del trabajo, promoción y prevención y los programas de vigilancia epidemiológica, de conformidad con las prioridades que se identificaron con base en los resultados del diagnóstico de las condiciones de salud y los peligros/riesgos de intervención prioritarios.
C34: FECHA SEGUIMIENTO | I34: SEGUIMIENTO A LA IMPLEMENTACIÓN
C35: 46203 | I35: Ejecución e implementación de los programas SVE
C36: 46358
C37: RESPONSABLE
C38: ='Tablero indicadores 2026'!G8 -> Líder Funcional SG SST

Sheet SVE-DME
B2: INDICADORES DEL SISTEMA DE VIGILANCIA EPIDEMIOLÒGICA PARA EL CONTROL DE DESORDENES MUSCULO ESQUELÈTICOS EN MIEMBROS SUPERIORES Y ESPALDA
C5: No. de casos nuevos en el periodo | D5: No. de trabajadores expuestos al riesgo en el periodo | E5: INCIDENCIA
B6: ENERO | C6: 0 | D6: 1099 | E6: =(C6/D6) -> 0
B7: FEBRERO
B8: MARZO
B9: ABRIL
B10: MAYO
B11: JUNIO
B12: JULIO | C12: 0 | D12: 1072 | E12: =(C12/D12) -> 0
B13: AGOSTO
B14: SEPTIEMBRE
B15: OCTUBRE
B16: NOVIEMBRE
B17: DICIEMBRE
B18: TOTAL | C18: =SUM(C6+C12) -> 0 | D18: =AVERAGE(D6:D17) -> 1085.5 | E18: =(C18/D18) -> 0
C23: No. de casos históricos presentados en el período (5 años) | D23: No. de trabajadores expuestos al riesgo en el período | E23: PREVALENCIA
B24: 2013 a 2017 | C24: 9 | D24: 1301 | E24: =(C24/D24) -> 0.0069177556
E25: =(C25/D25) -> #DIV/0!
E26: =(C26/D26) -> #DIV/0!
E27: =(C27/D27) -> #DIV/0!
E28: =(C28/D28) -> #DIV/0!
E29: =(C29/D29) -> #DIV/0!
B30: TOTAL | C30: =SUM(C24:C29) -> 9 | D30: =AVERAGE(D24:D29) -> 1301 | E30: =(C30/D30) -> 0.0069177556
C32: No. de casos históricos presentados en el período (5 años) | D32: No. de trabajadores expuestos al riesgo en el período | E32: PREVALENCIA
B33: 2018 a 2022 | D33: 1019 | E33: 0
E34: #DIV/0!
E35: #DIV/0!
E36: #DIV/0!
E37: #DIV/0!
E38: #DIV/0!
B39: TOTAL | C39: 0 | D39: 1019 | E39: 0
C41: No. de casos históricos presentados en el período (5 años) | D41: No. de trabajadores expuestos al riesgo en el período | E41: PREVALENCIA
B42: 2023 a 2028 | D42: 1038 | E42: 0
E43: #DIV/0!
E44: #DIV/0!
E45: #DIV/0!
E46: #DIV/0!
E47: #DIV/0!
B48: TOTAL | C48: 0 | D48: =D42 -> 1038 | E48: =C48/D48 -> 0
C50: No. Personas cubiertas por el SVE | D50: No. Total de Personas expuestas | E50: CUBRIMIENTO
B51: ENERO | C51: 870 | D51: 1043 | E51: =(C51/D51) -> 0.83413231
B52: FEBRERO | C52: 846 | D52: 1032 | E52: =(C52/D52) -> 0.81976744
B53: MARZO | C53: 823 | D53: 1021 | E53: =(C53/D53) -> 0.80607248
B54: ABRIL | C54: 816 | D54: 1031 | E54: =(C54/D54) -> 0.7914646
B55: MAYO | C55: 811 | D55: 1038 | E55: =(C55/D55) -> 0.78131021
B56: JUNIO | C56: 797 | D56: 1019 | E56: =(C56/D56) -> 0.78213935
B57: JULIO | C57: 0 | D57: 995 | E57: =(C57/D57) -> 0
B58: AGOSTO | C58: 0 | D58: 933 | E58: =(C58/D58) -> 0
B59: SEPTIEMBRE | C59: 0 | D59: 929 | E59: =(C59/D59) -> 0
B60: OCTUBRE | C60: 0 | D60: 919 | E60: =(C60/D60) -> 0
B61: NOVIEMBRE | C61: 0 | D61: 950 | E61: 0
B62: DICIEMBRE | C62: 0 | D62: 920 | E62: 0
B63: TOTAL | C63: =SUM(C51:C62) -> 4963 | D63: =SUM(D51:D62) -> 11830 | E63: =(C63/D63) -> 0.41952663

Sheet 6,1
A1: PROCESOS ADMINISTRATIVOS / SEGURIDAD Y SALUD EN EL TRABAJO
A2: INDICADORES DE GESTION
A3: CODIGO | C3: RE-RH-37-SST | D3: NIVEL DE CLASIFICACIÓN | G3: USO INTERNO (NC2) | K3: VERSION | L3: 0.2
A5: NOMBRE DEL INDICADOR | E5: ='Tablero indicadores 2026'!B46 -> 6.1 Cumplimiento del cronogrma de actividades de SVE FRPS
A7: PROCESO | E7: ='Tablero indicadores 2026'!A1 -> PROCESOS ADMINISTRATIVOS / SEGURIDAD Y SALUD EN EL TRABAJO | R7: META | T7: ='Tablero indicadores 2026'!L37 -> 0.9
A9: FORMULA | E9: # de acciones realizadas / Número total de acciones presupuestadas. | R9: FRECUENCIA DE MEDICIÓN | T9: ='Tablero indicadores 2026'!H46 -> Anual
A11: UNIDAD | E11: ='Tablero indicadores 2026'!I45 -> Porcentaje | R11: TIPO INDICADOR | T11: ='Tablero indicadores 2026'!A36 -> RESULTADO
A13: RESPONSABLE MEDICIÓN | E13: ='Tablero indicadores 2026'!G7 -> Líder Funcional SG SST | R13: VIGENCIA | T13: 2026
A17: PARAMETROS | E17: Enero | F17: Febrero | G17: Marzo | H17: Abril | I17: Mayo | J17: Junio | K17: Julio | L17: Agosto | M17: Septiembre | N17: Octubre | O17: Noviembre | P17: Diciembre | R17: OBSERVACIONES: # de acciones realizadas / Número total de acciones presupuestadas.
A19: Numerador
A20: Denominador | P20: 0
A22: Rango Mayor (Meta) | P22: 1 | Q22: =#REF! -> #REF!
A24: Rango Menor | P24: 0
A26: Avance | P26: =P19/P20 -> #DIV/0!
D32: ANÁLISIS | J32: ACCIÓN A SEGUIR
D33: Desarrollar las actividades de medicina del trabajo, prevención y promoción de la salud y programas de vigilancia epidemiológica requeridos, de conformidad con las prioridades identificadas en el diagnóstico de condiciones de salud y con los peligros/riesgos prioritarios | J33: Solicitar las evidencias que constaten la definición y ejecución de las actividades de medicina del trabajo, promoción y prevención y los programas de vigilancia epidemiológica, de conformidad con las prioridades que se identificaron con base en los resultados del diagnóstico de las condiciones de salud y los peligros/riesgos de intervención prioritarios.
D34: FECHA SEGUIMIENTO | J34: SEGUIMIENTO A LA IMPLEMENTACIÓN
D35: 46358 | J35: Ejecución e implementación de los programas SVE
D37: RESPONSABLE
D38: ='Tablero indicadores 2026'!H8 -> Anual

Sheet 6,2
A1: PROCESOS ADMINISTRATIVOS / SEGURIDAD Y SALUD EN EL TRABAJO
A2: INDICADORES DE GESTION
A3: CODIGO | C3: RE-RH-37-SST | D3: NIVEL DE CLASIFICACIÓN | G3: USO INTERNO (NC2) | K3: VERSION | L3: 0.2
A5: NOMBRE DEL INDICADOR | E5: ='Tablero indicadores 2026'!B47 -> 6.2 Cumplimiento del cobertura del SVE FRPS
A7: PROCESO | E7: ='Tablero indicadores 2026'!A1 -> PROCESOS ADMINISTRATIVOS / SEGURIDAD Y SALUD EN EL TRABAJO | R7: META | T7: ='Tablero indicadores 2026'!L37 -> 0.9
A9: FORMULA | E9: (N° de trabajadores intervenidos/ N° de trabajadores de la empresa) * 100 | R9: FRECUENCIA DE MEDICIÓN | T9: ='Tablero indicadores 2026'!H46 -> Anual
A11: UNIDAD | E11: ='Tablero indicadores 2026'!I45 -> Porcentaje | R11: TIPO INDICADOR | T11: ='Tablero indicadores 2026'!A36 -> RESULTADO
A13: RESPONSABLE MEDICIÓN | E13: ='Tablero indicadores 2026'!G7 -> Líder Funcional SG SST | R13: VIGENCIA | T13: 2026
A17: PARAMETROS | E17: Enero | F17: Febrero | G17: Marzo | H17: Abril | I17: Mayo | J17: Junio | K17: Julio | L17: Agosto | M17: Septiembre | N17: Octubre | O17: Noviembre | P17: Diciembre | R17: OBSERVACIONES: # de acciones realizadas / Número total de acciones presupuestadas.
A19: Numerador
A20: Denominador | P20: 0
A22: Rango Mayor (Meta) | P22: 1 | Q22: =#REF! -> #REF!
A24: Rango Menor | P24: 0
A26: Avance | P26: =P19/P20 -> #DIV/0!
D32: ANÁLISIS | J32: ACCIÓN A SEGUIR
D33: Desarrollar las actividades de medicina del trabajo, prevención y promoción de la salud y programas de vigilancia epidemiológica requeridos, de conformidad con las prioridades identificadas en el diagnóstico de condiciones de salud y con los peligros/riesgos prioritarios | J33: Solicitar las evidencias que constaten la definición y ejecución de las actividades de medicina del trabajo, promoción y prevención y los programas de vigilancia epidemiológica, de conformidad con las prioridades que se identificaron con base en los resultados del diagnóstico de las condiciones de salud y los peligros/riesgos de intervención prioritarios.
D34: FECHA SEGUIMIENTO | J34: SEGUIMIENTO A LA IMPLEMENTACIÓN
D35: 46358 | J35: Ejecución e implementación de los programas SVE
D37: RESPONSABLE
D38: ='Tablero indicadores 2026'!H8 -> Anual

Sheet 7,
A1: PROCESOS ADMINISTRATIVOS / SEGURIDAD Y SALUD EN EL TRABAJO
A2: INDICADORES DE GESTION
A3: CODIGO | C3: RE-RH-37-SST | D3: NIVEL DE CLASIFICACIÓN | G3: USO INTERNO (NC2) | K3: VERSION | L3: 0.2
A5: NOMBRE DEL INDICADOR | E5: ='Tablero indicadores 2026'!B48 -> 7. Evaluación de los programas de rehabilitación de la salud
A7: PROCESO | E7: ='Tablero indicadores 2026'!A1 -> PROCESOS ADMINISTRATIVOS / SEGURIDAD Y SALUD EN EL TRABAJO | R7: META | T7: ='Tablero indicadores 2026'!L37 -> 0.9
A9: FORMULA | E9: (NO. DE TRABAJADORES INTERVENIDOS EN EL PROGRAMA / NO. TRABAJADORES A INTERVENIR)*100 | R9: FRECUENCIA DE MEDICIÓN | T9: ='Tablero indicadores 2026'!H48 -> Semestral
A11: UNIDAD | E11: ='Tablero indicadores 2026'!I45 -> Porcentaje | R11: TIPO INDICADOR | T11: ='Tablero indicadores 2026'!A36 -> RESULTADO
A13: RESPONSABLE MEDICIÓN | E13: ='Tablero indicadores 2026'!G7 -> Líder Funcional SG SST | R13: VIGENCIA | T13: 2026
A17: PARAMETROS | E17: Enero | F17: Febrero | G17: Marzo | H17: Abril | I17: Mayo | J17: Junio | K17: Julio | L17: Agosto | M17: Septiembre | N17: Octubre | O17: Noviembre | P17: Diciembre | R17: OBSERVACIONES: (NO. DE TRABAJADORES INTERVENIDOS EN EL PROGRAMA / NO. TRABAJADORES A INTERVENIR)*100
A19: Numerador | J19: 0
A20: Denominador | J20: 0 | P20: 0
A22: Rango Mayor (Meta) | J22: 1 | P22: 1 | Q22: =#REF! -> #REF!
A24: Rango Menor | J24: 0 | P24: 0
A26: Avance | J26: =J19/J20 -> #DIV/0! | P26: =P19/P20 -> #DIV/0!
D32: ANÁLISIS | J32: ACCIÓN A SEGUIR
D33: Desarrollar las actividades de medicina del trabajo, prevención y promoción de la salud y programas de vigilancia epidemiológica requeridos, de conformidad con las prioridades identificadas en el diagnóstico de condiciones de salud y con los peligros/riesgos prioritarios | J33: Solicitar las evidencias que constaten la definición y ejecución de las actividades de medicina del trabajo, promoción y prevención y los programas de vigilancia epidemiológica, de conformidad con las prioridades que se identificaron con base en los resultados del diagnóstico de las condiciones de salud y los peligros/riesgos de intervención prioritarios.
D34: FECHA SEGUIMIENTO | J34: SEGUIMIENTO A LA IMPLEMENTACIÓN
D35: 46203 | J35: Ejecución e implementación de los programas SVE
D36: 46358
D37: RESPONSABLE
D38: ='Tablero indicadores 2026'!H8 -> Anual

Sheet 8,
A1: PROCESOS ADMINISTRATIVOS / SEGURIDAD Y SALUD EN EL TRABAJO
A2: INDICADORES DE GESTION
A3: CODIGO | C3: RE-RH-37-SST | D3: NIVEL DE CLASIFICACIÓN | G3: USO INTERNO (NC2) | K3: VERSION | L3: 0.2
A5: NOMBRE DEL INDICADOR | E5: ='Tablero indicadores 2026'!B49 -> 8.Frecuencia de Accidentalidad (Resoluciòn 312 de 2019)
A7: PROCESO | E7: ='Tablero indicadores 2026'!A1 -> PROCESOS ADMINISTRATIVOS / SEGURIDAD Y SALUD EN EL TRABAJO | R7: META | T7: ='Tablero indicadores 2026'!L37 -> 0.9
A9: FORMULA | E9: IFAT =(N° TOTAL DE A.T EN EL MES / N° DE TRABAJADORES EN EL MES) * 100 | R9: FRECUENCIA DE MEDICIÓN | T9: ='Tablero indicadores 2026'!H49 -> Mensual
A11: UNIDAD | E11: ='Tablero indicadores 2026'!I49 -> Número | R11: TIPO INDICADOR | T11: ='Tablero indicadores 2026'!A36 -> RESULTADO
A13: RESPONSABLE MEDICIÓN | E13: ='Tablero indicadores 2026'!G7 -> Líder Funcional SG SST | R13: VIGENCIA | T13: 2026
A17: PARAMETROS | E17: Enero | F17: Febrero | G17: Marzo | H17: Abril | I17: Mayo | J17: Junio | K17: Julio | L17: Agosto | M17: Septiembre | N17: Octubre | O17: Noviembre | P17: Diciembre | R17: OBSERVACIONES: IFAT =(N° TOTAL DE A.T EN EL MES / N° DE TRABAJADORES EN EL MES) * 100
A19: Numerador | E19: 2 | F19: 0 | G19: 0 | H19: 0 | I19: 0 | J19: 0
A20: Denominador | E20: 2 | F20: 0 | G20: 0 | H20: 0 | I20: 0 | J20: 0 | K20: 0 | L20: 0 | M20: 0 | N20: 0 | O20: 0 | P20: 0 | Q20: 0
A22: Rango Mayor (Meta) | E22: 1 | F22: 1 | G22: 1 | H22: 1 | I22: 1 | J22: 1 | K22: 1 | L22: 1 | M22: 1 | N22: 1 | O22: 1 | P22: 1 | Q22: =#REF! -> #REF!
A24: Rango Menor | E24: 0 | F24: 0 | G24: 0 | H24: 0 | I24: 0 | J24: 0 | K24: 0 | L24: 0 | M24: 0 | N24: 0 | O24: 0 | P24: 0
A26: Avance | E26: =E19/E20 -> 1 | F26: =F19/F20 -> #DIV/0! | G26: =G19/G20 -> #DIV/0! | H26: =H19/H20 -> #DIV/0! | I26: =I19/I20*100 -> #DIV/0! | J26: =J19/J20 -> #DIV/0! | K26: =K19/K20 -> #DIV/0! | L26: =L19/L20 -> #DIV/0! | M26: =M19/M20 -> #DIV/0! | N26: =N19/N20 -> #DIV/0! | O26: =O19/O20 -> #DIV/0! | P26: =P19/P20 -> #DIV/0!
C32: ANÁLISIS | I32: ACCIÓN A SEGUIR
C33: Medir la frecuencia de los accidentes como mínimo una (1) vez al mes y realizar la clasificación del origen del peligro/riesgo que los generó (físicos, de químicos, biológicos, seguridad, públicos, psicosociales, entre otros.). | I33: Solicitar los resultados de la medición para lo corrido del año y/o el año inmediatamente anterior y constatar el comportamiento de la frecuencia de los accidentes y la relación del evento con los peligros/riesgos identificados.
C34: FECHA SEGUIMIENTO | I34: SEGUIMIENTO A LA IMPLEMENTACIÓN
C35: 46052 | F35: Revisión del registro estadistico | I35: Se actualiza el registro estadistico sin ningun reporte de 0 ATEL
C36: 46080 | F36: Revisión del registro estadistico | I36: Se actualiza el registro estadistico sin ningun reporte de 0 ATEL
C37: 46112 | F37: Revisión del registro estadistico | I37: Se actualiza el registro estadistico sin ningun reporte de 0 ATEL
C38: 46142 | F38: Revisión del registro estadistico | I38: Se actualiza el registro estadistico sin ningun reporte de 0 ATEL
C39: 46171 | F39: Revisión del registro estadistico | I39: Se actualiza el registro estadistico sin ningun reporte de 0 ATEL
C40: 46203 | F40: Revisión del registro estadistico | I40: Se actualiza el registro estadistico sin ningun reporte de 1 ATEL
C41: 46234 | F41: Revisión del registro estadistico
C42: 46265 | F42: Revisión del registro estadistico
C43: 46295 | F43: Revisión del registro estadistico
C44: 46325 | F44: Revisión del registro estadistico
C45: 46356 | F45: Revisión del registro estadistico
C46: 46360
C48: ='Tablero indicadores 2026'!G8 -> Líder Funcional SG SST

Sheet 8,1
A1: PROCESOS ADMINISTRATIVOS / SEGURIDAD Y SALUD EN EL TRABAJO
A2: INDICADORES DE GESTION
A3: CODIGO | C3: RE-RH-37-SST | D3: NIVEL DE CLASIFICACIÓN | G3: USO INTERNO (NC2) | K3: VERSION | L3: 0.2
A5: NOMBRE DEL INDICADOR | E5: ='Tablero indicadores 2026'!B50 -> 8.1 Severidad de Accidentalidad (Resolución 312 de 2019)
A7: PROCESO | E7: ='Tablero indicadores 2026'!A1 -> PROCESOS ADMINISTRATIVOS / SEGURIDAD Y SALUD EN EL TRABAJO | R7: META | T7: ='Tablero indicadores 2026'!L37 -> 0.9
A9: FORMULA | E9: ISAT= (N° DIAS DE INCAPACIDAD POR ACCIDENTES DE TRABAJO EN EL MES + NÚMERO DE DÍAS CARGADOS EN EL MES / N° DE TRABAJADORES EN EL MES) * 100 | R9: FRECUENCIA DE MEDICIÓN | T9: ='Tablero indicadores 2026'!H49 -> Mensual
A11: UNIDAD | E11: ='Tablero indicadores 2026'!I49 -> Número | R11: TIPO INDICADOR | T11: ='Tablero indicadores 2026'!A36 -> RESULTADO
A13: RESPONSABLE MEDICIÓN | E13: ='Tablero indicadores 2026'!G7 -> Líder Funcional SG SST | R13: VIGENCIA | T13: 2026
A17: PARAMETROS | E17: Enero | F17: Febrero | G17: Marzo | H17: Abril | I17: Mayo | J17: Junio | K17: Julio | L17: Agosto | M17: Septiembre | N17: Octubre | O17: Noviembre | P17: Diciembre | R17: OBSERVACIONES: ISAT= (N° DIAS DE INCAPACIDAD POR ACCIDENTES DE TRABAJO EN EL MES + NÚMERO DE DÍAS CARGADOS EN EL MES / N° DE TRABAJADORES EN EL MES) * 100
A19: Numerador | E19: 2 | F19: 0 | G19: 0 | H19: 0 | I19: 0 | J19: 0
A20: Denominador | E20: 2 | F20: 0 | G20: 0 | H20: 0 | I20: 0 | J20: 0 | K20: 0 | L20: 0 | M20: 0 | N20: 0 | O20: 0 | P20: 0
A22: Rango Mayor (Meta) | E22: 1 | F22: 1 | G22: 1 | H22: 1 | I22: 1 | J22: 1 | K22: 1 | L22: 1 | M22: 1 | N22: 1 | O22: 1 | P22: 1 | Q22: =#REF! -> #REF!
A24: Rango Menor | E24: 0 | F24: 0 | G24: 0 | H24: 0 | I24: 0 | J24: 0 | K24: 0 | L24: 0 | M24: 0 | N24: 0 | O24: 0 | P24: 0
A26: Avance | E26: =E19/E20 -> 1 | F26: =F19/F20 -> #DIV/0! | G26: =G19/G20 -> #DIV/0! | H26: =H19/H20 -> #DIV/0! | I26: =I19/I20 -> #DIV/0! | J26: =J19/J20 -> #DIV/0! | K26: =K19/K20 -> #DIV/0! | L26: =L19/L20 -> #DIV/0! | ... P26: =P19/P20 -> #DIV/0!
C32: ANÁLISIS | I32: ACCIÓN A SEGUIR
C33: Medir la severidad de los accidentes de trabajo como mínimo una (1) vez al mes y realizar la clasificación del origen del peligro/riesgo que los generó (físicos, químicos, biológicos, de seguridad, públicos, psicosociales, entre otros). | I33: Solicitar los resultados de la medición para lo corrido del año y/o el año inmediatamente anterior y constatar el comportamiento de la severidad y la relación del evento con los peligros/riesgos identificados.
C34: FECHA SEGUIMIENTO | I34: SEGUIMIENTO A LA IMPLEMENTACIÓN
C35: 46052 | F35: Revisión del registro estadistico | I35: Se actualiza el registro estadistico sin ningun reporte de 0 ATEL
C36: 46080 | F36: Revisión del registro estadistico | I36: Se actualiza el registro estadistico sin ningun reporte de 0 ATEL
C37: 46112 | F37: Revisión del registro estadistico | I37: Se actualiza el registro estadistico sin ningun reporte de 0 ATEL
C38: 46142 | F38: Revisión del registro estadistico | I38: Se actualiza el registro estadistico sin ningun reporte de 0 ATEL
C39: 46171 | F39: Revisión del registro estadistico | I39: Se actualiza el registro estadistico sin ningun reporte de 0 ATEL
C40: 46203 | F40: Revisión del registro estadistico | I40: Se actualiza el registro estadistico sin ningun reporte de 0 ATEL
C41: 46234 | F41: Revisión del registro estadistico
C42: 46265 | F42: Revisión del registro estadistico
C43: 46295 | F43: Revisión del registro estadistico
C44: 46325 | F44: Revisión del registro estadistico
C45: 46356 | F45: Revisión del registro estadistico
C46: 46360
C47: RESPONSABLE
C48: ='Tablero indicadores 2026'!G7 -> Líder Funcional SG SST
D49: ='Tablero indicadores 2026'!I8 -> Cumplimiento

Sheet 8,2
A1: PROCESOS ADMINISTRATIVOS / SEGURIDAD Y SALUD EN EL TRABAJO
A2: INDICADORES DE GESTION
A3: CODIGO | C3: RE-RH-37-SST | D3: NIVEL DE CLASIFICACIÓN | G3: USO INTERNO (NC2) | K3: VERSION | L3: 0.2
A5: NOMBRE DEL INDICADOR | E5: ='Tablero indicadores 2026'!B51 -> 8.2 Indice de Lesiones Incapacitantes por A.T
A7: PROCESO | E7: ='Tablero indicadores 2026'!A1 -> PROCESOS ADMINISTRATIVOS / SEGURIDAD Y SALUD EN EL TRABAJO | R7: META | T7: ='Tablero indicadores 2026'!L37 -> 0.9
A9: FORMULA | E9: I = (N° CASOS NUEVOS DE ENFERMEDAD LABORAL EN EL AÑO / PROMEDIO DE TRABAJADORES EN EL AÑO) * 100.000 | R9: FRECUENCIA DE MEDICIÓN | T9: ='Tablero indicadores 2026'!H51 -> Anual
A11: UNIDAD | E11: ='Tablero indicadores 2026'!I49 -> Número | R11: TIPO INDICADOR | T11: ='Tablero indicadores 2026'!A36 -> RESULTADO
A13: RESPONSABLE MEDICIÓN | E13: ='Tablero indicadores 2026'!G7 -> Líder Funcional SG SST | R13: VIGENCIA | T13: 2026
A17: PARAMETROS | E17: Enero | F17: Febrero | G17: Marzo | H17: Abril | I17: Mayo | J17: Junio | K17: Julio | L17: Agosto | M17: Septiembre | N17: Octubre | O17: Noviembre | P17: Diciembre | R17: OBSERVACIONES: I = (N° CASOS NUEVOS DE ENFERMEDAD LABORAL EN EL AÑO / PROMEDIO DE TRABAJADORES EN EL AÑO) * 100.000
A19: Numerador
A20: Denominador | P20: 1045
A22: Rango Mayor (Meta) | P22: 0 | Q22: =#REF! -> #REF!
A24: Rango Menor | P24: 1
A26: Avance | P26: =P19/P20 -> 0
C32: ANÁLISIS | J32: ACCIÓN A SEGUIR
D33: Medir la incidencia de la enfermedad laboral como mínimo una (1) vez al año y realizar la clasificación del origen del peligro/riesgo que la generó (físicos, químicos, biológicos, ergonómicos o biomecánicos, psicosociales, entre otros). | J33: Solicitar los resultados de la medición para lo corrido del año y/o el año inmediatamente anterior y constatar el comportamiento de la incidencia de las enfermedades laborales y la relación del evento con los peligros/riesgos identificados.
D34: FECHA SEGUIMIENTO | J34: SEGUIMIENTO A LA IMPLEMENTACIÓN
D35: 46052 | G35: Revisión del registro estadistico | J35: Se actualiza el registro estadistico sin ningun reporte de 0 ATEL
D36: 46080 | G36: Revisión del registro estadistico | J36: Se actualiza el registro estadistico sin ningun reporte de 0 ATEL
D37: 46112 | G37: Revisión del registro estadistico | J37: Se actualiza el registro estadistico sin ningun reporte de 0 ATEL
D38: 46142 | G38: Revisión del registro estadistico | J38: Se actualiza el registro estadistico sin ningun reporte de 0 ATEL
D39: 46171 | G39: Revisión del registro estadistico | J39: Se actualiza el registro estadistico sin ningun reporte de 0 ATEL
D40: 46203 | G40: Revisión del registro estadistico | J40: Se actualiza el registro estadistico sin ningun reporte de 1 ATEL
D41: 46234 | G41: Revisión del registro estadistico
D42: 46265 | G42: Revisión del registro estadistico
D43: 46295 | G43: Revisión del registro estadistico
D44: 46325 | G44: Revisión del registro estadistico
D45: 46356 | G45: Revisión del registro estadistico
D46: 46360
D47: RESPONSABLE
D48: =E13 -> Líder Funcional SG SST

Sheet 8,3
A1: PROCESOS ADMINISTRATIVOS / SEGURIDAD Y SALUD EN EL TRABAJO
A2: INDICADORES DE GESTION
A3: CODIGO | C3: RE-RH-37-SST | D3: NIVEL DE CLASIFICACIÓN | G3: USO INTERNO (NC2) | K3: VERSION | L3: 0.2
A5: NOMBRE DEL INDICADOR | E5: ='Tablero indicadores 2026'!B52 -> 8.3 Proporciòn de accidentes de trabajo mortales (Resolución 312 de 2019)
A7: PROCESO | E7: ='Tablero indicadores 2026'!A1 -> PROCESOS ADMINISTRATIVOS / SEGURIDAD Y SALUD EN EL TRABAJO | R7: META | T7: ='Tablero indicadores 2026'!L37 -> 0.9
A9: FORMULA | E9: (NO. DE ACCIDENTES DE TRABAJO MORTALES QUE SE PRESENTARON EL AÑO/ TOTAL DE ACCIDENTES DE TRABAJO QUE SE PRESENTARON EN EL AÑO) x 100 | R9: FRECUENCIA DE MEDICIÓN | T9: ='Tablero indicadores 2026'!H51 -> Anual
A11: UNIDAD | E11: ='Tablero indicadores 2026'!I52 -> Porcentaje | R11: TIPO INDICADOR | T11: ='Tablero indicadores 2026'!A36 -> RESULTADO
A13: RESPONSABLE MEDICIÓN | E13: ='Tablero indicadores 2026'!G7 -> Líder Funcional SG SST | R13: VIGENCIA | T13: 2026
A17: PARAMETROS | E17: Enero | F17: Febrero | G17: Marzo | H17: Abril | I17: Mayo | J17: Junio | K17: Julio | L17: Agosto | M17: Septiembre | N17: Octubre | O17: Noviembre | P17: Diciembre | R17: OBSERVACIONES: (NO. DE ACCIDENTES DE TRABAJO MORTALES QUE SE PRESENTARON EL AÑO/ TOTAL DE ACCIDENTES DE TRABAJO QUE SE PRESENTARON EN EL AÑO) x 100
A19: Numerador
A20: Denominador | P20: 0
A22: Rango Mayor (Meta) | P22: 0 | Q22: =#REF! -> #REF!
A24: Rango Menor | P24: 1
A26: Avance | P26: =P19/P20 -> #DIV/0!
D32: ANÁLISIS | J32: ACCIÓN A SEGUIR
D33: Medir la mortalidad por accidentes como mínimo una (1) vez al año y realizar la clasificación del origen del peligro/riesgo que los generó (físicos, químicos, biológicos, de seguridad, públicos, psicosociales, entre otros). | J33: Solicitar los resultados de la medición para lo corrido del año y/o el año inmediatamente anterior y constatar el comportamiento de la mortalidad y la relación del evento con los peligros/riesgos identificados.
D34: FECHA SEGUIMIENTO | J34: SEGUIMIENTO A LA IMPLEMENTACIÓN
D35: 46052 | G35: Revisión del registro estadistico | J35: Se actualiza el registro estadistico sin ningun reporte de 0 ATEL
D36: 46080 | G36: Revisión del registro estadistico | J36: Se actualiza el registro estadistico sin ningun reporte de 0 ATEL
D37: 46112 | G37: Revisión del registro estadistico | J37: Se actualiza el registro estadistico sin ningun reporte de 0 ATEL
D38: 46142 | G38: Revisión del registro estadistico | J38: Se actualiza el registro estadistico sin ningun reporte de 0 ATEL
D39: 46171 | G39: Revisión del registro estadistico | J39: Se actualiza el registro estadistico sin ningun reporte de 0 ATEL
D40: 46203 | G40: Revisión del registro estadistico | J40: Se actualiza el registro estadistico sin ningun reporte de 1 ATEL
D41: 46234 | G41: Revisión del registro estadistico
D42: 46265 | G42: Revisión del registro estadistico
D43: 46295 | G43: Revisión del registro estadistico
D44: 46325 | G44: Revisión del registro estadistico
D45: 46356 | G45: Revisión del registro estadistico
D46: 46360
D47: RESPONSABLE
D48: =E13 -> Líder Funcional SG SST

Sheet 8,4
A1: PROCESOS ADMINISTRATIVOS / SEGURIDAD Y SALUD EN EL TRABAJO
A2: INDICADORES DE GESTION
A3: CODIGO | C3: RE-RH-37-SST | D3: NIVEL DE CLASIFICACIÓN | G3: USO INTERNO (NC2) | K3: VERSION | L3: 0.2
A5: NOMBRE DEL INDICADOR | E5: ='Tablero indicadores 2026'!B53 -> 8.4 Tasa Accidentalidad
A7: PROCESO | E7: ='Tablero indicadores 2026'!A1 -> PROCESOS ADMINISTRATIVOS / SEGURIDAD Y SALUD EN EL TRABAJO | R7: META | T7: ='Tablero indicadores 2026'!L37 -> 0.9
A9: FORMULA | E9: TA = N° AT / N° PROMEDIO DE TRABAJADORES | R9: FRECUENCIA DE MEDICIÓN | T9: ='Tablero indicadores 2026'!H53 -> Mensual
A11: UNIDAD | E11: ='Tablero indicadores 2026'!I52 -> Porcentaje | R11: TIPO INDICADOR | T11: ='Tablero indicadores 2026'!A36 -> RESULTADO
A13: RESPONSABLE MEDICIÓN | E13: ='Tablero indicadores 2026'!G7 -> Líder Funcional SG SST | R13: VIGENCIA | T13: 2026
A17: PARAMETROS | E17: Enero | F17: Febrero | G17: Marzo | H17: Abril | I17: Mayo | J17: Junio | K17: Julio | L17: Agosto | M17: Septiembre | N17: Octubre | O17: Noviembre | P17: Diciembre | R17: OBSERVACIONES: TA = N° AT / N° PROMEDIO DE TRABAJADORES
A19: Numerador | E19: 2 | F19: 0 | G19: 0 | H19: 0 | I19: 0 | J19: 0
A20: Denominador | E20: 2 | F20: 0 | G20: 0 | H20: 0 | I20: 0 | J20: 0 | K20: 0 | L20: 0 | M20: 0 | N20: 0 | O20: 0 | P20: 0
A22: Rango Mayor (Meta) | E22: 0 | F22: 0 | G22: 0 | H22: 0 | I22: 0 | J22: 0 | K22: 0 | L22: 0 | M22: 0 | N22: 0 | O22: 0 | P22: 0 | Q22: =#REF! -> #REF!
A24: Rango Menor | E24: 1 | F24: 1 | G24: 1 | H24: 1 | I24: 1 | J24: 1 | K24: 1 | L24: 1 | M24: 1 | N24: 1 | O24: 1 | P24: 1
A26: Avance | E26: =E19/E20 -> 1 | F26: =F19/F20 -> #DIV/0! | G26: =G19/G20 -> #DIV/0! | H26: =H19/H20 -> #DIV/0! | I26: =I19/I20 -> #DIV/0! | J26: =J19/J20 -> #DIV/0! | K26: =K19/K20 -> #DIV/0! | L26: =L19/L20 -> #DIV/0! | ... P26: =P19/P20 -> #DIV/0!
C32: ANÁLISIS | J32: ACCIÓN A SEGUIR
D33: Medir la mortalidad por accidentes como mínimo una (1) vez al año y realizar la clasificación del origen del peligro/riesgo que los generó (físicos, químicos, biológicos, de seguridad, públicos, psicosociales, entre otros). | J33: Solicitar los resultados de la medición para lo corrido del año y/o el año inmediatamente anterior y constatar el comportamiento de la mortalidad y la relación del evento con los peligros/riesgos identificados.
D34: FECHA SEGUIMIENTO | J34: SEGUIMIENTO A LA IMPLEMENTACIÓN
D35: 46052 | G35: Revisión del registro estadistico | J35: Se actualiza el registro estadistico sin ningun reporte de 0 ATEL
D36: 46080 | G36: Revisión del registro estadistico | J36: Se actualiza el registro estadistico sin ningun reporte de 0 ATEL
D37: 46112 | G37: Revisión del registro estadistico | J37: Se actualiza el registro estadistico sin ningun reporte de 0 ATEL
D38: 46142 | G38: Revisión del registro estadistico | J38: Se actualiza el registro estadistico sin ningun reporte de 0 ATEL
D39: 46171 | G39: Revisión del registro estadistico | J39: Se actualiza el registro estadistico sin ningun reporte de 0 ATEL
D40: 46203 | G40: Revisión del registro estadistico | J40: Se actualiza el registro estadistico sin ningun reporte de 1 ATEL
D41: 46234 | G41: Revisión del registro estadistico
D42: 46265 | G42: Revisión del registro estadistico
D43: 46295 | G43: Revisión del registro estadistico
D44: 46325 | G44: Revisión del registro estadistico
D45: 46356 | G45: Revisión del registro estadistico
D46: 46360 | G46: Revisión del registro estadistico
D47: RESPONSABLE
D48: =E13 -> Líder Funcional SG SST

Sheet 8,5
A1: PROCESOS ADMINISTRATIVOS / SEGURIDAD Y SALUD EN EL TRABAJO
A2: INDICADORES DE GESTION
A3: CODIGO | C3: RE-RH-37-SST | D3: NIVEL DE CLASIFICACIÓN | G3: USO INTERNO (NC2) | K3: VERSION | L3: 0.2
A5: NOMBRE DEL INDICADOR | E5: ='Tablero indicadores 2026'!B54 -> 8.5 Prevalencia de la enfermedad (Resolución 312 de 2019)
A7: PROCESO | E7: ='Tablero indicadores 2026'!A1 -> PROCESOS ADMINISTRATIVOS / SEGURIDAD Y SALUD EN EL TRABAJO | R7: META | T7: ='Tablero indicadores 2026'!L37 -> 0.9
A9: FORMULA | E9: P = (N° DE CASOS NUEVOS Y ANTIGUOS DE ENFERMEDAD LABORAL EN CINCO AÑOS / PROMEDIO DE TRABAJADORES EN CINCO AÑOS)* 100.000 | R9: FRECUENCIA DE MEDICIÓN | T9: ='Tablero indicadores 2026'!H54 -> Anual
A11: UNIDAD | E11: ='Tablero indicadores 2026'!I54 -> Número | R11: TIPO INDICADOR | T11: ='Tablero indicadores 2026'!A36 -> RESULTADO
A13: RESPONSABLE MEDICIÓN | E13: ='Tablero indicadores 2026'!G7 -> Líder Funcional SG SST | R13: VIGENCIA | T13: 2026
A17: PARAMETROS | E17: Enero | F17: Febrero | G17: Marzo | H17: Abril | I17: Mayo | J17: Junio | K17: Julio | L17: Agosto | M17: Septiembre | N17: Octubre | O17: Noviembre | P17: Diciembre | R17: OBSERVACIONES: P = (N° DE CASOS NUEVOS Y ANTIGUOS DE ENFERMEDAD LABORAL EN CINCO AÑOS / PROMEDIO DE TRABAJADORES EN CINCO AÑOS)* 100.000
A19: Numerador
A20: Denominador | P20: 1033
A22: Rango Mayor (Meta) | P22: 0 | Q22: =#REF! -> #REF!
A24: Rango Menor | P24: 1
A26: Avance | P26: =P19/P20 -> 0
C32: ANÁLISIS | J32: ACCIÓN A SEGUIR
D33: Medir la prevalencia de la enfermedad laboral como mínimo una 1) vez al año y realizar la clasificación del origen del peligro/riesgo que la generó (físico, químico, biológico, ergonómico o biomecánico, psicosocial, entre otros). | J33: Solicitar los resultados de la medición para lo corrido del año y/o el año inmediatamente anterior y constatar el comportamiento de la prevalencia de las enfermedades laborales y la relación del evento con los peligros/riesgos identificados.
D34: FECHA SEGUIMIENTO | J34: SEGUIMIENTO A LA IMPLEMENTACIÓN
D35: Año 2020 | G35: Revisión del registro estadistico | J35: Se realiza la actualización de analisis estadisticos EL
D36: Año 2021 | G36: Revisión del registro estadistico | J36: Se realiza la actualización de analisis estadisticos EL
D37: Año 2022 | G37: Revisión del registro estadistico | J37: Se realiza la actualización de analisis estadisticos EL
D38: Año 2023 | G38: Revisión del registro estadistico | J38: Se realiza la actualización de analisis estadisticos EL
D39: Año 2024 | G39: Revisión del registro estadistico | J39: Se realiza la actualización de analisis estadisticos EL
D40: Año 2025 | G40: Revisión del registro estadistico | J40: Se realiza la actualización de analisis estadisticos EL
D41: Año 2026 | G41: Revisión del registro estadistico
D42: RESPONSABLE
D43: =E13 -> Líder Funcional SG SST

Sheet 8,6
A1: PROCESOS ADMINISTRATIVOS / SEGURIDAD Y SALUD EN EL TRABAJO
A2: INDICADORES DE GESTION
A3: CODIGO | C3: RE-RH-37-SST | D3: NIVEL DE CLASIFICACIÓN | G3: USO INTERNO (NC2) | K3: VERSION | L3: 0.2
A5: NOMBRE DEL INDICADOR | E5: ='Tablero indicadores 2026'!B55 -> 8.6 Incidencia de la enfermedad (Resolución 312 de 2019)
A7: PROCESO | E7: ='Tablero indicadores 2026'!A1 -> PROCESOS ADMINISTRATIVOS / SEGURIDAD Y SALUD EN EL TRABAJO | R7: META | T7: ='Tablero indicadores 2026'!L37 -> 0.9
A9: FORMULA | E9: I = (N° CASOS NUEVOS DE ENFERMEDAD LABORAL EN EL AÑO / PROMEDIO DE TRABAJADORES EN EL AÑO) * 100.000 | R9: FRECUENCIA DE MEDICIÓN | T9: ='Tablero indicadores 2026'!H54 -> Anual
A11: UNIDAD | E11: ='Tablero indicadores 2026'!I54 -> Número | R11: TIPO INDICADOR | T11: ='Tablero indicadores 2026'!A36 -> RESULTADO
A13: RESPONSABLE MEDICIÓN | E13: ='Tablero indicadores 2026'!G7 -> Líder Funcional SG SST | R13: VIGENCIA | T13: 2026
A17: PARAMETROS | E17: Enero | F17: Febrero | G17: Marzo | H17: Abril | I17: Mayo | J17: Junio | K17: Julio | L17: Agosto | M17: Septiembre | N17: Octubre | O17: Noviembre | P17: Diciembre | R17: OBSERVACIONES: I = (N° CASOS NUEVOS DE ENFERMEDAD LABORAL EN EL AÑO / PROMEDIO DE TRABAJADORES EN EL AÑO) * 100.000
A19: Numerador
A20: Denominador
A22: Rango Mayor (Meta) | P22: 0 | Q22: =#REF! -> #REF!
A24: Rango Menor | P24: 1
A26: Avance | P26: =P19/P20 -> #DIV/0!
C32: ANÁLISIS | J32: ACCIÓN A SEGUIR
D33: Medir la incidencia de la enfermedad laboral como mínimo una (1) vez al año y realizar la clasificación del origen del peligro/riesgo que la generó (físicos, químicos, biológicos, ergonómicos o biomecánicos, psicosociales, entre otros). | J33: Solicitar los resultados de la medición para lo corrido del año y/o el año inmediatamente anterior y constatar el comportamiento de la incidencia de las enfermedades laborales y la relación del evento con los peligros/riesgos identificados.
D34: FECHA SEGUIMIENTO | J34: SEGUIMIENTO A LA IMPLEMENTACIÓN
D35: Año 2020 | G35: Revisión del registro estadistico | J35: Se realiza la actualización de analisis estadisticos EL
D36: Año 2021 | G36: Revisión del registro estadistico | J36: Se realiza la actualización de analisis estadisticos EL
D37: Año 2022 | G37: Revisión del registro estadistico | J37: Se realiza la actualización de analisis estadisticos EL
D38: Año 2023 | G38: Revisión del registro estadistico | J38: Se realiza la actualización de analisis estadisticos EL
D39: Año 2024 | G39: Revisión del registro estadistico | J39: Se realiza la actualización de analisis estadisticos EL
D40: Año 2025 | G40: Revisión del registro estadistico | J40: Se realiza la actualización de analisis estadisticos EL
D41: Año 2026 | G41: Revisión del registro estadistico
D42: RESPONSABLE
D43: =E13 -> Líder Funcional SG SST

Sheet 8,f
B1: PROCESOS ADMINISTRATIVOS / SEGURIDAD Y SALUD EN EL TRABAJO
B2: REGISTRO ESTADÍSTICO DE ACCIDENTALIDAD
B3: CÓDIGO | F3: RE-RH-39-SST | H3: NIVEL DE CLASIFICACIÓN | L3: USO INTERNO (NC2) | P3: VERSIÓN | S3: 0.1
C6: REGISTRO ESTADÍSTICO DE ACCIDENTALIDAD
C8: 1. | D8: OBJETIVO
D9: Analizar el comportamiento y tendencia de la accidentalidad en la organización teniendo en cuenta al personal directo e indirecto, verificando el avance en la implementación del sistema de gestión de seguridad y salud en el trabajo teniendo en cuenta las tendencias de los Indicadores de gestión.
C11: 2. | D11: ALCANCE
D12: Las áreas involucradas en este proceso son: Personal Directo e indirecto
C14: 3. | D14: INDICADORES | O14: Jornada laboral
C15: 3.1. | D15: Accidentalidad | I15: K (Constante) | L15: 100 | O15: Reporte mensual
H17: MES | I17: Semanas del periodo | J17: Horas Laboradas / Semana | K17: No Trabaj. | L17: MENSUAL
L18: N° de AT | M18: HHT | N18: N° Días Perdidos | O18: N° de días cargados | P18: N° AT Mortales | Q18: Frecuencia de Accidentalidad | R18: Severidad de Accidentalidad | S18: ILI | T18: Proporción AT Mortales
H19: Ene | I19: =50/12 -> 4.1666667 | J19: 44 | K19: 1043 | L19: 0 | M19: =K19*J19*I19 -> 191216.67 | N19: 0 | O19: 0 | P19: 0 | Q19: =+((L19)/(K19))*($L$15) -> 0 | R19: =+((N19+O19)/(K19))*($L$15) -> 0 | S19: =+((Q19)*(R19))/(1000) -> 0 | T19: =+((P19)/(L19))*($L$15) -> #DIV/0!
H20: Feb | I20: =50/12 -> 4.1666667 | J20: 44 | K20: 1032 | L20: 0 | M20: =K20*J20*I20 -> 189200 | N20: 0 | O20: 0 | P20: 0 | Q20: =+((L20)/(K20))*($L$15) -> 0 | R20: =+((N20+O20)/(K20))*($L$15) -> 0 | S20: =+((Q20)*(R20))/(1000) -> 0 | T20: =+((P20)/(L20))*($L$15) -> #DIV/0!
H21: Mar | I21: =50/12 -> 4.1666667 | J21: 44 | K21: 1021 | L21: 0 | M21: =K21*J21*I21 -> 187183.33 | N21: 0 | O21: 0 | P21: 0 | Q21: =+((L21)/(K21))*($L$15) -> 0 | R21: =+((N21+O21)/(K21))*($L$15) -> 0 | S21: =+((Q21)*(R21))/(1000) -> 0 | T21: =+((P21)/(L21))*($L$15) -> #DIV/0!
H22: Abr | I22: =50/12 -> 4.1666667 | J22: 44 | K22: 1031 | L22: 0 | M22: =K22*J22*I22 -> 189016.67 | N22: 0 | O22: 0 | P22: 0 | Q22: =+((L22)/(K22))*($L$15) -> 0 | R22: =+((N22+O22)/(K22))*($L$15) -> 0 | S22: =+((Q22)*(R22))/(1000) -> 0 | T22: =+((P22)/(L22))*($L$15) -> #DIV/0!
H23: May | I23: =50/12 -> 4.1666667 | J23: 44 | K23: 1038 | L23: 0 | M23: =K23*J23*I23 -> 190300 | N23: 0 | O23: 0 | P23: 0 | Q23: =+((L23)/(K23))*($L$15) -> 0 | R23: =+((N23+O23)/(K23))*($L$15) -> 0 | S23: =+((Q23)*(R23))/(1000) -> 0 | T23: =+((P23)/(L23))*($L$15) -> #DIV/0!
H24: Jun | I24: =50/12 -> 4.1666667 | J24: 44 | K24: 1079 | L24: 1 | M24: =K24*J24*I24 -> 197816.67 | N24: 2 | O24: 0 | P24: 0 | Q24: =+((L24)/(K24))*($L$15) -> 0.092678406 | R24: =+((N24+O24)/(K24))*($L$15) -> 0.18535681 | S24: =+((Q24)*(R24))/(1000) -> 1.7178574e-05 | T24: =+((P24)/(L24))*($L$15) -> 0
H25: Jul | I25: =50/12 -> 4.1666667 | J25: 42 | K25: 995 | L25: 1 | M25: =K25*J25*I25 -> 174125 | N25: 3 | O25: 0 | P25: 0 | Q25: =+((L25)/(K25))*($L$15) -> 0.10050251 | R25: =+((N25+O25)/(K25))*($L$15) -> 0.30150754 | S25: =+((Q25)*(R25))/(1000) -> 3.0302265e-05 | T25: =+((P25)/(L25))*($L$15) -> 0
H26: Ago | I26: =50/12 -> 4.1666667 | J26: 42 | K26: 933 | L26: 0 | M26: =K26*J26*I26 -> 163275 | N26: 0 | O26: 0 | P26: 0 | Q26: =+((L26)/(K26))*($L$15) -> 0 | R26: =+((N26+O26)/(K26))*($L$15) -> 0 | S26: =+((Q26)*(R26))/(1000) -> 0 | T26: =+((P26)/(L26))*($L$15) -> #DIV/0!
H27: Sep | I27: =50/12 -> 4.1666667 | J27: 42 | K27: 929 | L27: 0 | M27: =K27*J27*I27 -> 162575 | N27: 0 | O27: 0 | P27: 0 | Q27: =+((L27)/(K27))*($L$15) -> 0 | R27: =+((N27+O27)/(K27))*($L$15) -> 0 | S27: =+((Q27)*(R27))/(1000) -> 0 | T27: =+((P27)/(L27))*($L$15) -> #DIV/0!
H28: Oct | I28: =50/12 -> 4.1666667 | J28: 42 | K28: 919 | L28: 0 | M28: =K28*J28*I28 -> 160825 | N28: 0 | O28: 0 | P28: 0 | Q28: =+((L28)/(K28))*($L$15) -> 0 | R28: =+((N28+O28)/(K28))*($L$15) -> 0 | S28: =+((Q28)*(R28))/(1000) -> 0 | T28: =+((P28)/(L28))*($L$15) -> #DIV/0!
H29: Nov | I29: =50/12 -> 4.1666667 | J29: 42 | K29: 950 | L29: 0 | M29: =K29*J29*I29 -> 166250 | N29: 0 | O29: 0 | P29: 0 | Q29: =+((L29)/(K29))*($L$15) -> 0 | R29: =+((N29+O29)/(K29))*($L$15) -> 0 | S29: =+((Q29)*(R29))/(1000) -> 0 | T29: =+((P29)/(L29))*($L$15) -> #DIV/0!
H30: Dic | I30: =50/12 -> 4.1666667 | J30: 42 | K30: 920 | L30: 0 | M30: =K30*J30*I30 -> 161000 | N30: 0 | O30: 0 | P30: 0 | Q30: =+((L30)/(K30))*($L$15) -> 0 | R30: =+((N30+O30)/(K30))*($L$15) -> 0 | S30: =+((Q30)*(R30))/(1000) -> 0 | T30: =+((P30)/(L30))*($L$15) -> #DIV/0!
I31: =SUM(I19:I30) -> 50 | J31: =AVERAGE(J19:J30) -> 43 | K31: =AVERAGE(K19:K30) -> 990.83333 | L31: =SUM(L19:L30) -> 2 | M31: =SUM(M19:M30) -> 2132783.3 | N31: =SUM(N19:N30) -> 5 | O31: =SUM(O19:O30) -> 0 | P31: =SUM(P19:P30) -> 0 | Q31: =+((L31)/(K31))*($L$15) -> 0.20185029 | R31: =+((N31+O31)/(K31))*($L$15) -> 0.50462574 | S31: =+((Q31)*(R31))/(1000) -> 0.00010185885 | T31: =+((P31)/(L31))*($L$15) -> 0

Sheet GRAFICA 2026
A1: PROCESOS ADMINISTRATIVOS / SEGURIDAD Y SALUD EN EL TRABAJO
A2: REGISTRO ESTADISTICO DE MORBILIDAD
A3: CODIGO | B3: RE-RH-40-SST | C3: NIVEL DE CLASIFICACION | E3: USO INTERNO (NC2) | G3: VERSION | I3: 0.0
A5: MORBILIDAD 2026
B9: AÑO | C9: No. EL
B10: 2012 | C10: 2
B11: 2013 | C11: 0
B12: 2014 | C12: 1 | D12: 1120
B13: 2015 | C13: 3 | D13: 1363
B14: 2016 | C14: 4 | D14: 1410
B15: 2017 | C15: 1 | D15: 1311
B16: 2018 | C16: 1 | D16: 1081
B17: 2019 | C17: 0
B18: 2020 | C18: 0
B19: 2021 | C19: 0
B20: 2022 | C20: 0
B21: 2023 | C21: 0
B22: 2024 | C22: 0
B23: 2025 | C23: 0
B24: 2026 | C24: 0
B25: TOTAL | C25: =SUM(C10:C23) -> 12 | D25: =AVERAGE(D12:D16) -> 1257
B30: DIAGNOSTICO | C30: No. EL
B31: EPICONDILITIS MEDIAL DERECHA | C31: 0
B32: SINDROME DE TUNEL CARPIANO | C32: 0
B33: TENOSINOVITIS RADIAL DE QUERVAIN DERECHA | C33: 0
B34: TRASTORNO MIXTO DE ANSIEDAD Y DEPRESION | C34: 0
B35: TOTAL | C35: =SUM(C31:C34) -> 0
B46: TIPO DE RIESGO | C46: No. EL
B47: BIOMECANICO | C47: 0
B48: PSICOSOCIAL | C48: 0
B49: TOTAL | C49: =SUM(C47:C48) -> 0
B55: DIAGNOSTICO | C55: DIAS DE INCAPACIDAD
B56: EPICONDILITIS MEDIAL DERECHA | C56: 0
B57: SINDROME DE TUNEL CARPIANO | C57: 0
B58: TRASTORNO MIXTO DE ANSIEDAD Y DEPRESION | C58: 0
B59: TENOSINOVITIS RADIAL DE QUERVAIN DERECHA | C59: 0
B60: TOTAL | C60: =SUM(C56:C59) -> 0
B66: No. EL | C66: 0
B67: No. de trabajadores promedio | C67: 1257
B68: PREVALENCIA | C68: =C66/C67 -> 0
B70: No. EL nuevas | C70: 1
B71: No. trabajadores prom | C71: 1257
B72: INCIDENCIA | C72: =C70/C71 -> 0.00079554495

Sheet 9,A
A1: INDICADORES DE AUSENTISMO 2026
M2: Etiquetas de fila | N2: Suma de N° de eventos por incapacidad
A3: K constante | B3: 100 | M3: Ene | N3: 94
A4: MES | B4: Semanas del periodo | C4: Horas Laboradas / Semana | D4: No Trabaj. | E4: N° de eventos por incapacidad | F4: HHT | G4: N° Días Perdidos | H4: Indice Frecuencia Ausentismo | I4: Indice Severidad | J4: ILI | K4: Porcentaje Tiempo perdido | M4: Feb | N4: 137
A5: Ene | B5: =50/12 -> 4.1666667 | C5: 44 | D5: 870 | E5: 94 | F5: =D5*C5*B5 -> 159500 | G5: 653 | H5: =+((E5)/(D5))*($B$3) -> 10.804598 | I5: =+((G5)/(D5*30))*($B$3) -> 2.5019157 | J5: =+((H5)*(I5))/(1000) -> 0.027032193 | K5: =+((G5*8)/(F5)) -> 0.032752351 | M5: Mar | N5: 108
A6: Feb | B6: =50/12 -> 4.1666667 | C6: 44 | D6: 846 | E6: 137 | F6: =D6*C6*B6 -> 155100 | G6: 572 | H6: =+((E6)/(D6))*($B$3) -> 16.193853 | I6: =+((G6)/(D6*30))*($B$3) -> 2.2537431 | J6: =+((H6)*(I6))/(1000) -> 0.036496786 | K6: =+((G6*8)/(F6)) -> 0.029503546 | M6: Abr | N6: 101
A7: Mar | B7: =50/12 -> 4.1666667 | C7: 44 | D7: 823 | E7: 108 | F7: =D7*C7*B7 -> 150883.33 | G7: 856 | H7: =+((E7)/(D7))*($B$3) -> 13.122722 | I7: =+((G7)/(D7*30))*($B$3) -> 3.4669907 | J7: =+((H7)*(I7))/(1000) -> 0.045496354 | K7: =+((G7*8)/(F7)) -> 0.04538606 | M7: May | N7: 100
A8: Abr | B8: =50/12 -> 4.1666667 | C8: 44 | D8: 816 | E8: 101 | F8: =D8*C8*B8 -> 149600 | G8: 606 | H8: =+((E8)/(D8))*($B$3) -> 12.377451 | I8: =+((G8)/(D8*30))*($B$3) -> 2.4754902 | J8: =+((H8)*(I8))/(1000) -> 0.030640259 | K8: =+((G8*8)/(F8)) -> 0.032406417 | M8: Jun | N8: 94
A9: May | B9: =50/12 -> 4.1666667 | C9: 44 | D9: 811 | E9: 100 | F9: =D9*C9*B9 -> 148683.33 | G9: 998 | H9: =+((E9)/(D9))*($B$3) -> 12.330456 | I9: =+((G9)/(D9*30))*($B$3) -> 4.1019318 | J9: =+((H9)*(I9))/(1000) -> 0.05057869 | K9: =+((G9*8)/(F9)) -> 0.053698016 | M9: Jul | N9: 15
A10: Jun | B10: =50/12 -> 4.1666667 | C10: 44 | D10: 797 | E10: 94 | F10: =D10*C10*B10 -> 146116.67 | G10: 593 | H10: =+((E10)/(D10))*($B$3) -> 11.794228 | I10: =+((G10)/(D10*30))*($B$3) -> 2.4801338 | J10: =+((H10)*(I10))/(1000) -> 0.029251265 | K10: =+((G10*8)/(F10)) -> 0.032467207 | M10: Ago | N10: 0
A11: Jul | B11: =50/12 -> 4.1666667 | C11: 42 | D11: 792 | E11: 15 | F11: =D11*C11*B11 -> 138600 | G11: 80 | H11: =+((E11)/(D11))*($B$3) -> 1.8939394 | I11: =+((G11)/(D11*30))*($B$3) -> 0.33670034 | J11: =+((H11)*(I11))/(1000) -> 0.00063769003 | K11: =+((G11*8)/(F11)) -> 0.0046176046 | M11: Sep | N11: 0
A12: Ago | B12: =50/12 -> 4.1666667 | C12: 42 | D12: 0 | E12: 0 | F12: =D12*C12*B12 -> 0 | G12: 0 | H12: =+((E12)/(D12))*($B$3) -> #DIV/0! | I12: =+((G12)/(D12*30))*($B$3) -> #DIV/0! | J12: =+((H12)*(I12))/(1000) -> #DIV/0! | K12: =+((G12*8)/(F12)) -> #DIV/0! | M12: Oct | N12: 0
A13: Sep | B13: =50/12 -> 4.1666667 | C13: 42 | D13: 0 | E13: 0 | F13: =D13*C13*B13 -> 0 | G13: 0 | H13: =+((E13)/(D13))*($B$3) -> #DIV/0! | I13: =+((G13)/(D13*30))*($B$3) -> #DIV/0! | J13: =+((H13)*(I13))/(1000) -> #DIV/0! | K13: =+((G13*8)/(F13)) -> #DIV/0! | M13: Nov | N13: 0
A14: Oct | B14: =50/12 -> 4.1666667 | C14: 42 | D14: 0 | E14: 0 | F14: =D14*C14*B14 -> 0 | G14: 0 | H14: =+((E14)/(D14))*($B$3) -> #DIV/0! | I14: =+((G14)/(D14*30))*($B$3) -> #DIV/0! | J14: =+((H14)*(I14))/(1000) -> #DIV/0! | K14: =+((G14*8)/(F14)) -> #DIV/0! | M14: Dic | N14: 0
A15: Nov | B15: =50/12 -> 4.1666667 | C15: 42 | D15: 0 | E15: 0 | F15: =D15*C15*B15 -> 0 | G15: 0 | H15: =+((E15)/(D15))*($B$3) -> #DIV/0! | I15: =+((G15)/(D15*30))*($B$3) -> #DIV/0! | J15: =+((H15)*(I15))/(1000) -> #DIV/0! | K15: =+((G15*8)/(F15)) -> #DIV/0! | M15: Total general | N15: 649
A16: Dic | B16: =50/12 -> 4.1666667 | C16: 42 | D16: 0 | E16: 0 | F16: =D16*C16*B16 -> 0 | G16: 0 | H16: =+((E16)/(D16))*($B$3) -> #DIV/0! | I16: =+((G16)/(D16*30))*($B$3) -> #DIV/0! | J16: =+((H16)*(I16))/(1000) -> #DIV/0! | K16: =+((G16*8)/(F16)) -> #DIV/0!
A17: TOTAL | B17: =SUM(B5:B16) -> 50 | C17: =SUM(C5:C16) -> 516 | D17: =AVERAGE(D5:D16) -> 479.58333 | E17: =SUM(E5:E16) -> 649 | F17: =SUM(F5:F16) -> 1048483.3 | G17: =SUM(G5:G16) -> 4358 | H17: =+((E17)/(D17))*($B$3) -> 135.3258 | I17: =+((G17)/(D17*360))*($B$3) -> 2.5241819 | J17: =+((H17)*(I17))/(1000) -> 0.34158694 | K17: =+((G17*8)/(F17)) -> 0.03325184

Sheet 9,
A1: PROCESOS ADMINISTRATIVOS / SEGURIDAD Y SALUD EN EL TRABAJO
A2: INDICADORES DE GESTION
A3: CODIGO | C3: RE-RH-37-SST | D3: NIVEL DE CLASIFICACIÓN | G3: USO INTERNO (NC2) | K3: VERSION | L3: 0.2
A5: NOMBRE DEL INDICADOR | E5: ='Tablero indicadores 2026'!B56 -> 9. Indice de Frecuecia de Ausentismo
A7: PROCESO | E7: ='Tablero indicadores 2026'!A1 -> PROCESOS ADMINISTRATIVOS / SEGURIDAD Y SALUD EN EL TRABAJO | R7: META | T7: ='Tablero indicadores 2026'!L37 -> 0.9
A9: FORMULA | E9: IFA=N° DE EVENTOS DE AUSENCIA POR CAUSA DE SALUD ULTIMO AÑO / No, DE TRABAJADORES PROMEDIO AÑO *100 | R9: FRECUENCIA DE MEDICIÓN | T9: ='Tablero indicadores 2026'!H56 -> Anual
A11: UNIDAD | E11: ='Tablero indicadores 2026'!I54 -> Número | R11: TIPO INDICADOR | T11: ='Tablero indicadores 2026'!A36 -> RESULTADO
A13: RESPONSABLE MEDICIÓN | E13: ='Tablero indicadores 2026'!G7 -> Líder Funcional SG SST | R13: VIGENCIA | T13: 2026
A17: PARAMETROS | E17: Enero | F17: Febrero | G17: Marzo | H17: Abril | I17: Mayo | J17: Junio | K17: Julio | L17: Agosto | M17: Septiembre | N17: Octubre | O17: Noviembre | P17: Diciembre | R17: OBSERVACIONES: IFA=N° DE EVENTOS DE AUSENCIA POR CAUSA DE SALUD ULTIMO AÑO / No, DE TRABAJADORES PROMEDIO AÑO *100
A19: Numerador | E19: 136 | F19: 161 | G19: 195 | H19: 160 | I19: 153 | J19: 150 | K19: 175 | L19: 116 | M19: 167 | N19: 154 | O19: 120
A20: Denominador | E20: 1043 | F20: 10432 | G20: 1021 | H20: 1031 | I20: 1038 | J20: 1077 | K20: 995 | L20: 933 | M20: 929 | N20: 919 | O20: 950 | P20: 920
A22: Rango Mayor (Meta) | E22: 0 | F22: 0 | G22: 0 | H22: 0 | I22: 0 | J22: 0 | K22: 0 | L22: 0 | M22: 0 | N22: 0 | O22: 0 | P22: 0 | Q22: =#REF! -> #REF!
A24: Rango Menor | E24: 1 | F24: 1 | G24: 1 | H24: 1 | I24: 1 | J24: 1 | K24: 1 | L24: 1 | M24: 1 | N24: 1 | O24: 1 | P24: 1
A26: Avance | E26: =E19/E20 -> 0.1303931 | F26: =F19/F20 -> 0.015433282 | G26: =G19/G20 -> 0.19098923 | H26: =H19/H20 -> 0.15518914 | I26: =I19/I20 -> 0.14739884 | J26: =J19/J20 -> 0.13927577 | K26: =K19/K20 -> 0.1758794 | L26: =L19/L20 -> 0.12433012 | ... P26: =P19/P20 -> 0
C32: ANÁLISIS | I32: ACCIÓN A SEGUIR
C33: Medir el ausentismo por incapacidad de origen laboral y común, como mínimo una (1) vez al mes y realizar la clasificación del origen del peligro/riesgo que lo generó (físicos, ergonómicos, o biomecánicos, químicos, de seguridad, públicos, psicosociales, entre otros). | I33: Solicitar los resultados de la medición para lo corrido del año y/o el año inmediatamente anterior y constatar el comportamiento del ausentismo y la relación del evento con los peligros/riesgos.
C34: FECHA SEGUIMIENTO | I34: SEGUIMIENTO A LA IMPLEMENTACIÓN
C35: 46052 | F35: Revisión del registro estadistico | I35: Se realiza la actualización de analisis estadisticos del ausentismo
C36: 46080 | F36: Revisión del registro estadistico | I36: Se realiza la actualización de analisis estadisticos del ausentismo
C37: 46112 | F37: Revisión del registro estadistico | I37: Se realiza la actualización de analisis estadisticos del ausentismo
C38: 46142 | F38: Revisión del registro estadistico | I38: Se realiza la actualización de analisis estadisticos del ausentismo
C39: 46171 | F39: Revisión del registro estadistico | I39: Se realiza la actualización de analisis estadisticos del ausentismo
C40: 46203 | F40: Revisión del registro estadistico | I40: Se realiza la actualización de analisis estadisticos del ausentismo
C41: 46234 | F41: Revisión del registro estadistico | I41: Se realiza la actualización de analisis estadisticos del ausentismo
C42: 46265 | F42: Revisión del registro estadistico | I42: Se realiza la actualización de analisis estadisticos del ausentismo
C43: 46295 | F43: Revisión del registro estadistico | I43: Se realiza la actualización de analisis estadisticos del ausentismo
C44: 46325 | F44: Revisión del registro estadistico | I44: Se realiza la actualización de analisis estadisticos del ausentismo
C45: 46356 | F45: Revisión del registro estadistico | I45: Se realiza la actualización de analisis estadisticos del ausentismo
C46: 46360 | F46: Revisión del registro estadistico | I46: Se realiza la actualización de analisis estadisticos del ausentismo
C47: RESPONSABLE
C48: ='Tablero indicadores 2026'!G8 -> Líder Funcional SG SST

Sheet 9,1
A1: PROCESOS ADMINISTRATIVOS / SEGURIDAD Y SALUD EN EL TRABAJO
A2: INDICADORES DE GESTION
A3: CODIGO | C3: RE-RH-37-SST | D3: NIVEL DE CLASIFICACIÓN | G3: USO INTERNO (NC2) | K3: VERSION | L3: 0.2
A5: NOMBRE DEL INDICADOR | E5: ='Tablero indicadores 2026'!B57 -> 9.1. Ausentismo por causa médica (Resolución 312 de 2019)
A7: PROCESO | E7: ='Tablero indicadores 2026'!A1 -> PROCESOS ADMINISTRATIVOS / SEGURIDAD Y SALUD EN EL TRABAJO | S7: META | U7: ='Tablero indicadores 2026'!L37 -> 0.9
A9: FORMULA | E9: ISA=N° DIAS DE AUSENCIA POR INCAPACIDAD LABORAL O COMÚN / N° DE DIAS DE TRABAJO PROGRAMADOS EN EL MES * 100 | S9: FRECUENCIA DE MEDICIÓN | U9: ='Tablero indicadores 2026'!H56 -> Anual
A11: UNIDAD | E11: ='Tablero indicadores 2026'!I57 -> Porcentaje | S11: TIPO INDICADOR | U11: ='Tablero indicadores 2026'!A36 -> RESULTADO
A13: RESPONSABLE MEDICIÓN | E13: ='Tablero indicadores 2026'!G7 -> Líder Funcional SG SST | S13: VIGENCIA | U13: 2026
A17: PARAMETROS | E17: Enero | F17: Febrero | G17: Marzo | H17: Abril | I17: Mayo | J17: Junio | K17: Julio | L17: Agosto | M17: Septiembre | N17: Octubre | O17: Noviembre | P17: Diciembre | Q17: Promedio | S17: OBSERVACIONES: ISA=N° DIAS DE AUSENCIA POR INCAPACIDAD LABORAL O COMÚN / N° DE DIAS DE TRABAJO PROGRAMADOS EN EL MES * 100
A19: Numerador | E19: 0 | F19: 0 | G19: 0 | H19: 0 | I19: 0 | J19: 0 | K19: 0 | L19: 0 | M19: 0 | N19: 0 | O19: 0 | P19: 0
A20: Denominador | E20: 10413 | F20: 1032 | G20: 1021 | H20: 1031 | I20: 1038 | J20: 1077 | K20: 995 | L20: 933 | M20: 929 | N20: 919 | O20: 950 | P20: 920
A22: Rango Mayor (Meta) | E22: 0 | F22: 0 | G22: 0 | H22: 0 | I22: 0 | J22: 0 | K22: 0 | L22: 0 | M22: 0 | N22: 0 | O22: 0 | P22: 0 | Q22: 0 | R22: =#REF! -> #REF!
A24: Rango Menor | E24: 1 | F24: 1 | G24: 1 | H24: 1 | I24: 1 | J24: 1 | K24: 1 | L24: 1 | M24: 1 | N24: 1 | O24: 1 | P24: 1 | Q24: 1
A26: Avance | E26: =E19/E20 -> 0 | F26: =F19/F20 -> 0 | G26: =G19/G20 -> 0 | H26: =H19/H20 -> 0 | I26: =I19/I20 -> 0 | J26: =J19/J20 -> 0 | K26: =K19/K20 -> 0 | L26: =L19/L20 -> 0 | ... Q26: =Q19/Q20 -> #DIV/0!
C32: ANÁLISIS | I32: ACCIÓN A SEGUIR
C33: Medir el ausentismo por incapacidad de origen laboral y común, como mínimo una (1) vez al mes y realizar la clasificación del origen del peligro/riesgo que lo generó (físicos, ergonómicos, o biomecánicos, químicos, de seguridad, públicos, psicosociales, entre otros). | I33: Solicitar los resultados de la medición para lo corrido del año y/o el año inmediatamente anterior y constatar el comportamiento del ausentismo y la relación del evento con los peligros/riesgos.
C34: FECHA SEGUIMIENTO | I34: SEGUIMIENTO A LA IMPLEMENTACIÓN
C35: 46052 | F35: Revisión del registro estadistico | I35: Se realiza la actualización de analisis estadisticos del ausentismo
C36: 46080 | F36: Revisión del registro estadistico | I36: Se realiza la actualización de analisis estadisticos del ausentismo
C37: 46112 | F37: Revisión del registro estadistico | I37: Se realiza la actualización de analisis estadisticos del ausentismo
C38: 46142 | F38: Revisión del registro estadistico | I38: Se realiza la actualización de analisis estadisticos del ausentismo
C39: 46171 | F39: Revisión del registro estadistico | I39: Se realiza la actualización de analisis estadisticos del ausentismo
C40: 46203 | F40: Revisión del registro estadistico | I40: Se realiza la actualización de analisis estadisticos del ausentismo
C41: 46234 | F41: Revisión del registro estadistico | I41: Se realiza la actualización de analisis estadisticos del ausentismo
C42: 46265 | F42: Revisión del registro estadistico | I42: Se realiza la actualización de analisis estadisticos del ausentismo
C43: 46295 | F43: Revisión del registro estadistico | I43: Se realiza la actualización de analisis estadisticos del ausentismo
C44: 46325 | F44: Revisión del registro estadistico | I44: Se realiza la actualización de analisis estadisticos del ausentismo
C45: 46356 | F45: Revisión del registro estadistico | I45: Se realiza la actualización de analisis estadisticos del ausentismo
C46: 46360
C47: RESPONSABLE
C48: ='Tablero indicadores 2026'!G8 -> Líder Funcional SG SST

Sheet 9,2
A1: PROCESOS ADMINISTRATIVOS / SEGURIDAD Y SALUD EN EL TRABAJO
A2: INDICADORES DE GESTION
A3: CODIGO | C3: RE-RH-37-SST | D3: NIVEL DE CLASIFICACIÓN | G3: USO INTERNO (NC2) | K3: VERSION | L3: 0.2
A5: NOMBRE DEL INDICADOR | E5: ='Tablero indicadores 2026'!B58 -> 9.2. Porcentaje de Tiempo Perdido
A7: PROCESO | E7: ='Tablero indicadores 2026'!A1 -> PROCESOS ADMINISTRATIVOS / SEGURIDAD Y SALUD EN EL TRABAJO | S7: META | U7: ='Tablero indicadores 2026'!L37 -> 0.9
A9: FORMULA | E9: %TP=N° DIAS U HORAS PERDIDAS EN EL AÑO *100 / N° DIAS U HORAS PROGRAMADAS EN EL PERIODO | S9: FRECUENCIA DE MEDICIÓN | U9: ='Tablero indicadores 2026'!H58 -> Anual
A11: UNIDAD | E11: ='Tablero indicadores 2026'!I57 -> Porcentaje | S11: TIPO INDICADOR | U11: ='Tablero indicadores 2026'!A36 -> RESULTADO
A13: RESPONSABLE MEDICIÓN | E13: ='Tablero indicadores 2026'!G7 -> Líder Funcional SG SST | S13: VIGENCIA | U13: 2026
A17: PARAMETROS | E17: Enero | F17: Febrero | G17: Marzo | H17: Abril | I17: Mayo | J17: Junio | K17: Julio | L17: Agosto | M17: Septiembre | N17: Octubre | O17: Noviembre | P17: Diciembre | Q17: Promedio | S17: OBSERVACIONES: %TP=N° DIAS U HORAS PERDIDAS EN EL AÑO *100 / N° DIAS U HORAS PROGRAMADAS EN EL PERIODO
A19: Numerador | P19: ='9,A'!G17*8 -> 34864
A20: Denominador | P20: ='9,A'!F17 -> 1048483.3
A22: Rango Mayor (Meta) | P22: 0 | Q22: 0 | R22: =#REF! -> #REF!
A24: Rango Menor | P24: 1 | Q24: 1
A26: Avance | P26: =P19/P20 -> 0.03325184 | Q26: =Q19/Q20 -> #DIV/0!
C32: ANÁLISIS | I32: ACCIÓN A SEGUIR
C33: Medir la frecuencia de los accidentes como mínimo una (1) vez al mes y realizar la clasificación del origen del peligro/riesgo que los generó (físicos, de químicos, biológicos, seguridad, públicos, psicosociales, entre otros.). | I33: Solicitar los resultados de la medición para lo corrido del año y/o el año inmediatamente anterior y constatar el comportamiento de la frecuencia de los accidentes y la relación del evento con los peligros/riesgos identificados.
C34: FECHA SEGUIMIENTO | I34: SEGUIMIENTO A LA IMPLEMENTACIÓN
C35: 46052 | F35: Revisión del registro estadistico | I35: Se realiza la actualización de analisis estadisticos del ausentismo
C36: 46080 | F36: Revisión del registro estadistico | I36: Se realiza la actualización de analisis estadisticos del ausentismo
C37: 46112 | F37: Revisión del registro estadistico | I37: Se realiza la actualización de analisis estadisticos del ausentismo
C38: 46142 | F38: Revisión del registro estadistico | I38: Se realiza la actualización de analisis estadisticos del ausentismo
C39: 46171 | F39: Revisión del registro estadistico | I39: Se realiza la actualización de analisis estadisticos del ausentismo
C40: 46203 | F40: Revisión del registro estadistico | I40: Se realiza la actualización de analisis estadisticos del ausentismo
C41: 46234 | F41: Revisión del registro estadistico | I41: Se realiza la actualización de analisis estadisticos del ausentismo
C42: 46265 | F42: Revisión del registro estadistico | I42: Se realiza la actualización de analisis estadisticos del ausentismo
C43: 46295 | F43: Revisión del registro estadistico | I43: Se realiza la actualización de analisis estadisticos del ausentismo
C44: 46325 | F44: Revisión del registro estadistico | I44: Se realiza la actualización de analisis estadisticos del ausentismo
C45: 46356 | F45: Revisión del registro estadistico | I45: Se realiza la actualización de analisis estadisticos del ausentismo
C46: 46360
C47: RESPONSABLE
C48: ='Tablero indicadores 2026'!G8 -> Líder Funcional SG SST

Sheet 10,
A1: PROCESOS ADMINISTRATIVOS / SEGURIDAD Y SALUD EN EL TRABAJO
A2: INDICADORES DE GESTION
A3: CODIGO | C3: RE-RH-37-SST | D3: NIVEL DE CLASIFICACIÓN | G3: USO INTERNO (NC2) | K3: VERSION | L3: 0.2
A5: NOMBRE DEL INDICADOR | E5: ='Tablero indicadores 2026'!B59 -> 10. Medidas de control en los riesgos y peligros priorizados
A7: PROCESO | E7: ='Tablero indicadores 2026'!A1 -> PROCESOS ADMINISTRATIVOS / SEGURIDAD Y SALUD EN EL TRABAJO | R7: META | T7: ='Tablero indicadores 2026'!L37 -> 0.9
A9: FORMULA | E9: No. De medidas de control de los peligros y riesgos realizadas /No. De medidas de control de los peligros y riesgos establecidas *100 | R9: FRECUENCIA DE MEDICIÓN | T9: ='Tablero indicadores 2026'!H58 -> Anual
A11: UNIDAD | E11: ='Tablero indicadores 2026'!I57 -> Porcentaje | R11: TIPO INDICADOR | T11: ='Tablero indicadores 2026'!A36 -> RESULTADO
A13: RESPONSABLE MEDICIÓN | E13: ='Tablero indicadores 2026'!G7 -> Líder Funcional SG SST | R13: VIGENCIA | T13: 2026
A17: PARAMETROS | E17: Enero | F17: Febrero | G17: Marzo | H17: Abril | I17: Mayo | J17: Junio | K17: Julio | L17: Agosto | M17: Septiembre | N17: Octubre | O17: Noviembre | P17: Diciembre | R17: OBSERVACIONES: No. De medidas de control de los peligros y riesgos realizadas /No. De medidas de control de los peligros y riesgos establecidas *100
A19: Numerador
A20: Denominador
A22: Rango Mayor (Meta) | P22: 0 | Q22: =#REF! -> #REF!
A24: Rango Menor | P24: 1
A26: Avance | P26: =P19/P20 -> #DIV/0!
C32: ANÁLISIS | I32: ACCIÓN A SEGUIR
C33: Ejecutar las medidas de prevención y control con base en el resultado de la identificación de peligros, la evaluación y valoración de los riesgos (físicos, ergonómicos, biológicos, químicos, de seguridad, públicos, psicosociales, entre otros), incluidos los prioritarios y estas se ejecutan acorde con el esquema de jerarquización, de ser factible priorizar la intervención en la fuente y en el medio. | I33: _Solicitar evidencias de la ejecución de las medidas de prevención y control, de acuerdo con el esquema de jerarquización y la identificación de los peligros, la evaluación y valoración de los riesgos realizada. _Constatar que estas medidas se encuentran programadas en el plan anual de trabajo. _Verificar que efectivamente se dio prioridad a las medidas de prevención y control frente a los peligros/riesgos identificados como prioritarios.
C34: FECHA SEGUIMIENTO | I34: SEGUIMIENTO A LA IMPLEMENTACIÓN
C35: 46358 | F35: Seguimiento a las medidas de control | I35: Verificar el seguimiento a la medida de control
C36: RESPONSABLE
C37: ='Tablero indicadores 2026'!G8 -> Líder Funcional SG SST

Sheet 11,
A1: PROCESOS ADMINISTRATIVOS / SEGURIDAD Y SALUD EN EL TRABAJO
A2: INDICADORES DE GESTION
A3: CODIGO | C3: RE-RH-37-SST | D3: NIVEL DE CLASIFICACIÓN | G3: USO INTERNO (NC2) | K3: VERSION | L3: 0.2
A5: NOMBRE DEL INDICADOR | E5: ='Tablero indicadores 2026'!B60 -> 11. Mediciones ambientales
A7: PROCESO | E7: ='Tablero indicadores 2026'!A1 -> PROCESOS ADMINISTRATIVOS / SEGURIDAD Y SALUD EN EL TRABAJO | R7: META | T7: ='Tablero indicadores 2026'!L37 -> 0.9
A9: FORMULA | E9: (No. RECOMENDACIONES ADOPTADAS DE LAS MEDICIONES / No. RECOMENDACIONES EMITIDAS)*100 | R9: FRECUENCIA DE MEDICIÓN | T9: ='Tablero indicadores 2026'!H60 -> Semestral
A11: UNIDAD | E11: ='Tablero indicadores 2026'!I57 -> Porcentaje | R11: TIPO INDICADOR | T11: ='Tablero indicadores 2026'!A36 -> RESULTADO
A13: RESPONSABLE MEDICIÓN | E13: ='Tablero indicadores 2026'!G7 -> Líder Funcional SG SST | R13: VIGENCIA | T13: 2026
A17: PARAMETROS | E17: Enero | F17: Febrero | G17: Marzo | H17: Abril | I17: Mayo | J17: Junio | K17: Julio | L17: Agosto | M17: Septiembre | N17: Octubre | O17: Noviembre | P17: Diciembre | R17: OBSERVACIONES: No. De medidas de control de los peligros y riesgos realizadas /No. De medidas de control de los peligros y riesgos establecidas *100
A19: Numerador
A20: Denominador | L20: 1 | P20: 1
A22: Rango Mayor (Meta) | L22: 0 | P22: 0 | Q22: =#REF! -> #REF!
A24: Rango Menor | L24: 1 | P24: 1
A26: Avance | L26: =L19/L20 -> 0 | P26: =P19/P20 -> 0
C32: ANÁLISIS | I32: ACCIÓN A SEGUIR
C33: Realizar mediciones ambientales de los riesgos prioritarios, provenientes de peligros químicos, físicos y/o biológicos. | I33: Verificar los soportes documentales de las mediciones ambientales realizadas y la remisión de estos resultados al Comité Paritario de Seguridad y Salud en el Trabajo.
C34: FECHA SEGUIMIENTO | I34: SEGUIMIENTO A LA IMPLEMENTACIÓN
C35: 46203 | F35: Revisión de realización de mediciones | I35: Realizar natura
C36: 46360 | F36: Revisión de realización de mediciones
C37: RESPONSABLE
C38: ='Tablero indicadores 2026'!G8 -> Líder Funcional SG SST

Sheet Pesv 
D1: PLAN ESTRATEGICO DE SEGURIDAD VIAL | J1: Código | K1: Versión 0
J2: Versión
D3: MATRIZ DE OBJETIVOS METAS E INDICADORES | M3: Casillas con números azules formuladas
K5: # de Kms recorridos
K7: # Dias trabajados
K9: # de Trabajadores
B11: # | C11: OBJETIVO DEL INDICADOR | D11: INDICADOR | E11: FORMULA | G11: META 2024 | H11: UNIDAD DE MEDIDA | I11: PERIODO O FRECUENCIA | J11: MAYOR ES MEJOR | K11: RESPONSABLE | L11: ENERO | M11: FEBRERO | N11: MARZO | O11: ABRIL | P11: MAYO | Q11: JUNIO | R11: JULIO | S11: AGOSTO | T11: SEPTIEMBRE | U11: OCTUBRE | V11: NOVIEMBRE | W11: DICIEMBRE
B12: 1 | C12: Monitorear y reducir la frecuencia y gravedad de los accidentes de tráfico, proporcionando datos esenciales para la implementación de medidas de seguridad vial más efectivas y la promoción de prácticas de conducción más seguras | D12: Tasa de siniestros viales por nivel de perdida TSV(n) | E12: Número de siniestros viales x trimestre * 1'000.000 | G12: 0 | H12: % | I12: Trimestral y acomulado año | J12: MEJOR | K12: LIDER FUNCIONAL DE SG SST | L12: ='[72]Matriz objetivos metas indi'!$L$12 -> 0 | M12: ='[72]Matriz objetivos metas indi'!$L$12 -> 0 | N12: ='[72]Matriz objetivos metas indi'!$L$12 -> 0 | O12: ='[72]Matriz objetivos metas indi'!$L$12 -> 0 | P12: ='[72]Matriz objetivos metas indi'!$L$12 -> 0 | Q12: ='[72]Matriz objetivos metas indi'!$L$12 -> 0 | R12: ='[72]Matriz objetivos metas indi'!$L$12 -> 0 | S12: ='[72]Matriz objetivos metas indi'!$L$12 -> 0 | ... W12: ='[72]Matriz objetivos metas indi'!$L$12 -> 0
E13: Número de kilometros recorridos por trimestre por toda la flota de vehiculos | J13: MEJOR | L13: 0 | M13: 0 | N13: 6786 | O13: 0 | P13: 0 | Q13: 9422 | R13: 0 | S13: 0 | T13: 13560 | U13: 0 | V13: 0 | W13: 40119
B14: 2 | C14: NO APLICA | D14: Costo siniestros viales por nivel de perdida $SV(n) | E14: Costos directos de siniestros viales x trimestre con nivel de perdida + Costos indirectos de siniestros viales x trimestre con nivel de perdida | G14: 0 | H14: % | I14: Trimestral y acomulado año | J14: MEJOR | K14: NO APLICA
J15: MEJOR
B16: 3 | C16: Verificar la cantidfad de riesgos identificados al inicio del año vs el final del año | D16: Riesgos de seguridad vial identificados RSVI | E16: Cantidad de riesgos identificados al final de año - cantidad de riesgos identificados al inicio de año | G16: 1 | H16: % | I16: Anual | J16: MEJOR | K16: LIDER FUNCIONAL DE SG SST | L16: 35
